Workbook

Sheet Instrucciones
B2: Tablero de proyectos — Websy
C4: Archivo de trabajo de Julio (administrador del área). Súbelo a Google Drive y ábrelo con Google Sheets: tiene que ser un solo link en vivo, nunca un archivo que se manda por correo. Actualizado el 30/07/2026: columnas Código, Prioridad, Plataforma y Avance de diseño, buscador de clientes y hojas de equipo editables.
B6: Cómo se usa
B7: 1 | C7: Empieza por la hoja PROYECTOS: un cliente por fila. Arriba de todo hay una BARRA DE BÚSQUEDA (celda celeste): escribe parte del nombre del cliente o su código y las filas que coinciden se resaltan. Bórrala para volver a ver todo.
B8: 2 | C8: Llena solo las celdas AMARILLAS. Las BLANCAS se calculan solas — si escribes encima, rompes la fórmula.
B9: 3 | C9: CÓDIGO es el número de cada empresa (022, 059, 065b…) y la hoja PROYECTOS va ordenada por ese número; los clientes sin código quedan al final. PRIORIDAD DISEÑO (JC) es solo la cola de Juan Carlos: 1 es el primero que diseña, y así se ordena su hoja. GRUPO se calcula solo: A = listo para producir, B = trabado por el cliente, C = no pagó o no responde.
B10: 4 | C10: PLATAFORMA (Shopify / WooCommerce / Personalizado) es lista desplegable; lo que siga en «Por definir» se pinta naranja hasta que lo completes. DEV y DISEÑADOR son distintos: Juan Carlos es el diseñador, va en TODOS los proyectos y no se cuenta como dev; los «Sin asignar» en rojo necesitan developer.
B11: 5 | C11: AVANCE DE DISEÑO (JC) es exclusiva de Juan Carlos: la marca él en su hoja y aquí se ve sola. Va de «Falta material» → «Material completo — iniciar diseño» → «Diseño en curso» → «Avance listo para presentar» → «En revisión del cliente» → «Diseño finalizado». Los devs marcan lo suyo en «Aviso del dev».
B12: 6 | C12: La hoja TABLERO se dibuja sola con lo que escribes en PROYECTOS: captura y mándasela a Luis los viernes. CHECKLISTS y REGLAS no se editan, son para consultar.
B13: Leyenda de colores
B14: Amarillo | C14: Lo llenas tú a mano.
B15: Blanco | C15: Se calcula solo. No escribir.
B16: Verde | C16: Todo en orden.
B17: Naranja | C17: Requiere que lo persigas.
B18: Rojo | C18: Urgente o congelado.
B19: Lo más importante
C20: Este archivo no obliga a nadie a nada. Las tres compuertas y los límites de trabajo los haces cumplir tú, diciendo que no. Léelas en la hoja REGLAS antes de empezar.

Sheet Proyectos
A1: BUSCAR CLIENTE → | F1: =IF($C$1="","",COUNTIF($C$4:$C$60,"*"&$C$1&"*")&" coincidencia(s)") | H1: Escribe aquí parte del nombre del cliente (o su código) y las filas que coinciden se pintan de celeste. Borra la celda para volver a ver todo. Esta hoja va ordenada por CÓDIGO; la columna Prioridad diseño solo manda la cola de Juan Carlos.
A3: Prioridad diseño (JC) | B3: Código | C3: Cliente | D3: Correo del cliente | E3: Tipo | F3: Plataforma | G3: Estado | H3: Dev | I3: Diseñador | J3: Avance de diseño (JC) | K3: Grupo | L3: Acción de hoy | M3: Pagó 50% | N3: Pagó 30% | O3: Pagó 20% | P3: Material de diseño | Q3: Plantilla productos | R3: Total productos | S3: Imágenes de Productos | T3: Cargados | U3: % cargado | V3: Qué falta exactamente | W3: Últ. respuesta | X3: Días sin responder | Y3: Notas | Z3: Aviso del dev (auto) | AA3: Nota del dev (auto) | AB3: Nota de diseño (auto)
B4: 012 | C4: LCH Graphic Equipment | E4: E-commerce | F4: Por definir | G4: Cerrado | H4: Luis | I4: Juan Carlos | J4: =IFERROR(INDEX('Juan Carlos'!$P:$P,MATCH($C4,'Juan Carlos'!$A:$A,0))&"","") | K4: =IF($C4="","",IF($M4<>"Sí","C",IF($P4="Completo","A","B"))) -> B | L4: =IF($C4="","",IF($G4="Congelado","Congelado — mensaje cada 15 días",IF(N($X4)>15,"CONGELAR HOY",IF($M4<>"Sí","COBRAR EL 50%",IF($P4<>"Completo","PERSEGUIR MATERIAL",IF(AND($G4="Desarrollo",$N4<>"Sí"),"COBRAR EL 30%",IF(AND($G4="QA + entrega",$O4<>"Sí"),"COBRAR EL 20%",IF($G4="Cola","Listo para asignar","Al día")))))))) -> CONGELAR HOY | M4: Sí | N4: Sí | O4: No | P4: Incompleto | Q4: Recibida y validada | U4: =IF(N($R4)=0,"",$T4/$R4) | V4: Nada — en revisión y ajustes de contenido post-entrega | W4: 46174 | X4: =IF($W4="","",TODAY()-$W4) -> 63 | Y4: Cliente: Luzgardo Chavez. Dev histórico: Luis. Últ. contacto de hace más de 15 días: revisar si sigue realmente al día. | Z4: =IFERROR(INDEX(Aarón!$P:$P,MATCH($C4,Aarón!$A:$A,0))&"",IFERROR(INDEX(Rubit!$P:$P,MATCH($C4,Rubit!$A:$A,0))&"",IFERROR(INDEX(Luis!$P:$P,MATCH($C4,Luis!$A:$A,0))&"",""))) | AA4: =IFERROR(INDEX(Aarón!$Q:$Q,MATCH($C4,Aarón!$A:$A,0))&"",IFERROR(INDEX(Rubit!$Q:$Q,MATCH($C4,Rubit!$A:$A,0))&"",IFERROR(INDEX(Luis!$Q:$Q,MATCH($C4,Luis!$A:$A,0))&"",""))) | AB4: =IFERROR(INDEX('Juan Carlos'!$Q:$Q,MATCH($C4,'Juan Carlos'!$A:$A,0))&"","")
B5: 019 | C5: Urban | E5: Informativa | F5: Por definir | G5: Cerrado | H5: Aarón | I5: Juan Carlos | J5: =IFERROR(INDEX('Juan Carlos'!$P:$P,MATCH($C5,'Juan Carlos'!$A:$A,0))&"","") | K5: =IF($C5="","",IF($M5<>"Sí","C",IF($P5="Completo","A","B"))) -> A | L5: =IF($C5="","",IF($G5="Congelado","Congelado — mensaje cada 15 días",IF(N($X5)>15,"CONGELAR HOY",IF($M5<>"Sí","COBRAR EL 50%",IF($P5<>"Completo","PERSEGUIR MATERIAL",IF(AND($G5="Desarrollo",$N5<>"Sí"),"COBRAR EL 30%",IF(AND($G5="QA + entrega",$O5<>"Sí"),"COBRAR EL 20%",IF($G5="Cola","Listo para asignar","Al día")))))))) -> CONGELAR HOY | M5: Sí | N5: No | O5: No | P5: Completo | Q5: No aplica | U5: =IF(N($R5)=0,"",$T5/$R5) | V5: Desarrollo | W5: 46211 | X5: =IF($W5="","",TODAY()-$W5) -> 26 | Y5: Cliente: Maria Jose. Dev histórico: Aarón. | Z5: =IFERROR(INDEX(Aarón!$P:$P,MATCH($C5,Aarón!$A:$A,0))&"",IFERROR(INDEX(Rubit!$P:$P,MATCH($C5,Rubit!$A:$A,0))&"",IFERROR(INDEX(Luis!$P:$P,MATCH($C5,Luis!$A:$A,0))&"",""))) | AA5: =IFERROR(INDEX(Aarón!$Q:$Q,MATCH($C5,Aarón!$A:$A,0))&"",IFERROR(INDEX(Rubit!$Q:$Q,MATCH($C5,Rubit!$A:$A,0))&"",IFERROR(INDEX(Luis!$Q:$Q,MATCH($C5,Luis!$A:$A,0))&"",""))) | AB5: =IFERROR(INDEX('Juan Carlos'!$Q:$Q,MATCH($C5,'Juan Carlos'!$A:$A,0))&"","")
B6: 022 | C6: By Dra. Deyanira | E6: E-commerce | F6: Por definir | G6: Cerrado | H6: Aarón | I6: Juan Carlos | J6: =IFERROR(INDEX('Juan Carlos'!$P:$P,MATCH($C6,'Juan Carlos'!$A:$A,0))&"","") | K6: =IF($C6="","",IF($M6<>"Sí","C",IF($P6="Completo","A","B"))) -> B | L6: =IF($C6="","",IF($G6="Congelado","Congelado — mensaje cada 15 días",IF(N($X6)>15,"CONGELAR HOY",IF($M6<>"Sí","COBRAR EL 50%",IF($P6<>"Completo","PERSEGUIR MATERIAL",IF(AND($G6="Desarrollo",$N6<>"Sí"),"COBRAR EL 30%",IF(AND($G6="QA + entrega",$O6<>"Sí"),"COBRAR EL 20%",IF($G6="Cola","Listo para asignar","Al día")))))))) -> CONGELAR HOY | M6: Sí | N6: Sí | O6: No | P6: Incompleto | Q6: No enviada | U6: =IF(N($R6)=0,"",$T6/$R6) | V6: Nada — entregado, en espera de comprar el hosting. Marcha blanca | W6: 46192 | X6: =IF($W6="","",TODAY()-$W6) -> 45 | Y6: Cliente: Jonathan Quiches. Dev histórico: Aarón. | Z6: =IFERROR(INDEX(Aarón!$P:$P,MATCH($C6,Aarón!$A:$A,0))&"",IFERROR(INDEX(Rubit!$P:$P,MATCH($C6,Rubit!$A:$A,0))&"",IFERROR(INDEX(Luis!$P:$P,MATCH($C6,Luis!$A:$A,0))&"",""))) | AA6: =IFERROR(INDEX(Aarón!$Q:$Q,MATCH($C6,Aarón!$A:$A,0))&"",IFERROR(INDEX(Rubit!$Q:$Q,MATCH($C6,Rubit!$A:$A,0))&"",IFERROR(INDEX(Luis!$Q:$Q,MATCH($C6,Luis!$A:$A,0))&"",""))) | AB6: =IFERROR(INDEX('Juan Carlos'!$Q:$Q,MATCH($C6,'Juan Carlos'!$A:$A,0))&"","")
B7: 026 | C7: Maginhard | E7: E-commerce | F7: Por definir | G7: Esperando material | H7: Aarón | I7: Juan Carlos | J7: =IFERROR(INDEX('Juan Carlos'!$P:$P,MATCH($C7,'Juan Carlos'!$A:$A,0))&"","") | K7: =IF($C7="","",IF($M7<>"Sí","C",IF($P7="Completo","A","B"))) -> B | L7: =IF($C7="","",IF($G7="Congelado","Congelado — mensaje cada 15 días",IF(N($X7)>15,"CONGELAR HOY",IF($M7<>"Sí","COBRAR EL 50%",IF($P7<>"Completo","PERSEGUIR MATERIAL",IF(AND($G7="Desarrollo",$N7<>"Sí"),"COBRAR EL 30%",IF(AND($G7="QA + entrega",$O7<>"Sí"),"COBRAR EL 20%",IF($G7="Cola","Listo para asignar","Al día")))))))) -> PERSEGUIR MATERIAL | M7: Sí | N7: No aplica | O7: No aplica | P7: Nada | Q7: No enviada | U7: =IF(N($R7)=0,"",$T7/$R7) | V7: Todo — BLOQUEADO: no hay acceso al grupo del cliente | X7: =IF($W7="","",TODAY()-$W7) | Y7: Cliente: Kevin. Dev histórico: Aarón. Requiere desbloquear canal de comunicación antes de nada. 30 | Z7: =IFERROR(INDEX(Aarón!$P:$P,MATCH($C7,Aarón!$A:$A,0))&"",IFERROR(INDEX(Rubit!$P:$P,MATCH($C7,Rubit!$A:$A,0))&"",IFERROR(INDEX(Luis!$P:$P,MATCH($C7,Luis!$A:$A,0))&"",""))) | AA7: =IFERROR(INDEX(Aarón!$Q:$Q,MATCH($C7,Aarón!$A:$A,0))&"",IFERROR(INDEX(Rubit!$Q:$Q,MATCH($C7,Rubit!$A:$A,0))&"",IFERROR(INDEX(Luis!$Q:$Q,MATCH($C7,Luis!$A:$A,0))&"",""))) | AB7: =IFERROR(INDEX('Juan Carlos'!$Q:$Q,MATCH($C7,'Juan Carlos'!$A:$A,0))&"","")
B8: 035 | C8: Jufrarvp S.R.L. | E8: E-commerce | F8: Por definir | G8: Congelado | H8: Aarón | I8: Juan Carlos | J8: =IFERROR(INDEX('Juan Carlos'!$P:$P,MATCH($C8,'Juan Carlos'!$A:$A,0))&"","") | K8: =IF($C8="","",IF($M8<>"Sí","C",IF($P8="Completo","A","B"))) -> A | L8: =IF($C8="","",IF($G8="Congelado","Congelado — mensaje cada 15 días",IF(N($X8)>15,"CONGELAR HOY",IF($M8<>"Sí","COBRAR EL 50%",IF($P8<>"Completo","PERSEGUIR MATERIAL",IF(AND($G8="Desarrollo",$N8<>"Sí"),"COBRAR EL 30%",IF(AND($G8="QA + entrega",$O8<>"Sí"),"COBRAR EL 20%",IF($G8="Cola","Listo para asignar","Al día")))))))) -> Congelado — mensaje cada 15 días | M8: Sí | N8: Sí | O8: No | P8: Completo | Q8: Recibida y validada | U8: =IF(N($R8)=0,"",$T8/$R8) | V8: Validación/aprobación del cliente | X8: =IF($W8="","",TODAY()-$W8) | Y8: Cliente: Julio Ponce. Sin fecha de última respuesta registrada — confirmar. | Z8: =IFERROR(INDEX(Aarón!$P:$P,MATCH($C8,Aarón!$A:$A,0))&"",IFERROR(INDEX(Rubit!$P:$P,MATCH($C8,Rubit!$A:$A,0))&"",IFERROR(INDEX(Luis!$P:$P,MATCH($C8,Luis!$A:$A,0))&"",""))) | AA8: =IFERROR(INDEX(Aarón!$Q:$Q,MATCH($C8,Aarón!$A:$A,0))&"",IFERROR(INDEX(Rubit!$Q:$Q,MATCH($C8,Rubit!$A:$A,0))&"",IFERROR(INDEX(Luis!$Q:$Q,MATCH($C8,Luis!$A:$A,0))&"",""))) | AB8: =IFERROR(INDEX('Juan Carlos'!$Q:$Q,MATCH($C8,'Juan Carlos'!$A:$A,0))&"","")
B9: 036 | C9: Soluz | E9: E-commerce | F9: Por definir | G9: Desarrollo | H9: Aarón | I9: Juan Carlos | J9: =IFERROR(INDEX('Juan Carlos'!$P:$P,MATCH($C9,'Juan Carlos'!$A:$A,0))&"","") -> Diseño finalizado | K9: =IF($C9="","",IF($M9<>"Sí","C",IF($P9="Completo","A","B"))) -> A | L9: =IF($C9="","",IF($G9="Congelado","Congelado — mensaje cada 15 días",IF(N($X9)>15,"CONGELAR HOY",IF($M9<>"Sí","COBRAR EL 50%",IF($P9<>"Completo","PERSEGUIR MATERIAL",IF(AND($G9="Desarrollo",$N9<>"Sí"),"COBRAR EL 30%",IF(AND($G9="QA + entrega",$O9<>"Sí"),"COBRAR EL 20%",IF($G9="Cola","Listo para asignar","Al día")))))))) -> CONGELAR HOY | M9: Sí | N9: Sí | O9: No | P9: Completo | Q9: No enviada | U9: =IF(N($R9)=0,"",$T9/$R9) | V9: Reunión reprogramada + validación del cliente sobre carga de productos | W9: 46213 | X9: =IF($W9="","",TODAY()-$W9) -> 24 | Y9: Cliente: Giancarlo Rosario. En transición de Aarón a Luis (aún no formalizada). | Z9: =IFERROR(INDEX(Aarón!$P:$P,MATCH($C9,Aarón!$A:$A,0))&"",IFERROR(INDEX(Rubit!$P:$P,MATCH($C9,Rubit!$A:$A,0))&"",IFERROR(INDEX(Luis!$P:$P,MATCH($C9,Luis!$A:$A,0))&"",""))) | AA9: =IFERROR(INDEX(Aarón!$Q:$Q,MATCH($C9,Aarón!$A:$A,0))&"",IFERROR(INDEX(Rubit!$Q:$Q,MATCH($C9,Rubit!$A:$A,0))&"",IFERROR(INDEX(Luis!$Q:$Q,MATCH($C9,Luis!$A:$A,0))&"",""))) | AB9: =IFERROR(INDEX('Juan Carlos'!$Q:$Q,MATCH($C9,'Juan Carlos'!$A:$A,0))&"","")
B10: 038 | C10: L'Andrea's Secret | E10: E-commerce | F10: Por definir | G10: Esperando material | H10: Luis | I10: Juan Carlos | J10: =IFERROR(INDEX('Juan Carlos'!$P:$P,MATCH($C10,'Juan Carlos'!$A:$A,0))&"","") -> Material completo — iniciar diseño | K10: =IF($C10="","",IF($M10<>"Sí","C",IF($P10="Completo","A","B"))) -> A | L10: =IF($C10="","",IF($G10="Congelado","Congelado — mensaje cada 15 días",IF(N($X10)>15,"CONGELAR HOY",IF($M10<>"Sí","COBRAR EL 50%",IF($P10<>"Completo","PERSEGUIR MATERIAL",IF(AND($G10="Desarrollo",$N10<>"Sí"),"COBRAR EL 30%",IF(AND($G10="QA + entrega",$O10<>"Sí"),"COBRAR EL 20%",IF($G10="Cola","Listo para asignar","Al día")))))))) -> Al día | M10: Sí | N10: Sí | O10: No | P10: Completo | Q10: Recibida con errores | U10: =IF(N($R10)=0,"",$T10/$R10) | V10: Material de diseño — brief llenado | X10: =IF($W10="","",TODAY()-$W10) | Y10: Cliente: Gladys Poma. Dev histórico: Luis. 30% ya pagado según pizarra. | Z10: =IFERROR(INDEX(Aarón!$P:$P,MATCH($C10,Aarón!$A:$A,0))&"",IFERROR(INDEX(Rubit!$P:$P,MATCH($C10,Rubit!$A:$A,0))&"",IFERROR(INDEX(Luis!$P:$P,MATCH($C10,Luis!$A:$A,0))&"",""))) | AA10: =IFERROR(INDEX(Aarón!$Q:$Q,MATCH($C10,Aarón!$A:$A,0))&"",IFERROR(INDEX(Rubit!$Q:$Q,MATCH($C10,Rubit!$A:$A,0))&"",IFERROR(INDEX(Luis!$Q:$Q,MATCH($C10,Luis!$A:$A,0))&"",""))) | AB10: =IFERROR(INDEX('Juan Carlos'!$Q:$Q,MATCH($C10,'Juan Carlos'!$A:$A,0))&"","")
B11: 040 | C11: Maquinarias Aoxiang | E11: E-commerce | F11: Por definir | G11: Cerrado | H11: Aarón | I11: Juan Carlos | J11: =IFERROR(INDEX('Juan Carlos'!$P:$P,MATCH($C11,'Juan Carlos'!$A:$A,0))&"","") -> Diseño finalizado | K11: =IF($C11="","",IF($M11<>"Sí","C",IF($P11="Completo","A","B"))) -> A | L11: =IF($C11="","",IF($G11="Congelado","Congelado — mensaje cada 15 días",IF(N($X11)>15,"CONGELAR HOY",IF($M11<>"Sí","COBRAR EL 50%",IF($P11<>"Completo","PERSEGUIR MATERIAL",IF(AND($G11="Desarrollo",$N11<>"Sí"),"COBRAR EL 30%",IF(AND($G11="QA + entrega",$O11<>"Sí"),"COBRAR EL 20%",IF($G11="Cola","Listo para asignar","Al día")))))))) -> CONGELAR HOY | M11: Sí | N11: Sí | O11: Sí | P11: Completo | Q11: Recibida con errores | U11: =IF(N($R11)=0,"",$T11/$R11) | V11: Nada — diseño aprobado | W11: 46200 | X11: =IF($W11="","",TODAY()-$W11) -> 37 | Y11: Cliente: Liliana y Javier. | Z11: =IFERROR(INDEX(Aarón!$P:$P,MATCH($C11,Aarón!$A:$A,0))&"",IFERROR(INDEX(Rubit!$P:$P,MATCH($C11,Rubit!$A:$A,0))&"",IFERROR(INDEX(Luis!$P:$P,MATCH($C11,Luis!$A:$A,0))&"",""))) | AA11: =IFERROR(INDEX(Aarón!$Q:$Q,MATCH($C11,Aarón!$A:$A,0))&"",IFERROR(INDEX(Rubit!$Q:$Q,MATCH($C11,Rubit!$A:$A,0))&"",IFERROR(INDEX(Luis!$Q:$Q,MATCH($C11,Luis!$A:$A,0))&"",""))) | AB11: =IFERROR(INDEX('Juan Carlos'!$Q:$Q,MATCH($C11,'Juan Carlos'!$A:$A,0))&"","")
B12: 041 | C12: Place For Pet | E12: E-commerce | F12: Por definir | G12: Congelado | H12: Rubit | I12: Juan Carlos | J12: =IFERROR(INDEX('Juan Carlos'!$P:$P,MATCH($C12,'Juan Carlos'!$A:$A,0))&"","") | K12: =IF($C12="","",IF($M12<>"Sí","C",IF($P12="Completo","A","B"))) -> A | L12: =IF($C12="","",IF($G12="Congelado","Congelado — mensaje cada 15 días",IF(N($X12)>15,"CONGELAR HOY",IF($M12<>"Sí","COBRAR EL 50%",IF($P12<>"Completo","PERSEGUIR MATERIAL",IF(AND($G12="Desarrollo",$N12<>"Sí"),"COBRAR EL 30%",IF(AND($G12="QA + entrega",$O12<>"Sí"),"COBRAR EL 20%",IF($G12="Cola","Listo para asignar","Al día")))))))) -> Congelado — mensaje cada 15 días | M12: Sí | N12: Sí | O12: Sí | P12: Completo | Q12: Recibida con errores | U12: =IF(N($R12)=0,"",$T12/$R12) | V12: Reunión agendada | W12: 46216 | X12: =IF($W12="","",TODAY()-$W12) -> 21 | Y12: Cliente: Natasha Marval y Vanessa Ayvar. Dev histórico: Rubit. - Perseguir material a partir del 5/08 | Z12: =IFERROR(INDEX(Aarón!$P:$P,MATCH($C12,Aarón!$A:$A,0))&"",IFERROR(INDEX(Rubit!$P:$P,MATCH($C12,Rubit!$A:$A,0))&"",IFERROR(INDEX(Luis!$P:$P,MATCH($C12,Luis!$A:$A,0))&"",""))) | AA12: =IFERROR(INDEX(Aarón!$Q:$Q,MATCH($C12,Aarón!$A:$A,0))&"",IFERROR(INDEX(Rubit!$Q:$Q,MATCH($C12,Rubit!$A:$A,0))&"",IFERROR(INDEX(Luis!$Q:$Q,MATCH($C12,Luis!$A:$A,0))&"",""))) | AB12: =IFERROR(INDEX('Juan Carlos'!$Q:$Q,MATCH($C12,'Juan Carlos'!$A:$A,0))&"","")
A13: 9 | B13: 051 | C13: Dr. Gonzalo Caballero | E13: Informativa | F13: Por definir | G13: Esperando material | H13: Sin asignar | I13: Juan Carlos | J13: =IFERROR(INDEX('Juan Carlos'!$P:$P,MATCH($C13,'Juan Carlos'!$A:$A,0))&"","") | K13: =IF($C13="","",IF($M13<>"Sí","C",IF($P13="Completo","A","B"))) -> B | L13: =IF($C13="","",IF($G13="Congelado","Congelado — mensaje cada 15 días",IF(N($X13)>15,"CONGELAR HOY",IF($M13<>"Sí","COBRAR EL 50%",IF($P13<>"Completo","PERSEGUIR MATERIAL",IF(AND($G13="Desarrollo",$N13<>"Sí"),"COBRAR EL 30%",IF(AND($G13="QA + entrega",$O13<>"Sí"),"COBRAR EL 20%",IF($G13="Cola","Listo para asignar","Al día")))))))) -> CONGELAR HOY | M13: Sí | N13: No aplica | O13: No aplica | P13: Incompleto | Q13: No aplica | U13: =IF(N($R13)=0,"",$T13/$R13) | V13: Toda la información del cliente — aún no ha entregado nada | W13: 46210 | X13: =IF($W13="","",TODAY()-$W13) -> 27 | Y13: Cliente: Gonzalo Caballero. 30% marcado como 'en camino'. | Z13: =IFERROR(INDEX(Aarón!$P:$P,MATCH($C13,Aarón!$A:$A,0))&"",IFERROR(INDEX(Rubit!$P:$P,MATCH($C13,Rubit!$A:$A,0))&"",IFERROR(INDEX(Luis!$P:$P,MATCH($C13,Luis!$A:$A,0))&"",""))) | AA13: =IFERROR(INDEX(Aarón!$Q:$Q,MATCH($C13,Aarón!$A:$A,0))&"",IFERROR(INDEX(Rubit!$Q:$Q,MATCH($C13,Rubit!$A:$A,0))&"",IFERROR(INDEX(Luis!$Q:$Q,MATCH($C13,Luis!$A:$A,0))&"",""))) | AB13: =IFERROR(INDEX('Juan Carlos'!$Q:$Q,MATCH($C13,'Juan Carlos'!$A:$A,0))&"","")
B14: 053 | C14: Youbi Importaciones | E14: Informativa | F14: Por definir | G14: Desarrollo | H14: Aarón | I14: Juan Carlos | J14: =IFERROR(INDEX('Juan Carlos'!$P:$P,MATCH($C14,'Juan Carlos'!$A:$A,0))&"","") -> Diseño finalizado | K14: =IF($C14="","",IF($M14<>"Sí","C",IF($P14="Completo","A","B"))) -> A | L14: =IF($C14="","",IF($G14="Congelado","Congelado — mensaje cada 15 días",IF(N($X14)>15,"CONGELAR HOY",IF($M14<>"Sí","COBRAR EL 50%",IF($P14<>"Completo","PERSEGUIR MATERIAL",IF(AND($G14="Desarrollo",$N14<>"Sí"),"COBRAR EL 30%",IF(AND($G14="QA + entrega",$O14<>"Sí"),"COBRAR EL 20%",IF($G14="Cola","Listo para asignar","Al día")))))))) -> CONGELAR HOY | M14: Sí | N14: No | O14: No | P14: Completo | Q14: No aplica | U14: =IF(N($R14)=0,"",$T14/$R14) | V14: Validación de diseño en paralelo al desarrollo | W14: 46212 | X14: =IF($W14="","",TODAY()-$W14) -> 25 | Y14: Cliente: Jenifer y Jorge. 30% pagado. | Z14: =IFERROR(INDEX(Aarón!$P:$P,MATCH($C14,Aarón!$A:$A,0))&"",IFERROR(INDEX(Rubit!$P:$P,MATCH($C14,Rubit!$A:$A,0))&"",IFERROR(INDEX(Luis!$P:$P,MATCH($C14,Luis!$A:$A,0))&"",""))) | AA14: =IFERROR(INDEX(Aarón!$Q:$Q,MATCH($C14,Aarón!$A:$A,0))&"",IFERROR(INDEX(Rubit!$Q:$Q,MATCH($C14,Rubit!$A:$A,0))&"",IFERROR(INDEX(Luis!$Q:$Q,MATCH($C14,Luis!$A:$A,0))&"",""))) | AB14: =IFERROR(INDEX('Juan Carlos'!$Q:$Q,MATCH($C14,'Juan Carlos'!$A:$A,0))&"","")
B15: 054 | C15: Ale Bakery | E15: Informativa | F15: WooCommerce | G15: Cerrado | H15: Rubit | I15: Juan Carlos | J15: =IFERROR(INDEX('Juan Carlos'!$P:$P,MATCH($C15,'Juan Carlos'!$A:$A,0))&"","") | K15: =IF($C15="","",IF($M15<>"Sí","C",IF($P15="Completo","A","B"))) -> A | L15: =IF($C15="","",IF($G15="Congelado","Congelado — mensaje cada 15 días",IF(N($X15)>15,"CONGELAR HOY",IF($M15<>"Sí","COBRAR EL 50%",IF($P15<>"Completo","PERSEGUIR MATERIAL",IF(AND($G15="Desarrollo",$N15<>"Sí"),"COBRAR EL 30%",IF(AND($G15="QA + entrega",$O15<>"Sí"),"COBRAR EL 20%",IF($G15="Cola","Listo para asignar","Al día")))))))) -> CONGELAR HOY | M15: Sí | N15: Sí | O15: Sí | P15: Completo | Q15: No aplica | U15: =IF(N($R15)=0,"",$T15/$R15) | V15: Fotografías finales del cliente para completar el diseño (30% ya pagado) | W15: 46219 | X15: =IF($W15="","",TODAY()-$W15) -> 18 | Y15: Cliente: Alejandro y Alejandra. Dev histórico: Rubit. Cita viernes 24/07 . Finalizado , agendar reunion final 5 dias antes de su ultima cita | Z15: =IFERROR(INDEX(Aarón!$P:$P,MATCH($C15,Aarón!$A:$A,0))&"",IFERROR(INDEX(Rubit!$P:$P,MATCH($C15,Rubit!$A:$A,0))&"",IFERROR(INDEX(Luis!$P:$P,MATCH($C15,Luis!$A:$A,0))&"",""))) | AA15: =IFERROR(INDEX(Aarón!$Q:$Q,MATCH($C15,Aarón!$A:$A,0))&"",IFERROR(INDEX(Rubit!$Q:$Q,MATCH($C15,Rubit!$A:$A,0))&"",IFERROR(INDEX(Luis!$Q:$Q,MATCH($C15,Luis!$A:$A,0))&"",""))) | AB15: =IFERROR(INDEX('Juan Carlos'!$Q:$Q,MATCH($C15,'Juan Carlos'!$A:$A,0))&"","")
B16: 055 | C16: Anahir Store | E16: E-commerce | F16: Por definir | G16: Diseño | H16: Rubit | I16: Juan Carlos | J16: =IFERROR(INDEX('Juan Carlos'!$P:$P,MATCH($C16,'Juan Carlos'!$A:$A,0))&"","") | K16: =IF($C16="","",IF($M16<>"Sí","C",IF($P16="Completo","A","B"))) -> B | L16: =IF($C16="","",IF($G16="Congelado","Congelado — mensaje cada 15 días",IF(N($X16)>15,"CONGELAR HOY",IF($M16<>"Sí","COBRAR EL 50%",IF($P16<>"Completo","PERSEGUIR MATERIAL",IF(AND($G16="Desarrollo",$N16<>"Sí"),"COBRAR EL 30%",IF(AND($G16="QA + entrega",$O16<>"Sí"),"COBRAR EL 20%",IF($G16="Cola","Listo para asignar","Al día")))))))) -> CONGELAR HOY | M16: Sí | N16: Sí | O16: No aplica | P16: Incompleto | Q16: No aplica | R16: 100 | U16: =IF(N($R16)=0,"",$T16/$R16) -> 0 | V16: Feedback/aprobación del diseño (30% ya pagado) | W16: 46212 | X16: =IF($W16="","",TODAY()-$W16) -> 25 | Y16: Cliente: Norma Gonzales. Dev histórico: Rubit. | Z16: =IFERROR(INDEX(Aarón!$P:$P,MATCH($C16,Aarón!$A:$A,0))&"",IFERROR(INDEX(Rubit!$P:$P,MATCH($C16,Rubit!$A:$A,0))&"",IFERROR(INDEX(Luis!$P:$P,MATCH($C16,Luis!$A:$A,0))&"",""))) | AA16: =IFERROR(INDEX(Aarón!$Q:$Q,MATCH($C16,Aarón!$A:$A,0))&"",IFERROR(INDEX(Rubit!$Q:$Q,MATCH($C16,Rubit!$A:$A,0))&"",IFERROR(INDEX(Luis!$Q:$Q,MATCH($C16,Luis!$A:$A,0))&"",""))) | AB16: =IFERROR(INDEX('Juan Carlos'!$Q:$Q,MATCH($C16,'Juan Carlos'!$A:$A,0))&"","")
B17: 056 | C17: Perforaciones H&A | E17: Informativa | F17: Por definir | G17: Cerrado | H17: Sin asignar | I17: Juan Carlos | J17: =IFERROR(INDEX('Juan Carlos'!$P:$P,MATCH($C17,'Juan Carlos'!$A:$A,0))&"","") | K17: =IF($C17="","",IF($M17<>"Sí","C",IF($P17="Completo","A","B"))) -> A | L17: =IF($C17="","",IF($G17="Congelado","Congelado — mensaje cada 15 días",IF(N($X17)>15,"CONGELAR HOY",IF($M17<>"Sí","COBRAR EL 50%",IF($P17<>"Completo","PERSEGUIR MATERIAL",IF(AND($G17="Desarrollo",$N17<>"Sí"),"COBRAR EL 30%",IF(AND($G17="QA + entrega",$O17<>"Sí"),"COBRAR EL 20%",IF($G17="Cola","Listo para asignar","Al día")))))))) -> CONGELAR HOY | M17: Sí | N17: Sí | O17: Sí | P17: Completo | Q17: No aplica | U17: =IF(N($R17)=0,"",$T17/$R17) | V17: Nada pendiente de diseño — falta confirmar developer asignado | W17: 46218 | X17: =IF($W17="","",TODAY()-$W17) -> 19 | Y17: Cliente: Jessenia Lizbeth. Diseño aprobado, sin developer confirmado. | Z17: =IFERROR(INDEX(Aarón!$P:$P,MATCH($C17,Aarón!$A:$A,0))&"",IFERROR(INDEX(Rubit!$P:$P,MATCH($C17,Rubit!$A:$A,0))&"",IFERROR(INDEX(Luis!$P:$P,MATCH($C17,Luis!$A:$A,0))&"",""))) | AA17: =IFERROR(INDEX(Aarón!$Q:$Q,MATCH($C17,Aarón!$A:$A,0))&"",IFERROR(INDEX(Rubit!$Q:$Q,MATCH($C17,Rubit!$A:$A,0))&"",IFERROR(INDEX(Luis!$Q:$Q,MATCH($C17,Luis!$A:$A,0))&"",""))) | AB17: =IFERROR(INDEX('Juan Carlos'!$Q:$Q,MATCH($C17,'Juan Carlos'!$A:$A,0))&"","")
B18: 057 | C18: Grúas Sagitario | E18: Informativa | F18: Por definir | G18: Diseño | H18: Luis | I18: Juan Carlos | J18: =IFERROR(INDEX('Juan Carlos'!$P:$P,MATCH($C18,'Juan Carlos'!$A:$A,0))&"","") | K18: =IF($C18="","",IF($M18<>"Sí","C",IF($P18="Completo","A","B"))) -> B | L18: =IF($C18="","",IF($G18="Congelado","Congelado — mensaje cada 15 días",IF(N($X18)>15,"CONGELAR HOY",IF($M18<>"Sí","COBRAR EL 50%",IF($P18<>"Completo","PERSEGUIR MATERIAL",IF(AND($G18="Desarrollo",$N18<>"Sí"),"COBRAR EL 30%",IF(AND($G18="QA + entrega",$O18<>"Sí"),"COBRAR EL 20%",IF($G18="Cola","Listo para asignar","Al día")))))))) -> CONGELAR HOY | M18: Sí | N18: No aplica | O18: No aplica | P18: Incompleto | Q18: No aplica | U18: =IF(N($R18)=0,"",$T18/$R18) | V18: Aprobación del diseño por parte del cliente | W18: 46218 | X18: =IF($W18="","",TODAY()-$W18) -> 19 | Y18: Cliente: J Pino. | Z18: =IFERROR(INDEX(Aarón!$P:$P,MATCH($C18,Aarón!$A:$A,0))&"",IFERROR(INDEX(Rubit!$P:$P,MATCH($C18,Rubit!$A:$A,0))&"",IFERROR(INDEX(Luis!$P:$P,MATCH($C18,Luis!$A:$A,0))&"",""))) | AA18: =IFERROR(INDEX(Aarón!$Q:$Q,MATCH($C18,Aarón!$A:$A,0))&"",IFERROR(INDEX(Rubit!$Q:$Q,MATCH($C18,Rubit!$A:$A,0))&"",IFERROR(INDEX(Luis!$Q:$Q,MATCH($C18,Luis!$A:$A,0))&"",""))) | AB18: =IFERROR(INDEX('Juan Carlos'!$Q:$Q,MATCH($C18,'Juan Carlos'!$A:$A,0))&"","")
B19: 059 | C19: Los Halcones | E19: E-commerce | F19: Por definir | G19: Desarrollo | H19: Aarón | I19: Juan Carlos | J19: =IFERROR(INDEX('Juan Carlos'!$P:$P,MATCH($C19,'Juan Carlos'!$A:$A,0))&"","") -> Diseño finalizado | K19: =IF($C19="","",IF($M19<>"Sí","C",IF($P19="Completo","A","B"))) -> A | L19: =IF($C19="","",IF($G19="Congelado","Congelado — mensaje cada 15 días",IF(N($X19)>15,"CONGELAR HOY",IF($M19<>"Sí","COBRAR EL 50%",IF($P19<>"Completo","PERSEGUIR MATERIAL",IF(AND($G19="Desarrollo",$N19<>"Sí"),"COBRAR EL 30%",IF(AND($G19="QA + entrega",$O19<>"Sí"),"COBRAR EL 20%",IF($G19="Cola","Listo para asignar","Al día")))))))) -> CONGELAR HOY | M19: Sí | N19: Sí | O19: Sí | P19: Completo | Q19: No aplica | R19: 0 | S19: Si- NO - INCOMPLETO | T19: 0 | U19: =IF(N($R19)=0,"",$T19/$R19) | V19: Nada — en implementación, cliente informado y disponible | W19: 46218 | X19: =IF($W19="","",TODAY()-$W19) -> 19 | Y19: Cliente: Juan. - Cita viernes 24-07 | Z19: =IFERROR(INDEX(Aarón!$P:$P,MATCH($C19,Aarón!$A:$A,0))&"",IFERROR(INDEX(Rubit!$P:$P,MATCH($C19,Rubit!$A:$A,0))&"",IFERROR(INDEX(Luis!$P:$P,MATCH($C19,Luis!$A:$A,0))&"",""))) | AA19: =IFERROR(INDEX(Aarón!$Q:$Q,MATCH($C19,Aarón!$A:$A,0))&"",IFERROR(INDEX(Rubit!$Q:$Q,MATCH($C19,Rubit!$A:$A,0))&"",IFERROR(INDEX(Luis!$Q:$Q,MATCH($C19,Luis!$A:$A,0))&"",""))) | AB19: =IFERROR(INDEX('Juan Carlos'!$Q:$Q,MATCH($C19,'Juan Carlos'!$A:$A,0))&"","")
B20: 061 | C20: Comsavitar SAC | E20: E-commerce | F20: Por definir | G20: Diseño | H20: Sin asignar | I20: Juan Carlos | J20: =IFERROR(INDEX('Juan Carlos'!$P:$P,MATCH($C20,'Juan Carlos'!$A:$A,0))&"","") | K20: =IF($C20="","",IF($M20<>"Sí","C",IF($P20="Completo","A","B"))) -> B | L20: =IF($C20="","",IF($G20="Congelado","Congelado — mensaje cada 15 días",IF(N($X20)>15,"CONGELAR HOY",IF($M20<>"Sí","COBRAR EL 50%",IF($P20<>"Completo","PERSEGUIR MATERIAL",IF(AND($G20="Desarrollo",$N20<>"Sí"),"COBRAR EL 30%",IF(AND($G20="QA + entrega",$O20<>"Sí"),"COBRAR EL 20%",IF($G20="Cola","Listo para asignar","Al día")))))))) -> CONGELAR HOY | M20: Sí | N20: No aplica | O20: No aplica | P20: Incompleto | Q20: No aplica | U20: =IF(N($R20)=0,"",$T20/$R20) | V20: Validación final del manual de marca | W20: 46218 | X20: =IF($W20="","",TODAY()-$W20) -> 19 | Y20: Cliente: Katia. PENDIENTE: agendar la reunión de brief. | Z20: =IFERROR(INDEX(Aarón!$P:$P,MATCH($C20,Aarón!$A:$A,0))&"",IFERROR(INDEX(Rubit!$P:$P,MATCH($C20,Rubit!$A:$A,0))&"",IFERROR(INDEX(Luis!$P:$P,MATCH($C20,Luis!$A:$A,0))&"",""))) | AA20: =IFERROR(INDEX(Aarón!$Q:$Q,MATCH($C20,Aarón!$A:$A,0))&"",IFERROR(INDEX(Rubit!$Q:$Q,MATCH($C20,Rubit!$A:$A,0))&"",IFERROR(INDEX(Luis!$Q:$Q,MATCH($C20,Luis!$A:$A,0))&"",""))) | AB20: =IFERROR(INDEX('Juan Carlos'!$Q:$Q,MATCH($C20,'Juan Carlos'!$A:$A,0))&"","")
A21: 1 | B21: 062 | C21: I&N Caprimoda | E21: E-commerce | F21: Por definir | G21: QA + entrega | H21: Sin asignar | I21: Juan Carlos | J21: =IFERROR(INDEX('Juan Carlos'!$P:$P,MATCH($C21,'Juan Carlos'!$A:$A,0))&"","") -> Diseño finalizado | K21: =IF($C21="","",IF($M21<>"Sí","C",IF($P21="Completo","A","B"))) -> A | L21: =IF($C21="","",IF($G21="Congelado","Congelado — mensaje cada 15 días",IF(N($X21)>15,"CONGELAR HOY",IF($M21<>"Sí","COBRAR EL 50%",IF($P21<>"Completo","PERSEGUIR MATERIAL",IF(AND($G21="Desarrollo",$N21<>"Sí"),"COBRAR EL 30%",IF(AND($G21="QA + entrega",$O21<>"Sí"),"COBRAR EL 20%",IF($G21="Cola","Listo para asignar","Al día")))))))) -> CONGELAR HOY | M21: Sí | N21: No | O21: No | P21: Completo | Q21: No enviada | U21: =IF(N($R21)=0,"",$T21/$R21) | V21: Carga y validación de contenidos | W21: 46218 | X21: =IF($W21="","",TODAY()-$W21) -> 19 | Y21: Cliente: Noelia Juanfer. OJO: Luis tiene capacidad 0 según Reglas — confirmar si esto es correcto. Cita viernes 24/07 | Z21: =IFERROR(INDEX(Aarón!$P:$P,MATCH($C21,Aarón!$A:$A,0))&"",IFERROR(INDEX(Rubit!$P:$P,MATCH($C21,Rubit!$A:$A,0))&"",IFERROR(INDEX(Luis!$P:$P,MATCH($C21,Luis!$A:$A,0))&"",""))) | AA21: =IFERROR(INDEX(Aarón!$Q:$Q,MATCH($C21,Aarón!$A:$A,0))&"",IFERROR(INDEX(Rubit!$Q:$Q,MATCH($C21,Rubit!$A:$A,0))&"",IFERROR(INDEX(Luis!$Q:$Q,MATCH($C21,Luis!$A:$A,0))&"",""))) | AB21: =IFERROR(INDEX('Juan Carlos'!$Q:$Q,MATCH($C21,'Juan Carlos'!$A:$A,0))&"","")
B22: 064 | C22: Eviext | E22: Informativa | F22: Por definir | G22: Desarrollo | H22: Sin asignar | I22: Juan Carlos | J22: =IFERROR(INDEX('Juan Carlos'!$P:$P,MATCH($C22,'Juan Carlos'!$A:$A,0))&"","") -> Diseño finalizado | K22: =IF($C22="","",IF($M22<>"Sí","C",IF($P22="Completo","A","B"))) -> A | L22: =IF($C22="","",IF($G22="Congelado","Congelado — mensaje cada 15 días",IF(N($X22)>15,"CONGELAR HOY",IF($M22<>"Sí","COBRAR EL 50%",IF($P22<>"Completo","PERSEGUIR MATERIAL",IF(AND($G22="Desarrollo",$N22<>"Sí"),"COBRAR EL 30%",IF(AND($G22="QA + entrega",$O22<>"Sí"),"COBRAR EL 20%",IF($G22="Cola","Listo para asignar","Al día")))))))) -> CONGELAR HOY | M22: Sí | N22: Sí | O22: No | P22: Completo | Q22: No aplica | U22: =IF(N($R22)=0,"",$T22/$R22) | V22: Integración de contenidos finales del cliente | W22: 46219 | X22: =IF($W22="","",TODAY()-$W22) -> 18 | Y22: Cliente: Reina. 30% en camino/confirmado. Sin developer confirmado — asignar. | Z22: =IFERROR(INDEX(Aarón!$P:$P,MATCH($C22,Aarón!$A:$A,0))&"",IFERROR(INDEX(Rubit!$P:$P,MATCH($C22,Rubit!$A:$A,0))&"",IFERROR(INDEX(Luis!$P:$P,MATCH($C22,Luis!$A:$A,0))&"",""))) | AA22: =IFERROR(INDEX(Aarón!$Q:$Q,MATCH($C22,Aarón!$A:$A,0))&"",IFERROR(INDEX(Rubit!$Q:$Q,MATCH($C22,Rubit!$A:$A,0))&"",IFERROR(INDEX(Luis!$Q:$Q,MATCH($C22,Luis!$A:$A,0))&"",""))) | AB22: =IFERROR(INDEX('Juan Carlos'!$Q:$Q,MATCH($C22,'Juan Carlos'!$A:$A,0))&"","")
B23: 065 | C23: Azcecorp | E23: E-commerce | F23: Por definir | G23: Desarrollo | H23: Sin asignar | I23: Juan Carlos | J23: =IFERROR(INDEX('Juan Carlos'!$P:$P,MATCH($C23,'Juan Carlos'!$A:$A,0))&"","") | K23: =IF($C23="","",IF($M23<>"Sí","C",IF($P23="Completo","A","B"))) -> B | L23: =IF($C23="","",IF($G23="Congelado","Congelado — mensaje cada 15 días",IF(N($X23)>15,"CONGELAR HOY",IF($M23<>"Sí","COBRAR EL 50%",IF($P23<>"Completo","PERSEGUIR MATERIAL",IF(AND($G23="Desarrollo",$N23<>"Sí"),"COBRAR EL 30%",IF(AND($G23="QA + entrega",$O23<>"Sí"),"COBRAR EL 20%",IF($G23="Cola","Listo para asignar","Al día")))))))) -> CONGELAR HOY | M23: Sí | N23: Sí | O23: No aplica | P23: Incompleto | Q23: Recibida con errores | U23: =IF(N($R23)=0,"",$T23/$R23) | V23: Validar catálogos y completar precios/datos finales antes de maquetar | W23: 46218 | X23: =IF($W23="","",TODAY()-$W23) -> 19 | Y23: Cliente: Alex Cordoba. Responsable actual 'Admin' — no es developer de código, reasignar a Aarón/Rubit/Luis. | Z23: =IFERROR(INDEX(Aarón!$P:$P,MATCH($C23,Aarón!$A:$A,0))&"",IFERROR(INDEX(Rubit!$P:$P,MATCH($C23,Rubit!$A:$A,0))&"",IFERROR(INDEX(Luis!$P:$P,MATCH($C23,Luis!$A:$A,0))&"",""))) | AA23: =IFERROR(INDEX(Aarón!$Q:$Q,MATCH($C23,Aarón!$A:$A,0))&"",IFERROR(INDEX(Rubit!$Q:$Q,MATCH($C23,Rubit!$A:$A,0))&"",IFERROR(INDEX(Luis!$Q:$Q,MATCH($C23,Luis!$A:$A,0))&"",""))) | AB23: =IFERROR(INDEX('Juan Carlos'!$Q:$Q,MATCH($C23,'Juan Carlos'!$A:$A,0))&"","")
B24: 065b | C24: Karol Milena Añez | E24: E-commerce | F24: Por definir | G24: Esperando material | H24: Rubit | I24: Juan Carlos | J24: =IFERROR(INDEX('Juan Carlos'!$P:$P,MATCH($C24,'Juan Carlos'!$A:$A,0))&"","") | K24: =IF($C24="","",IF($M24<>"Sí","C",IF($P24="Completo","A","B"))) -> B | L24: =IF($C24="","",IF($G24="Congelado","Congelado — mensaje cada 15 días",IF(N($X24)>15,"CONGELAR HOY",IF($M24<>"Sí","COBRAR EL 50%",IF($P24<>"Completo","PERSEGUIR MATERIAL",IF(AND($G24="Desarrollo",$N24<>"Sí"),"COBRAR EL 30%",IF(AND($G24="QA + entrega",$O24<>"Sí"),"COBRAR EL 20%",IF($G24="Cola","Listo para asignar","Al día")))))))) -> CONGELAR HOY | M24: Sí | N24: No aplica | O24: No aplica | P24: Incompleto | Q24: No enviada | U24: =IF(N($R24)=0,"",$T24/$R24) | V24: Levantamiento de información y materiales, falta brief formal | W24: 46218 | X24: =IF($W24="","",TODAY()-$W24) -> 19 | Y24: Cliente: Karol Añez. Dev histórico: Rubit. | Z24: =IFERROR(INDEX(Aarón!$P:$P,MATCH($C24,Aarón!$A:$A,0))&"",IFERROR(INDEX(Rubit!$P:$P,MATCH($C24,Rubit!$A:$A,0))&"",IFERROR(INDEX(Luis!$P:$P,MATCH($C24,Luis!$A:$A,0))&"",""))) | AA24: =IFERROR(INDEX(Aarón!$Q:$Q,MATCH($C24,Aarón!$A:$A,0))&"",IFERROR(INDEX(Rubit!$Q:$Q,MATCH($C24,Rubit!$A:$A,0))&"",IFERROR(INDEX(Luis!$Q:$Q,MATCH($C24,Luis!$A:$A,0))&"",""))) | AB24: =IFERROR(INDEX('Juan Carlos'!$Q:$Q,MATCH($C24,'Juan Carlos'!$A:$A,0))&"","")
A25: 2 | B25: 066 | C25: Erika Garay | E25: E-commerce | F25: Por definir | G25: Diseño | H25: Aarón | I25: Juan Carlos | J25: =IFERROR(INDEX('Juan Carlos'!$P:$P,MATCH($C25,'Juan Carlos'!$A:$A,0))&"","") -> Diseño en curso | K25: =IF($C25="","",IF($M25<>"Sí","C",IF($P25="Completo","A","B"))) -> A | L25: =IF($C25="","",IF($G25="Congelado","Congelado — mensaje cada 15 días",IF(N($X25)>15,"CONGELAR HOY",IF($M25<>"Sí","COBRAR EL 50%",IF($P25<>"Completo","PERSEGUIR MATERIAL",IF(AND($G25="Desarrollo",$N25<>"Sí"),"COBRAR EL 30%",IF(AND($G25="QA + entrega",$O25<>"Sí"),"COBRAR EL 20%",IF($G25="Cola","Listo para asignar","Al día")))))))) -> CONGELAR HOY | M25: Sí | N25: No aplica | O25: No aplica | P25: Completo | Q25: No enviada | U25: =IF(N($R25)=0,"",$T25/$R25) | V25: Material de diseño en general | W25: 46218 | X25: =IF($W25="","",TODAY()-$W25) -> 19 | Y25: Cliente: Erika Garay. Dev histórico: Aarón. | Z25: =IFERROR(INDEX(Aarón!$P:$P,MATCH($C25,Aarón!$A:$A,0))&"",IFERROR(INDEX(Rubit!$P:$P,MATCH($C25,Rubit!$A:$A,0))&"",IFERROR(INDEX(Luis!$P:$P,MATCH($C25,Luis!$A:$A,0))&"",""))) | AA25: =IFERROR(INDEX(Aarón!$Q:$Q,MATCH($C25,Aarón!$A:$A,0))&"",IFERROR(INDEX(Rubit!$Q:$Q,MATCH($C25,Rubit!$A:$A,0))&"",IFERROR(INDEX(Luis!$Q:$Q,MATCH($C25,Luis!$A:$A,0))&"",""))) | AB25: =IFERROR(INDEX('Juan Carlos'!$Q:$Q,MATCH($C25,'Juan Carlos'!$A:$A,0))&"","") -> en diseño
B26: 067 | C26: Ric Bian Originals | E26: E-commerce | F26: Por definir | G26: Diseño | H26: Rubit | I26: Juan Carlos | J26: =IFERROR(INDEX('Juan Carlos'!$P:$P,MATCH($C26,'Juan Carlos'!$A:$A,0))&"","") | K26: =IF($C26="","",IF($M26<>"Sí","C",IF($P26="Completo","A","B"))) -> B | L26: =IF($C26="","",IF($G26="Congelado","Congelado — mensaje cada 15 días",IF(N($X26)>15,"CONGELAR HOY",IF($M26<>"Sí","COBRAR EL 50%",IF($P26<>"Completo","PERSEGUIR MATERIAL",IF(AND($G26="Desarrollo",$N26<>"Sí"),"COBRAR EL 30%",IF(AND($G26="QA + entrega",$O26<>"Sí"),"COBRAR EL 20%",IF($G26="Cola","Listo para asignar","Al día")))))))) -> CONGELAR HOY | M26: Sí | N26: No aplica | O26: No aplica | P26: Incompleto | Q26: No enviada | U26: =IF(N($R26)=0,"",$T26/$R26) | V26: Material de diseño en general | W26: 46218 | X26: =IF($W26="","",TODAY()-$W26) -> 19 | Y26: Cliente: Romel. Dev histórico: Rubit.- espera de manual de marca websy , si pudieron algunas de las propuestas de logotipo | Z26: =IFERROR(INDEX(Aarón!$P:$P,MATCH($C26,Aarón!$A:$A,0))&"",IFERROR(INDEX(Rubit!$P:$P,MATCH($C26,Rubit!$A:$A,0))&"",IFERROR(INDEX(Luis!$P:$P,MATCH($C26,Luis!$A:$A,0))&"",""))) | AA26: =IFERROR(INDEX(Aarón!$Q:$Q,MATCH($C26,Aarón!$A:$A,0))&"",IFERROR(INDEX(Rubit!$Q:$Q,MATCH($C26,Rubit!$A:$A,0))&"",IFERROR(INDEX(Luis!$Q:$Q,MATCH($C26,Luis!$A:$A,0))&"",""))) | AB26: =IFERROR(INDEX('Juan Carlos'!$Q:$Q,MATCH($C26,'Juan Carlos'!$A:$A,0))&"","")
A27: 11 | B27: 068 | C27: Camaleon | E27: E-commerce | F27: Por definir | G27: Esperando material | H27: Aarón | I27: Juan Carlos | J27: =IFERROR(INDEX('Juan Carlos'!$P:$P,MATCH($C27,'Juan Carlos'!$A:$A,0))&"","") | K27: =IF($C27="","",IF($M27<>"Sí","C",IF($P27="Completo","A","B"))) -> B | L27: =IF($C27="","",IF($G27="Congelado","Congelado — mensaje cada 15 días",IF(N($X27)>15,"CONGELAR HOY",IF($M27<>"Sí","COBRAR EL 50%",IF($P27<>"Completo","PERSEGUIR MATERIAL",IF(AND($G27="Desarrollo",$N27<>"Sí"),"COBRAR EL 30%",IF(AND($G27="QA + entrega",$O27<>"Sí"),"COBRAR EL 20%",IF($G27="Cola","Listo para asignar","Al día")))))))) -> CONGELAR HOY | M27: Sí | N27: No aplica | O27: No aplica | P27: Nada | Q27: No enviada | U27: =IF(N($R27)=0,"",$T27/$R27) | V27: Todo — recién se llenó el brief | W27: 46219 | X27: =IF($W27="","",TODAY()-$W27) -> 18 | Y27: Cliente: Lady Quispe. Dev histórico: Aarón. Marca previa de Juan Carlos (el proyecto salió de su hoja por no estar en grupo A): «PERSEGUIR». | Z27: =IFERROR(INDEX(Aarón!$P:$P,MATCH($C27,Aarón!$A:$A,0))&"",IFERROR(INDEX(Rubit!$P:$P,MATCH($C27,Rubit!$A:$A,0))&"",IFERROR(INDEX(Luis!$P:$P,MATCH($C27,Luis!$A:$A,0))&"",""))) | AA27: =IFERROR(INDEX(Aarón!$Q:$Q,MATCH($C27,Aarón!$A:$A,0))&"",IFERROR(INDEX(Rubit!$Q:$Q,MATCH($C27,Rubit!$A:$A,0))&"",IFERROR(INDEX(Luis!$Q:$Q,MATCH($C27,Luis!$A:$A,0))&"",""))) | AB27: =IFERROR(INDEX('Juan Carlos'!$Q:$Q,MATCH($C27,'Juan Carlos'!$A:$A,0))&"","")
A28: 6 | B28: 069 | C28: Global Peru Renting | E28: Informativa | F28: Por definir | G28: Diseño | H28: Rubit | I28: Juan Carlos | J28: =IFERROR(INDEX('Juan Carlos'!$P:$P,MATCH($C28,'Juan Carlos'!$A:$A,0))&"","") | K28: =IF($C28="","",IF($M28<>"Sí","C",IF($P28="Completo","A","B"))) -> B | L28: =IF($C28="","",IF($G28="Congelado","Congelado — mensaje cada 15 días",IF(N($X28)>15,"CONGELAR HOY",IF($M28<>"Sí","COBRAR EL 50%",IF($P28<>"Completo","PERSEGUIR MATERIAL",IF(AND($G28="Desarrollo",$N28<>"Sí"),"COBRAR EL 30%",IF(AND($G28="QA + entrega",$O28<>"Sí"),"COBRAR EL 20%",IF($G28="Cola","Listo para asignar","Al día")))))))) -> CONGELAR HOY | M28: Sí | N28: No aplica | O28: No aplica | P28: Incompleto | Q28: No aplica | U28: =IF(N($R28)=0,"",$T28/$R28) | V28: Nada — en proceso de diseño | W28: 46218 | X28: =IF($W28="","",TODAY()-$W28) -> 19 | Y28: Cliente: Erika Ventura. Dev histórico: Rubit. , que suban sus archivos al drive Marca previa de Juan Carlos (el proyecto salió de su hoja por no estar en grupo A): «avance listo». | Z28: =IFERROR(INDEX(Aarón!$P:$P,MATCH($C28,Aarón!$A:$A,0))&"",IFERROR(INDEX(Rubit!$P:$P,MATCH($C28,Rubit!$A:$A,0))&"",IFERROR(INDEX(Luis!$P:$P,MATCH($C28,Luis!$A:$A,0))&"",""))) | AA28: =IFERROR(INDEX(Aarón!$Q:$Q,MATCH($C28,Aarón!$A:$A,0))&"",IFERROR(INDEX(Rubit!$Q:$Q,MATCH($C28,Rubit!$A:$A,0))&"",IFERROR(INDEX(Luis!$Q:$Q,MATCH($C28,Luis!$A:$A,0))&"",""))) | AB28: =IFERROR(INDEX('Juan Carlos'!$Q:$Q,MATCH($C28,'Juan Carlos'!$A:$A,0))&"","")
A29: 7 | B29: 070 | C29: Buzz Studios | E29: E-commerce | F29: Por definir | G29: Diseño | H29: Aarón | I29: Juan Carlos | J29: =IFERROR(INDEX('Juan Carlos'!$P:$P,MATCH($C29,'Juan Carlos'!$A:$A,0))&"","") -> Diseño en curso | K29: =IF($C29="","",IF($M29<>"Sí","C",IF($P29="Completo","A","B"))) -> A | L29: =IF($C29="","",IF($G29="Congelado","Congelado — mensaje cada 15 días",IF(N($X29)>15,"CONGELAR HOY",IF($M29<>"Sí","COBRAR EL 50%",IF($P29<>"Completo","PERSEGUIR MATERIAL",IF(AND($G29="Desarrollo",$N29<>"Sí"),"COBRAR EL 30%",IF(AND($G29="QA + entrega",$O29<>"Sí"),"COBRAR EL 20%",IF($G29="Cola","Listo para asignar","Al día")))))))) -> CONGELAR HOY | M29: Sí | N29: No aplica | O29: No aplica | P29: Completo | Q29: No enviada | U29: =IF(N($R29)=0,"",$T29/$R29) | V29: Material de diseño (brief y drive ya completados administrativamente) | W29: 46218 | X29: =IF($W29="","",TODAY()-$W29) -> 19 | Y29: Cliente: Elvis Stefano. Dev histórico: Aarón. | Z29: =IFERROR(INDEX(Aarón!$P:$P,MATCH($C29,Aarón!$A:$A,0))&"",IFERROR(INDEX(Rubit!$P:$P,MATCH($C29,Rubit!$A:$A,0))&"",IFERROR(INDEX(Luis!$P:$P,MATCH($C29,Luis!$A:$A,0))&"",""))) | AA29: =IFERROR(INDEX(Aarón!$Q:$Q,MATCH($C29,Aarón!$A:$A,0))&"",IFERROR(INDEX(Rubit!$Q:$Q,MATCH($C29,Rubit!$A:$A,0))&"",IFERROR(INDEX(Luis!$Q:$Q,MATCH($C29,Luis!$A:$A,0))&"",""))) | AB29: =IFERROR(INDEX('Juan Carlos'!$Q:$Q,MATCH($C29,'Juan Carlos'!$A:$A,0))&"","") -> Lunes
A30: 5 | B30: 071 | C30: Teccons SAC | E30: Informativa | F30: Por definir | G30: Diseño | H30: Rubit | I30: Juan Carlos | J30: =IFERROR(INDEX('Juan Carlos'!$P:$P,MATCH($C30,'Juan Carlos'!$A:$A,0))&"","") -> Avance listo para presentar | K30: =IF($C30="","",IF($M30<>"Sí","C",IF($P30="Completo","A","B"))) -> A | L30: =IF($C30="","",IF($G30="Congelado","Congelado — mensaje cada 15 días",IF(N($X30)>15,"CONGELAR HOY",IF($M30<>"Sí","COBRAR EL 50%",IF($P30<>"Completo","PERSEGUIR MATERIAL",IF(AND($G30="Desarrollo",$N30<>"Sí"),"COBRAR EL 30%",IF(AND($G30="QA + entrega",$O30<>"Sí"),"COBRAR EL 20%",IF($G30="Cola","Listo para asignar","Al día")))))))) -> CONGELAR HOY | M30: Sí | N30: No aplica | O30: No aplica | P30: Completo | Q30: No aplica | U30: =IF(N($R30)=0,"",$T30/$R30) | V30: Material de diseño (brief y drive ya completados administrativamente) | W30: 46218 | X30: =IF($W30="","",TODAY()-$W30) -> 19 | Y30: Cliente: Jhon Cabrera Sánchez. Dev histórico: Rubit. | Z30: =IFERROR(INDEX(Aarón!$P:$P,MATCH($C30,Aarón!$A:$A,0))&"",IFERROR(INDEX(Rubit!$P:$P,MATCH($C30,Rubit!$A:$A,0))&"",IFERROR(INDEX(Luis!$P:$P,MATCH($C30,Luis!$A:$A,0))&"",""))) | AA30: =IFERROR(INDEX(Aarón!$Q:$Q,MATCH($C30,Aarón!$A:$A,0))&"",IFERROR(INDEX(Rubit!$Q:$Q,MATCH($C30,Rubit!$A:$A,0))&"",IFERROR(INDEX(Luis!$Q:$Q,MATCH($C30,Luis!$A:$A,0))&"",""))) | AB30: =IFERROR(INDEX('Juan Carlos'!$Q:$Q,MATCH($C30,'Juan Carlos'!$A:$A,0))&"","") -> avance listo
A31: 8 | B31: 073 | C31: Hasso Group | E31: E-commerce | F31: Por definir | G31: Diseño | H31: Rubit | I31: Juan Carlos | J31: =IFERROR(INDEX('Juan Carlos'!$P:$P,MATCH($C31,'Juan Carlos'!$A:$A,0))&"","") -> Material completo — iniciar diseño | K31: =IF($C31="","",IF($M31<>"Sí","C",IF($P31="Completo","A","B"))) -> A | L31: =IF($C31="","",IF($G31="Congelado","Congelado — mensaje cada 15 días",IF(N($X31)>15,"CONGELAR HOY",IF($M31<>"Sí","COBRAR EL 50%",IF($P31<>"Completo","PERSEGUIR MATERIAL",IF(AND($G31="Desarrollo",$N31<>"Sí"),"COBRAR EL 30%",IF(AND($G31="QA + entrega",$O31<>"Sí"),"COBRAR EL 20%",IF($G31="Cola","Listo para asignar","Al día")))))))) -> CONGELAR HOY | M31: Sí | N31: No aplica | O31: No aplica | P31: Completo | Q31: No enviada | U31: =IF(N($R31)=0,"",$T31/$R31) | V31: Materiales y activos del cliente para iniciar estructura de la tienda | W31: 46218 | X31: =IF($W31="","",TODAY()-$W31) -> 19 | Y31: Cliente: Sharmely Zanabria Carmona. Dev histórico: Rubit. Enviar materiales logotipos y fotos | Z31: =IFERROR(INDEX(Aarón!$P:$P,MATCH($C31,Aarón!$A:$A,0))&"",IFERROR(INDEX(Rubit!$P:$P,MATCH($C31,Rubit!$A:$A,0))&"",IFERROR(INDEX(Luis!$P:$P,MATCH($C31,Luis!$A:$A,0))&"",""))) | AA31: =IFERROR(INDEX(Aarón!$Q:$Q,MATCH($C31,Aarón!$A:$A,0))&"",IFERROR(INDEX(Rubit!$Q:$Q,MATCH($C31,Rubit!$A:$A,0))&"",IFERROR(INDEX(Luis!$Q:$Q,MATCH($C31,Luis!$A:$A,0))&"",""))) | AB31: =IFERROR(INDEX('Juan Carlos'!$Q:$Q,MATCH($C31,'Juan Carlos'!$A:$A,0))&"","")
A32: 3 | B32: 074 | C32: HSM Foods & Agro | E32: E-commerce | F32: Por definir | G32: Diseño | H32: Aarón | I32: Juan Carlos | J32: =IFERROR(INDEX('Juan Carlos'!$P:$P,MATCH($C32,'Juan Carlos'!$A:$A,0))&"","") -> Material completo — iniciar diseño | K32: =IF($C32="","",IF($M32<>"Sí","C",IF($P32="Completo","A","B"))) -> A | L32: =IF($C32="","",IF($G32="Congelado","Congelado — mensaje cada 15 días",IF(N($X32)>15,"CONGELAR HOY",IF($M32<>"Sí","COBRAR EL 50%",IF($P32<>"Completo","PERSEGUIR MATERIAL",IF(AND($G32="Desarrollo",$N32<>"Sí"),"COBRAR EL 30%",IF(AND($G32="QA + entrega",$O32<>"Sí"),"COBRAR EL 20%",IF($G32="Cola","Listo para asignar","Al día")))))))) -> CONGELAR HOY | M32: Sí | N32: No aplica | O32: No aplica | P32: Completo | Q32: Recibida con errores | R32: 110 | U32: =IF(N($R32)=0,"",$T32/$R32) -> 0 | V32: Fotos (comprometidas para la próxima semana) | W32: 46218 | X32: =IF($W32="","",TODAY()-$W32) -> 19 | Y32: Cliente: Sebastian y Mauricio. Dev histórico: Aarón. PENDIENTE: subir las fotos al Drive. Pedir en el grupo que suban el brief al Drive para que Luis lo descargue. | Z32: =IFERROR(INDEX(Aarón!$P:$P,MATCH($C32,Aarón!$A:$A,0))&"",IFERROR(INDEX(Rubit!$P:$P,MATCH($C32,Rubit!$A:$A,0))&"",IFERROR(INDEX(Luis!$P:$P,MATCH($C32,Luis!$A:$A,0))&"",""))) | AA32: =IFERROR(INDEX(Aarón!$Q:$Q,MATCH($C32,Aarón!$A:$A,0))&"",IFERROR(INDEX(Rubit!$Q:$Q,MATCH($C32,Rubit!$A:$A,0))&"",IFERROR(INDEX(Luis!$Q:$Q,MATCH($C32,Luis!$A:$A,0))&"",""))) | AB32: =IFERROR(INDEX('Juan Carlos'!$Q:$Q,MATCH($C32,'Juan Carlos'!$A:$A,0))&"","")
A33: 4 | B33: 075 | C33: Luma Home | E33: E-commerce | F33: Por definir | G33: Diseño | H33: Rubit | I33: Juan Carlos | J33: =IFERROR(INDEX('Juan Carlos'!$P:$P,MATCH($C33,'Juan Carlos'!$A:$A,0))&"","") -> Material completo — iniciar diseño | K33: =IF($C33="","",IF($M33<>"Sí","C",IF($P33="Completo","A","B"))) -> A | L33: =IF($C33="","",IF($G33="Congelado","Congelado — mensaje cada 15 días",IF(N($X33)>15,"CONGELAR HOY",IF($M33<>"Sí","COBRAR EL 50%",IF($P33<>"Completo","PERSEGUIR MATERIAL",IF(AND($G33="Desarrollo",$N33<>"Sí"),"COBRAR EL 30%",IF(AND($G33="QA + entrega",$O33<>"Sí"),"COBRAR EL 20%",IF($G33="Cola","Listo para asignar","Al día")))))))) -> CONGELAR HOY | M33: Sí | N33: No aplica | O33: No aplica | P33: Completo | Q33: No enviada | U33: =IF(N($R33)=0,"",$T33/$R33) | V33: Material de diseño (brief y drive ya completados administrativamente) | W33: 46218 | X33: =IF($W33="","",TODAY()-$W33) -> 19 | Y33: Cliente: Fatima. Dev histórico: Rubit. PENDIENTE: que envíen todo su material al Drive. | Z33: =IFERROR(INDEX(Aarón!$P:$P,MATCH($C33,Aarón!$A:$A,0))&"",IFERROR(INDEX(Rubit!$P:$P,MATCH($C33,Rubit!$A:$A,0))&"",IFERROR(INDEX(Luis!$P:$P,MATCH($C33,Luis!$A:$A,0))&"",""))) | AA33: =IFERROR(INDEX(Aarón!$Q:$Q,MATCH($C33,Aarón!$A:$A,0))&"",IFERROR(INDEX(Rubit!$Q:$Q,MATCH($C33,Rubit!$A:$A,0))&"",IFERROR(INDEX(Luis!$Q:$Q,MATCH($C33,Luis!$A:$A,0))&"",""))) | AB33: =IFERROR(INDEX('Juan Carlos'!$Q:$Q,MATCH($C33,'Juan Carlos'!$A:$A,0))&"","")
A34: 10 | B34: 076 | C34: Raul Cabana | E34: E-commerce | F34: Por definir | G34: Cola | H34: Aarón | I34: Juan Carlos | J34: =IFERROR(INDEX('Juan Carlos'!$P:$P,MATCH($C34,'Juan Carlos'!$A:$A,0))&"","") | K34: =IF($C34="","",IF($M34<>"Sí","C",IF($P34="Completo","A","B"))) -> B | L34: =IF($C34="","",IF($G34="Congelado","Congelado — mensaje cada 15 días",IF(N($X34)>15,"CONGELAR HOY",IF($M34<>"Sí","COBRAR EL 50%",IF($P34<>"Completo","PERSEGUIR MATERIAL",IF(AND($G34="Desarrollo",$N34<>"Sí"),"COBRAR EL 30%",IF(AND($G34="QA + entrega",$O34<>"Sí"),"COBRAR EL 20%",IF($G34="Cola","Listo para asignar","Al día")))))))) -> CONGELAR HOY | M34: Sí | N34: No aplica | O34: No aplica | P34: Incompleto | Q34: No enviada | U34: =IF(N($R34)=0,"",$T34/$R34) | V34: Material de diseño en general | W34: 46218 | X34: =IF($W34="","",TODAY()-$W34) -> 19 | Y34: Cliente: Raul Cabana. Dev histórico: Aarón. | Z34: =IFERROR(INDEX(Aarón!$P:$P,MATCH($C34,Aarón!$A:$A,0))&"",IFERROR(INDEX(Rubit!$P:$P,MATCH($C34,Rubit!$A:$A,0))&"",IFERROR(INDEX(Luis!$P:$P,MATCH($C34,Luis!$A:$A,0))&"",""))) | AA34: =IFERROR(INDEX(Aarón!$Q:$Q,MATCH($C34,Aarón!$A:$A,0))&"",IFERROR(INDEX(Rubit!$Q:$Q,MATCH($C34,Rubit!$A:$A,0))&"",IFERROR(INDEX(Luis!$Q:$Q,MATCH($C34,Luis!$A:$A,0))&"",""))) | AB34: =IFERROR(INDEX('Juan Carlos'!$Q:$Q,MATCH($C34,'Juan Carlos'!$A:$A,0))&"","")
B35: 077 | C35: Editora Desarrollo Humano | E35: Informativa | F35: Por definir | G35: Desarrollo | H35: Luis | I35: Juan Carlos | J35: =IFERROR(INDEX('Juan Carlos'!$P:$P,MATCH($C35,'Juan Carlos'!$A:$A,0))&"","") | K35: =IF($C35="","",IF($M35<>"Sí","C",IF($P35="Completo","A","B"))) -> C | L35: =IF($C35="","",IF($G35="Congelado","Congelado — mensaje cada 15 días",IF(N($X35)>15,"CONGELAR HOY",IF($M35<>"Sí","COBRAR EL 50%",IF($P35<>"Completo","PERSEGUIR MATERIAL",IF(AND($G35="Desarrollo",$N35<>"Sí"),"COBRAR EL 30%",IF(AND($G35="QA + entrega",$O35<>"Sí"),"COBRAR EL 20%",IF($G35="Cola","Listo para asignar","Al día")))))))) -> CONGELAR HOY | M35: No aplica | N35: No aplica | O35: No aplica | P35: Incompleto | Q35: No aplica | U35: =IF(N($R35)=0,"",$T35/$R35) | V35: Material de diseño / contenidos (proyecto de branding + intranet + LMS) | W35: 46218 | X35: =IF($W35="","",TODAY()-$W35) -> 19 | Y35: Cliente: Maria Gracia. Luis mencionado como responsable — capacidad 0 según Reglas, confirmar quién lo lleva en la práctica. | Z35: =IFERROR(INDEX(Aarón!$P:$P,MATCH($C35,Aarón!$A:$A,0))&"",IFERROR(INDEX(Rubit!$P:$P,MATCH($C35,Rubit!$A:$A,0))&"",IFERROR(INDEX(Luis!$P:$P,MATCH($C35,Luis!$A:$A,0))&"",""))) | AA35: =IFERROR(INDEX(Aarón!$Q:$Q,MATCH($C35,Aarón!$A:$A,0))&"",IFERROR(INDEX(Rubit!$Q:$Q,MATCH($C35,Rubit!$A:$A,0))&"",IFERROR(INDEX(Luis!$Q:$Q,MATCH($C35,Luis!$A:$A,0))&"",""))) | AB35: =IFERROR(INDEX('Juan Carlos'!$Q:$Q,MATCH($C35,'Juan Carlos'!$A:$A,0))&"","")
B36: 078 | C36: Guardiania Total 360 | E36: Informativa | F36: Por definir | G36: Esperando material | H36: Rubit | I36: Juan Carlos | J36: =IFERROR(INDEX('Juan Carlos'!$P:$P,MATCH($C36,'Juan Carlos'!$A:$A,0))&"","") | K36: =IF($C36="","",IF($M36<>"Sí","C",IF($P36="Completo","A","B"))) -> B | L36: =IF($C36="","",IF($G36="Congelado","Congelado — mensaje cada 15 días",IF(N($X36)>15,"CONGELAR HOY",IF($M36<>"Sí","COBRAR EL 50%",IF($P36<>"Completo","PERSEGUIR MATERIAL",IF(AND($G36="Desarrollo",$N36<>"Sí"),"COBRAR EL 30%",IF(AND($G36="QA + entrega",$O36<>"Sí"),"COBRAR EL 20%",IF($G36="Cola","Listo para asignar","Al día")))))))) -> CONGELAR HOY | M36: Sí | N36: No aplica | O36: No aplica | P36: Incompleto | Q36: No aplica | U36: =IF(N($R36)=0,"",$T36/$R36) | V36: Material de diseño en general | W36: 46218 | X36: =IF($W36="","",TODAY()-$W36) -> 19 | Y36: Cliente: Kenny. Dev histórico: Rubit. | Z36: =IFERROR(INDEX(Aarón!$P:$P,MATCH($C36,Aarón!$A:$A,0))&"",IFERROR(INDEX(Rubit!$P:$P,MATCH($C36,Rubit!$A:$A,0))&"",IFERROR(INDEX(Luis!$P:$P,MATCH($C36,Luis!$A:$A,0))&"",""))) | AA36: =IFERROR(INDEX(Aarón!$Q:$Q,MATCH($C36,Aarón!$A:$A,0))&"",IFERROR(INDEX(Rubit!$Q:$Q,MATCH($C36,Rubit!$A:$A,0))&"",IFERROR(INDEX(Luis!$Q:$Q,MATCH($C36,Luis!$A:$A,0))&"",""))) | AB36: =IFERROR(INDEX('Juan Carlos'!$Q:$Q,MATCH($C36,'Juan Carlos'!$A:$A,0))&"","")
B37: 079 | C37: Doctor G | E37: Informativa | F37: Por definir | G37: Cola | H37: Aarón | I37: Juan Carlos | J37: =IFERROR(INDEX('Juan Carlos'!$P:$P,MATCH($C37,'Juan Carlos'!$A:$A,0))&"","") | K37: =IF($C37="","",IF($M37<>"Sí","C",IF($P37="Completo","A","B"))) -> A | L37: =IF($C37="","",IF($G37="Congelado","Congelado — mensaje cada 15 días",IF(N($X37)>15,"CONGELAR HOY",IF($M37<>"Sí","COBRAR EL 50%",IF($P37<>"Completo","PERSEGUIR MATERIAL",IF(AND($G37="Desarrollo",$N37<>"Sí"),"COBRAR EL 30%",IF(AND($G37="QA + entrega",$O37<>"Sí"),"COBRAR EL 20%",IF($G37="Cola","Listo para asignar","Al día")))))))) -> Listo para asignar | M37: Sí | N37: No aplica | O37: No aplica | P37: Completo | Q37: No aplica | U37: =IF(N($R37)=0,"",$T37/$R37) | V37: Todo — sin información registrada aún | X37: =IF($W37="","",TODAY()-$W37) | Y37: Dev histórico: Aarón. Cliente sin identificar en los registros — confirmar nombre. Viernes 24/07 cinco pm | Z37: =IFERROR(INDEX(Aarón!$P:$P,MATCH($C37,Aarón!$A:$A,0))&"",IFERROR(INDEX(Rubit!$P:$P,MATCH($C37,Rubit!$A:$A,0))&"",IFERROR(INDEX(Luis!$P:$P,MATCH($C37,Luis!$A:$A,0))&"",""))) | AA37: =IFERROR(INDEX(Aarón!$Q:$Q,MATCH($C37,Aarón!$A:$A,0))&"",IFERROR(INDEX(Rubit!$Q:$Q,MATCH($C37,Rubit!$A:$A,0))&"",IFERROR(INDEX(Luis!$Q:$Q,MATCH($C37,Luis!$A:$A,0))&"",""))) | AB37: =IFERROR(INDEX('Juan Carlos'!$Q:$Q,MATCH($C37,'Juan Carlos'!$A:$A,0))&"","")
C38: Alpen Ingenieros | E38: Informativa | F38: Por definir | G38: Cerrado | H38: Luis | I38: Juan Carlos | J38: =IFERROR(INDEX('Juan Carlos'!$P:$P,MATCH($C38,'Juan Carlos'!$A:$A,0))&"","") | K38: =IF($C38="","",IF($M38<>"Sí","C",IF($P38="Completo","A","B"))) -> A | L38: =IF($C38="","",IF($G38="Congelado","Congelado — mensaje cada 15 días",IF(N($X38)>15,"CONGELAR HOY",IF($M38<>"Sí","COBRAR EL 50%",IF($P38<>"Completo","PERSEGUIR MATERIAL",IF(AND($G38="Desarrollo",$N38<>"Sí"),"COBRAR EL 30%",IF(AND($G38="QA + entrega",$O38<>"Sí"),"COBRAR EL 20%",IF($G38="Cola","Listo para asignar","Al día")))))))) -> Al día | M38: Sí | N38: Sí | O38: Sí | P38: Completo | Q38: No aplica | U38: =IF(N($R38)=0,"",$T38/$R38) | V38: Todo — lead sin pago ni código | X38: =IF($W38="","",TODAY()-$W38) | Y38: Cliente: Leonardo. | Z38: =IFERROR(INDEX(Aarón!$P:$P,MATCH($C38,Aarón!$A:$A,0))&"",IFERROR(INDEX(Rubit!$P:$P,MATCH($C38,Rubit!$A:$A,0))&"",IFERROR(INDEX(Luis!$P:$P,MATCH($C38,Luis!$A:$A,0))&"",""))) | AA38: =IFERROR(INDEX(Aarón!$Q:$Q,MATCH($C38,Aarón!$A:$A,0))&"",IFERROR(INDEX(Rubit!$Q:$Q,MATCH($C38,Rubit!$A:$A,0))&"",IFERROR(INDEX(Luis!$Q:$Q,MATCH($C38,Luis!$A:$A,0))&"",""))) | AB38: =IFERROR(INDEX('Juan Carlos'!$Q:$Q,MATCH($C38,'Juan Carlos'!$A:$A,0))&"","")
C39: Evi | E39: E-commerce | F39: Por definir | G39: Cerrado | H39: Luis | I39: Juan Carlos | J39: =IFERROR(INDEX('Juan Carlos'!$P:$P,MATCH($C39,'Juan Carlos'!$A:$A,0))&"","") | K39: =IF($C39="","",IF($M39<>"Sí","C",IF($P39="Completo","A","B"))) -> A | L39: =IF($C39="","",IF($G39="Congelado","Congelado — mensaje cada 15 días",IF(N($X39)>15,"CONGELAR HOY",IF($M39<>"Sí","COBRAR EL 50%",IF($P39<>"Completo","PERSEGUIR MATERIAL",IF(AND($G39="Desarrollo",$N39<>"Sí"),"COBRAR EL 30%",IF(AND($G39="QA + entrega",$O39<>"Sí"),"COBRAR EL 20%",IF($G39="Cola","Listo para asignar","Al día")))))))) -> Al día | M39: Sí | N39: Sí | O39: Sí | P39: Completo | Q39: Recibida y validada | U39: =IF(N($R39)=0,"",$T39/$R39) | V39: Todo — lead sin pago ni código | X39: =IF($W39="","",TODAY()-$W39) | Y39: Cliente: Evi. | Z39: =IFERROR(INDEX(Aarón!$P:$P,MATCH($C39,Aarón!$A:$A,0))&"",IFERROR(INDEX(Rubit!$P:$P,MATCH($C39,Rubit!$A:$A,0))&"",IFERROR(INDEX(Luis!$P:$P,MATCH($C39,Luis!$A:$A,0))&"",""))) | AA39: =IFERROR(INDEX(Aarón!$Q:$Q,MATCH($C39,Aarón!$A:$A,0))&"",IFERROR(INDEX(Rubit!$Q:$Q,MATCH($C39,Rubit!$A:$A,0))&"",IFERROR(INDEX(Luis!$Q:$Q,MATCH($C39,Luis!$A:$A,0))&"",""))) | AB39: =IFERROR(INDEX('Juan Carlos'!$Q:$Q,MATCH($C39,'Juan Carlos'!$A:$A,0))&"","")
C40: WJ Repuestos | E40: E-commerce | F40: Por definir | G40: Cerrado | H40: Aarón | I40: Juan Carlos | J40: =IFERROR(INDEX('Juan Carlos'!$P:$P,MATCH($C40,'Juan Carlos'!$A:$A,0))&"","") | K40: =IF($C40="","",IF($M40<>"Sí","C",IF($P40="Completo","A","B"))) -> A | L40: =IF($C40="","",IF($G40="Congelado","Congelado — mensaje cada 15 días",IF(N($X40)>15,"CONGELAR HOY",IF($M40<>"Sí","COBRAR EL 50%",IF($P40<>"Completo","PERSEGUIR MATERIAL",IF(AND($G40="Desarrollo",$N40<>"Sí"),"COBRAR EL 30%",IF(AND($G40="QA + entrega",$O40<>"Sí"),"COBRAR EL 20%",IF($G40="Cola","Listo para asignar","Al día")))))))) -> Al día | M40: Sí | N40: Sí | O40: Sí | P40: Completo | Q40: Recibida y validada | U40: =IF(N($R40)=0,"",$T40/$R40) | V40: Todo — lead sin pago ni código | X40: =IF($W40="","",TODAY()-$W40) | Y40: Cliente: Mariajose y Jon. | Z40: =IFERROR(INDEX(Aarón!$P:$P,MATCH($C40,Aarón!$A:$A,0))&"",IFERROR(INDEX(Rubit!$P:$P,MATCH($C40,Rubit!$A:$A,0))&"",IFERROR(INDEX(Luis!$P:$P,MATCH($C40,Luis!$A:$A,0))&"",""))) | AA40: =IFERROR(INDEX(Aarón!$Q:$Q,MATCH($C40,Aarón!$A:$A,0))&"",IFERROR(INDEX(Rubit!$Q:$Q,MATCH($C40,Rubit!$A:$A,0))&"",IFERROR(INDEX(Luis!$Q:$Q,MATCH($C40,Luis!$A:$A,0))&"",""))) | AB40: =IFERROR(INDEX('Juan Carlos'!$Q:$Q,MATCH($C40,'Juan Carlos'!$A:$A,0))&"","")
C41: Bellucci | E41: E-commerce | F41: Por definir | G41: Cerrado | H41: Aarón | I41: Juan Carlos | J41: =IFERROR(INDEX('Juan Carlos'!$P:$P,MATCH($C41,'Juan Carlos'!$A:$A,0))&"","") -> Diseño finalizado | K41: =IF($C41="","",IF($M41<>"Sí","C",IF($P41="Completo","A","B"))) -> A | L41: =IF($C41="","",IF($G41="Congelado","Congelado — mensaje cada 15 días",IF(N($X41)>15,"CONGELAR HOY",IF($M41<>"Sí","COBRAR EL 50%",IF($P41<>"Completo","PERSEGUIR MATERIAL",IF(AND($G41="Desarrollo",$N41<>"Sí"),"COBRAR EL 30%",IF(AND($G41="QA + entrega",$O41<>"Sí"),"COBRAR EL 20%",IF($G41="Cola","Listo para asignar","Al día")))))))) -> Al día | M41: Sí | N41: Sí | O41: Sí | P41: Completo | Q41: Recibida y validada | S41: faltante | U41: =IF(N($R41)=0,"",$T41/$R41) | V41: Todo — lead sin pago ni código | X41: =IF($W41="","",TODAY()-$W41) | Y41: Cliente: Joselyn Mendoza Vasquez. | Z41: =IFERROR(INDEX(Aarón!$P:$P,MATCH($C41,Aarón!$A:$A,0))&"",IFERROR(INDEX(Rubit!$P:$P,MATCH($C41,Rubit!$A:$A,0))&"",IFERROR(INDEX(Luis!$P:$P,MATCH($C41,Luis!$A:$A,0))&"",""))) | AA41: =IFERROR(INDEX(Aarón!$Q:$Q,MATCH($C41,Aarón!$A:$A,0))&"",IFERROR(INDEX(Rubit!$Q:$Q,MATCH($C41,Rubit!$A:$A,0))&"",IFERROR(INDEX(Luis!$Q:$Q,MATCH($C41,Luis!$A:$A,0))&"",""))) | AB41: =IFERROR(INDEX('Juan Carlos'!$Q:$Q,MATCH($C41,'Juan Carlos'!$A:$A,0))&"","")
C42: Proyectos Inversiones | E42: Informativa | F42: Por definir | G42: Cerrado | H42: Luis | I42: Juan Carlos | J42: =IFERROR(INDEX('Juan Carlos'!$P:$P,MATCH($C42,'Juan Carlos'!$A:$A,0))&"","") | K42: =IF($C42="","",IF($M42<>"Sí","C",IF($P42="Completo","A","B"))) -> A | L42: =IF($C42="","",IF($G42="Congelado","Congelado — mensaje cada 15 días",IF(N($X42)>15,"CONGELAR HOY",IF($M42<>"Sí","COBRAR EL 50%",IF($P42<>"Completo","PERSEGUIR MATERIAL",IF(AND($G42="Desarrollo",$N42<>"Sí"),"COBRAR EL 30%",IF(AND($G42="QA + entrega",$O42<>"Sí"),"COBRAR EL 20%",IF($G42="Cola","Listo para asignar","Al día")))))))) -> Al día | M42: Sí | N42: Sí | O42: Sí | P42: Completo | Q42: No aplica | U42: =IF(N($R42)=0,"",$T42/$R42) | V42: Todo — lead sin pago ni código (web + app) | X42: =IF($W42="","",TODAY()-$W42) | Y42: Cliente: Yoverth. | Z42: =IFERROR(INDEX(Aarón!$P:$P,MATCH($C42,Aarón!$A:$A,0))&"",IFERROR(INDEX(Rubit!$P:$P,MATCH($C42,Rubit!$A:$A,0))&"",IFERROR(INDEX(Luis!$P:$P,MATCH($C42,Luis!$A:$A,0))&"",""))) | AA42: =IFERROR(INDEX(Aarón!$Q:$Q,MATCH($C42,Aarón!$A:$A,0))&"",IFERROR(INDEX(Rubit!$Q:$Q,MATCH($C42,Rubit!$A:$A,0))&"",IFERROR(INDEX(Luis!$Q:$Q,MATCH($C42,Luis!$A:$A,0))&"",""))) | AB42: =IFERROR(INDEX('Juan Carlos'!$Q:$Q,MATCH($C42,'Juan Carlos'!$A:$A,0))&"","")
C43: Perlita Jeans | E43: E-commerce | F43: Shopify | G43: Cerrado | H43: Aarón | I43: Juan Carlos | J43: =IFERROR(INDEX('Juan Carlos'!$P:$P,MATCH($C43,'Juan Carlos'!$A:$A,0))&"","") | K43: =IF($C43="","",IF($M43<>"Sí","C",IF($P43="Completo","A","B"))) -> A | L43: =IF($C43="","",IF($G43="Congelado","Congelado — mensaje cada 15 días",IF(N($X43)>15,"CONGELAR HOY",IF($M43<>"Sí","COBRAR EL 50%",IF($P43<>"Completo","PERSEGUIR MATERIAL",IF(AND($G43="Desarrollo",$N43<>"Sí"),"COBRAR EL 30%",IF(AND($G43="QA + entrega",$O43<>"Sí"),"COBRAR EL 20%",IF($G43="Cola","Listo para asignar","Al día")))))))) -> Al día | M43: Sí | N43: Sí | O43: Sí | P43: Completo | Q43: Recibida y validada | U43: =IF(N($R43)=0,"",$T43/$R43) | V43: Todo — lead sin pago ni código (Shopify) | X43: =IF($W43="","",TODAY()-$W43) | Y43: Cliente: Rolando. | Z43: =IFERROR(INDEX(Aarón!$P:$P,MATCH($C43,Aarón!$A:$A,0))&"",IFERROR(INDEX(Rubit!$P:$P,MATCH($C43,Rubit!$A:$A,0))&"",IFERROR(INDEX(Luis!$P:$P,MATCH($C43,Luis!$A:$A,0))&"",""))) | AA43: =IFERROR(INDEX(Aarón!$Q:$Q,MATCH($C43,Aarón!$A:$A,0))&"",IFERROR(INDEX(Rubit!$Q:$Q,MATCH($C43,Rubit!$A:$A,0))&"",IFERROR(INDEX(Luis!$Q:$Q,MATCH($C43,Luis!$A:$A,0))&"",""))) | AB43: =IFERROR(INDEX('Juan Carlos'!$Q:$Q,MATCH($C43,'Juan Carlos'!$A:$A,0))&"","")
C44: The Mouse | E44: E-commerce | F44: Por definir | G44: Cerrado | H44: Luis | I44: Juan Carlos | J44: =IFERROR(INDEX('Juan Carlos'!$P:$P,MATCH($C44,'Juan Carlos'!$A:$A,0))&"","") | K44: =IF($C44="","",IF($M44<>"Sí","C",IF($P44="Completo","A","B"))) -> A | L44: =IF($C44="","",IF($G44="Congelado","Congelado — mensaje cada 15 días",IF(N($X44)>15,"CONGELAR HOY",IF($M44<>"Sí","COBRAR EL 50%",IF($P44<>"Completo","PERSEGUIR MATERIAL",IF(AND($G44="Desarrollo",$N44<>"Sí"),"COBRAR EL 30%",IF(AND($G44="QA + entrega",$O44<>"Sí"),"COBRAR EL 20%",IF($G44="Cola","Listo para asignar","Al día")))))))) -> Al día | M44: Sí | N44: Sí | O44: Sí | P44: Completo | Q44: Recibida y validada | U44: =IF(N($R44)=0,"",$T44/$R44) | V44: Todo — lead sin pago ni código | X44: =IF($W44="","",TODAY()-$W44) | Y44: Cliente: Edwin Montero. | Z44: =IFERROR(INDEX(Aarón!$P:$P,MATCH($C44,Aarón!$A:$A,0))&"",IFERROR(INDEX(Rubit!$P:$P,MATCH($C44,Rubit!$A:$A,0))&"",IFERROR(INDEX(Luis!$P:$P,MATCH($C44,Luis!$A:$A,0))&"",""))) | AA44: =IFERROR(INDEX(Aarón!$Q:$Q,MATCH($C44,Aarón!$A:$A,0))&"",IFERROR(INDEX(Rubit!$Q:$Q,MATCH($C44,Rubit!$A:$A,0))&"",IFERROR(INDEX(Luis!$Q:$Q,MATCH($C44,Luis!$A:$A,0))&"",""))) | AB44: =IFERROR(INDEX('Juan Carlos'!$Q:$Q,MATCH($C44,'Juan Carlos'!$A:$A,0))&"","")
C45: DiaGo Confecciones | E45: E-commerce | F45: Por definir | G45: Cerrado | H45: Aarón | I45: Juan Carlos | J45: =IFERROR(INDEX('Juan Carlos'!$P:$P,MATCH($C45,'Juan Carlos'!$A:$A,0))&"","") | K45: =IF($C45="","",IF($M45<>"Sí","C",IF($P45="Completo","A","B"))) -> A | L45: =IF($C45="","",IF($G45="Congelado","Congelado — mensaje cada 15 días",IF(N($X45)>15,"CONGELAR HOY",IF($M45<>"Sí","COBRAR EL 50%",IF($P45<>"Completo","PERSEGUIR MATERIAL",IF(AND($G45="Desarrollo",$N45<>"Sí"),"COBRAR EL 30%",IF(AND($G45="QA + entrega",$O45<>"Sí"),"COBRAR EL 20%",IF($G45="Cola","Listo para asignar","Al día")))))))) -> Al día | M45: Sí | N45: Sí | O45: Sí | P45: Completo | Q45: Recibida y validada | U45: =IF(N($R45)=0,"",$T45/$R45) | V45: Todo — lead sin pago ni código (informativa + branding) | X45: =IF($W45="","",TODAY()-$W45) | Y45: Cliente: Sonia Mamani. | Z45: =IFERROR(INDEX(Aarón!$P:$P,MATCH($C45,Aarón!$A:$A,0))&"",IFERROR(INDEX(Rubit!$P:$P,MATCH($C45,Rubit!$A:$A,0))&"",IFERROR(INDEX(Luis!$P:$P,MATCH($C45,Luis!$A:$A,0))&"",""))) | AA45: =IFERROR(INDEX(Aarón!$Q:$Q,MATCH($C45,Aarón!$A:$A,0))&"",IFERROR(INDEX(Rubit!$Q:$Q,MATCH($C45,Rubit!$A:$A,0))&"",IFERROR(INDEX(Luis!$Q:$Q,MATCH($C45,Luis!$A:$A,0))&"",""))) | AB45: =IFERROR(INDEX('Juan Carlos'!$Q:$Q,MATCH($C45,'Juan Carlos'!$A:$A,0))&"","")
C46: Time Motors Chew | E46: E-commerce | F46: Por definir | G46: Cerrado | H46: Aarón | I46: Juan Carlos | J46: =IFERROR(INDEX('Juan Carlos'!$P:$P,MATCH($C46,'Juan Carlos'!$A:$A,0))&"","") | K46: =IF($C46="","",IF($M46<>"Sí","C",IF($P46="Completo","A","B"))) -> A | L46: =IF($C46="","",IF($G46="Congelado","Congelado — mensaje cada 15 días",IF(N($X46)>15,"CONGELAR HOY",IF($M46<>"Sí","COBRAR EL 50%",IF($P46<>"Completo","PERSEGUIR MATERIAL",IF(AND($G46="Desarrollo",$N46<>"Sí"),"COBRAR EL 30%",IF(AND($G46="QA + entrega",$O46<>"Sí"),"COBRAR EL 20%",IF($G46="Cola","Listo para asignar","Al día")))))))) -> Al día | M46: Sí | N46: Sí | O46: Sí | P46: Completo | Q46: Recibida y validada | U46: =IF(N($R46)=0,"",$T46/$R46) | V46: Todo — lead sin pago ni código | X46: =IF($W46="","",TODAY()-$W46) | Y46: Cliente: Deysi. | Z46: =IFERROR(INDEX(Aarón!$P:$P,MATCH($C46,Aarón!$A:$A,0))&"",IFERROR(INDEX(Rubit!$P:$P,MATCH($C46,Rubit!$A:$A,0))&"",IFERROR(INDEX(Luis!$P:$P,MATCH($C46,Luis!$A:$A,0))&"",""))) | AA46: =IFERROR(INDEX(Aarón!$Q:$Q,MATCH($C46,Aarón!$A:$A,0))&"",IFERROR(INDEX(Rubit!$Q:$Q,MATCH($C46,Rubit!$A:$A,0))&"",IFERROR(INDEX(Luis!$Q:$Q,MATCH($C46,Luis!$A:$A,0))&"",""))) | AB46: =IFERROR(INDEX('Juan Carlos'!$Q:$Q,MATCH($C46,'Juan Carlos'!$A:$A,0))&"","")
C47: Hueda | E47: E-commerce | F47: Por definir | G47: Cerrado | H47: Luis | I47: Juan Carlos | J47: =IFERROR(INDEX('Juan Carlos'!$P:$P,MATCH($C47,'Juan Carlos'!$A:$A,0))&"","") | K47: =IF($C47="","",IF($M47<>"Sí","C",IF($P47="Completo","A","B"))) -> A | L47: =IF($C47="","",IF($G47="Congelado","Congelado — mensaje cada 15 días",IF(N($X47)>15,"CONGELAR HOY",IF($M47<>"Sí","COBRAR EL 50%",IF($P47<>"Completo","PERSEGUIR MATERIAL",IF(AND($G47="Desarrollo",$N47<>"Sí"),"COBRAR EL 30%",IF(AND($G47="QA + entrega",$O47<>"Sí"),"COBRAR EL 20%",IF($G47="Cola","Listo para asignar","Al día")))))))) -> Al día | M47: Sí | N47: Sí | O47: Sí | P47: Completo | Q47: Recibida y validada | U47: =IF(N($R47)=0,"",$T47/$R47) | V47: Todo — lead sin pago ni código | X47: =IF($W47="","",TODAY()-$W47) | Y47: Cliente: Sayuri Hueda. Falta Capacitacion | Z47: =IFERROR(INDEX(Aarón!$P:$P,MATCH($C47,Aarón!$A:$A,0))&"",IFERROR(INDEX(Rubit!$P:$P,MATCH($C47,Rubit!$A:$A,0))&"",IFERROR(INDEX(Luis!$P:$P,MATCH($C47,Luis!$A:$A,0))&"",""))) | AA47: =IFERROR(INDEX(Aarón!$Q:$Q,MATCH($C47,Aarón!$A:$A,0))&"",IFERROR(INDEX(Rubit!$Q:$Q,MATCH($C47,Rubit!$A:$A,0))&"",IFERROR(INDEX(Luis!$Q:$Q,MATCH($C47,Luis!$A:$A,0))&"",""))) | AB47: =IFERROR(INDEX('Juan Carlos'!$Q:$Q,MATCH($C47,'Juan Carlos'!$A:$A,0))&"","")
C48: Jump Fit Dance | E48: E-commerce | F48: Por definir | G48: Cerrado | H48: Luis | I48: Juan Carlos | J48: =IFERROR(INDEX('Juan Carlos'!$P:$P,MATCH($C48,'Juan Carlos'!$A:$A,0))&"","") | K48: =IF($C48="","",IF($M48<>"Sí","C",IF($P48="Completo","A","B"))) -> A | L48: =IF($C48="","",IF($G48="Congelado","Congelado — mensaje cada 15 días",IF(N($X48)>15,"CONGELAR HOY",IF($M48<>"Sí","COBRAR EL 50%",IF($P48<>"Completo","PERSEGUIR MATERIAL",IF(AND($G48="Desarrollo",$N48<>"Sí"),"COBRAR EL 30%",IF(AND($G48="QA + entrega",$O48<>"Sí"),"COBRAR EL 20%",IF($G48="Cola","Listo para asignar","Al día")))))))) -> Al día | M48: Sí | N48: Sí | O48: Sí | P48: Completo | Q48: Recibida y validada | U48: =IF(N($R48)=0,"",$T48/$R48) | V48: Todo — lead sin pago ni código | X48: =IF($W48="","",TODAY()-$W48) | Y48: Cliente: Glaussia. | Z48: =IFERROR(INDEX(Aarón!$P:$P,MATCH($C48,Aarón!$A:$A,0))&"",IFERROR(INDEX(Rubit!$P:$P,MATCH($C48,Rubit!$A:$A,0))&"",IFERROR(INDEX(Luis!$P:$P,MATCH($C48,Luis!$A:$A,0))&"",""))) | AA48: =IFERROR(INDEX(Aarón!$Q:$Q,MATCH($C48,Aarón!$A:$A,0))&"",IFERROR(INDEX(Rubit!$Q:$Q,MATCH($C48,Rubit!$A:$A,0))&"",IFERROR(INDEX(Luis!$Q:$Q,MATCH($C48,Luis!$A:$A,0))&"",""))) | AB48: =IFERROR(INDEX('Juan Carlos'!$Q:$Q,MATCH($C48,'Juan Carlos'!$A:$A,0))&"","")
C49: Grizell Romero | E49: Informativa | F49: Por definir | G49: Cerrado | H49: Aarón | I49: Juan Carlos | J49: =IFERROR(INDEX('Juan Carlos'!$P:$P,MATCH($C49,'Juan Carlos'!$A:$A,0))&"","") | K49: =IF($C49="","",IF($M49<>"Sí","C",IF($P49="Completo","A","B"))) -> A | L49: =IF($C49="","",IF($G49="Congelado","Congelado — mensaje cada 15 días",IF(N($X49)>15,"CONGELAR HOY",IF($M49<>"Sí","COBRAR EL 50%",IF($P49<>"Completo","PERSEGUIR MATERIAL",IF(AND($G49="Desarrollo",$N49<>"Sí"),"COBRAR EL 30%",IF(AND($G49="QA + entrega",$O49<>"Sí"),"COBRAR EL 20%",IF($G49="Cola","Listo para asignar","Al día")))))))) -> Al día | M49: Sí | N49: Sí | O49: Sí | P49: Completo | Q49: No aplica | U49: =IF(N($R49)=0,"",$T49/$R49) | V49: Todo — lead sin pago ni código | X49: =IF($W49="","",TODAY()-$W49) | Y49: Cliente: Meilyn Chang. | Z49: =IFERROR(INDEX(Aarón!$P:$P,MATCH($C49,Aarón!$A:$A,0))&"",IFERROR(INDEX(Rubit!$P:$P,MATCH($C49,Rubit!$A:$A,0))&"",IFERROR(INDEX(Luis!$P:$P,MATCH($C49,Luis!$A:$A,0))&"",""))) | AA49: =IFERROR(INDEX(Aarón!$Q:$Q,MATCH($C49,Aarón!$A:$A,0))&"",IFERROR(INDEX(Rubit!$Q:$Q,MATCH($C49,Rubit!$A:$A,0))&"",IFERROR(INDEX(Luis!$Q:$Q,MATCH($C49,Luis!$A:$A,0))&"",""))) | AB49: =IFERROR(INDEX('Juan Carlos'!$Q:$Q,MATCH($C49,'Juan Carlos'!$A:$A,0))&"","")
C50: The Mining Club | E50: E-commerce | F50: Por definir | G50: Congelado | H50: Aarón | I50: Juan Carlos | J50: =IFERROR(INDEX('Juan Carlos'!$P:$P,MATCH($C50,'Juan Carlos'!$A:$A,0))&"","") | K50: =IF($C50="","",IF($M50<>"Sí","C",IF($P50="Completo","A","B"))) -> B | L50: =IF($C50="","",IF($G50="Congelado","Congelado — mensaje cada 15 días",IF(N($X50)>15,"CONGELAR HOY",IF($M50<>"Sí","COBRAR EL 50%",IF($P50<>"Completo","PERSEGUIR MATERIAL",IF(AND($G50="Desarrollo",$N50<>"Sí"),"COBRAR EL 30%",IF(AND($G50="QA + entrega",$O50<>"Sí"),"COBRAR EL 20%",IF($G50="Cola","Listo para asignar","Al día")))))))) -> Congelado — mensaje cada 15 días | M50: Sí | N50: Sí | O50: No | P50: Nada | Q50: No aplica | U50: =IF(N($R50)=0,"",$T50/$R50) | V50: Todo — lead sin pago ni código | X50: =IF($W50="","",TODAY()-$W50) | Y50: Cliente: Carlos. Recuperado de la hoja de Aarón (no estaba en Proyectos). | Z50: =IFERROR(INDEX(Aarón!$P:$P,MATCH($C50,Aarón!$A:$A,0))&"",IFERROR(INDEX(Rubit!$P:$P,MATCH($C50,Rubit!$A:$A,0))&"",IFERROR(INDEX(Luis!$P:$P,MATCH($C50,Luis!$A:$A,0))&"",""))) | AA50: =IFERROR(INDEX(Aarón!$Q:$Q,MATCH($C50,Aarón!$A:$A,0))&"",IFERROR(INDEX(Rubit!$Q:$Q,MATCH($C50,Rubit!$A:$A,0))&"",IFERROR(INDEX(Luis!$Q:$Q,MATCH($C50,Luis!$A:$A,0))&"",""))) | AB50: =IFERROR(INDEX('Juan Carlos'!$Q:$Q,MATCH($C50,'Juan Carlos'!$A:$A,0))&"","")
C51: Industrial Protection | E51: E-commerce | F51: Por definir | G51: Congelado | H51: Aarón | I51: Juan Carlos | J51: =IFERROR(INDEX('Juan Carlos'!$P:$P,MATCH($C51,'Juan Carlos'!$A:$A,0))&"","") | K51: =IF($C51="","",IF($M51<>"Sí","C",IF($P51="Completo","A","B"))) -> B | L51: =IF($C51="","",IF($G51="Congelado","Congelado — mensaje cada 15 días",IF(N($X51)>15,"CONGELAR HOY",IF($M51<>"Sí","COBRAR EL 50%",IF($P51<>"Completo","PERSEGUIR MATERIAL",IF(AND($G51="Desarrollo",$N51<>"Sí"),"COBRAR EL 30%",IF(AND($G51="QA + entrega",$O51<>"Sí"),"COBRAR EL 20%",IF($G51="Cola","Listo para asignar","Al día")))))))) -> Congelado — mensaje cada 15 días | M51: Sí | N51: No | O51: No | P51: Nada | Q51: No aplica | U51: =IF(N($R51)=0,"",$T51/$R51) | V51: Todo — lead sin pago ni código | X51: =IF($W51="","",TODAY()-$W51) | Y51: Cliente: Rugui. Primer contacto registrado 5/6/2026. Recuperado de la hoja de Aarón (no estaba en Proyectos). | Z51: =IFERROR(INDEX(Aarón!$P:$P,MATCH($C51,Aarón!$A:$A,0))&"",IFERROR(INDEX(Rubit!$P:$P,MATCH($C51,Rubit!$A:$A,0))&"",IFERROR(INDEX(Luis!$P:$P,MATCH($C51,Luis!$A:$A,0))&"",""))) | AA51: =IFERROR(INDEX(Aarón!$Q:$Q,MATCH($C51,Aarón!$A:$A,0))&"",IFERROR(INDEX(Rubit!$Q:$Q,MATCH($C51,Rubit!$A:$A,0))&"",IFERROR(INDEX(Luis!$Q:$Q,MATCH($C51,Luis!$A:$A,0))&"",""))) | AB51: =IFERROR(INDEX('Juan Carlos'!$Q:$Q,MATCH($C51,'Juan Carlos'!$A:$A,0))&"","")
J52: =IFERROR(INDEX('Juan Carlos'!$P:$P,MATCH($C52,'Juan Carlos'!$A:$A,0))&"","") | K52: =IF($C52="","",IF($M52<>"Sí","C",IF($P52="Completo","A","B"))) | L52: =IF($C52="","",IF($G52="Congelado","Congelado — mensaje cada 15 días",IF(N($X52)>15,"CONGELAR HOY",IF($M52<>"Sí","COBRAR EL 50%",IF($P52<>"Completo","PERSEGUIR MATERIAL",IF(AND($G52="Desarrollo",$N52<>"Sí"),"COBRAR EL 30%",IF(AND($G52="QA + entrega",$O52<>"Sí"),"COBRAR EL 20%",IF($G52="Cola","Listo para asignar","Al día")))))))) | U52: =IF(N($R52)=0,"",$T52/$R52) | X52: =IF($W52="","",TODAY()-$W52) | Z52: =IFERROR(INDEX(Aarón!$P:$P,MATCH($C52,Aarón!$A:$A,0))&"",IFERROR(INDEX(Rubit!$P:$P,MATCH($C52,Rubit!$A:$A,0))&"",IFERROR(INDEX(Luis!$P:$P,MATCH($C52,Luis!$A:$A,0))&"",""))) | AA52: =IFERROR(INDEX(Aarón!$Q:$Q,MATCH($C52,Aarón!$A:$A,0))&"",IFERROR(INDEX(Rubit!$Q:$Q,MATCH($C52,Rubit!$A:$A,0))&"",IFERROR(INDEX(Luis!$Q:$Q,MATCH($C52,Luis!$A:$A,0))&"",""))) | AB52: =IFERROR(INDEX('Juan Carlos'!$Q:$Q,MATCH($C52,'Juan Carlos'!$A:$A,0))&"","")
J53: =IFERROR(INDEX('Juan Carlos'!$P:$P,MATCH($C53,'Juan Carlos'!$A:$A,0))&"","") | K53: =IF($C53="","",IF($M53<>"Sí","C",IF($P53="Completo","A","B"))) | L53: =IF($C53="","",IF($G53="Congelado","Congelado — mensaje cada 15 días",IF(N($X53)>15,"CONGELAR HOY",IF($M53<>"Sí","COBRAR EL 50%",IF($P53<>"Completo","PERSEGUIR MATERIAL",IF(AND($G53="Desarrollo",$N53<>"Sí"),"COBRAR EL 30%",IF(AND($G53="QA + entrega",$O53<>"Sí"),"COBRAR EL 20%",IF($G53="Cola","Listo para asignar","Al día")))))))) | U53: =IF(N($R53)=0,"",$T53/$R53) | X53: =IF($W53="","",TODAY()-$W53) | Z53: =IFERROR(INDEX(Aarón!$P:$P,MATCH($C53,Aarón!$A:$A,0))&"",IFERROR(INDEX(Rubit!$P:$P,MATCH($C53,Rubit!$A:$A,0))&"",IFERROR(INDEX(Luis!$P:$P,MATCH($C53,Luis!$A:$A,0))&"",""))) | AA53: =IFERROR(INDEX(Aarón!$Q:$Q,MATCH($C53,Aarón!$A:$A,0))&"",IFERROR(INDEX(Rubit!$Q:$Q,MATCH($C53,Rubit!$A:$A,0))&"",IFERROR(INDEX(Luis!$Q:$Q,MATCH($C53,Luis!$A:$A,0))&"",""))) | AB53: =IFERROR(INDEX('Juan Carlos'!$Q:$Q,MATCH($C53,'Juan Carlos'!$A:$A,0))&"","")
J54: =IFERROR(INDEX('Juan Carlos'!$P:$P,MATCH($C54,'Juan Carlos'!$A:$A,0))&"","") | K54: =IF($C54="","",IF($M54<>"Sí","C",IF($P54="Completo","A","B"))) | L54: =IF($C54="","",IF($G54="Congelado","Congelado — mensaje cada 15 días",IF(N($X54)>15,"CONGELAR HOY",IF($M54<>"Sí","COBRAR EL 50%",IF($P54<>"Completo","PERSEGUIR MATERIAL",IF(AND($G54="Desarrollo",$N54<>"Sí"),"COBRAR EL 30%",IF(AND($G54="QA + entrega",$O54<>"Sí"),"COBRAR EL 20%",IF($G54="Cola","Listo para asignar","Al día")))))))) | U54: =IF(N($R54)=0,"",$T54/$R54) | X54: =IF($W54="","",TODAY()-$W54) | Z54: =IFERROR(INDEX(Aarón!$P:$P,MATCH($C54,Aarón!$A:$A,0))&"",IFERROR(INDEX(Rubit!$P:$P,MATCH($C54,Rubit!$A:$A,0))&"",IFERROR(INDEX(Luis!$P:$P,MATCH($C54,Luis!$A:$A,0))&"",""))) | AA54: =IFERROR(INDEX(Aarón!$Q:$Q,MATCH($C54,Aarón!$A:$A,0))&"",IFERROR(INDEX(Rubit!$Q:$Q,MATCH($C54,Rubit!$A:$A,0))&"",IFERROR(INDEX(Luis!$Q:$Q,MATCH($C54,Luis!$A:$A,0))&"",""))) | AB54: =IFERROR(INDEX('Juan Carlos'!$Q:$Q,MATCH($C54,'Juan Carlos'!$A:$A,0))&"","")
J55: =IFERROR(INDEX('Juan Carlos'!$P:$P,MATCH($C55,'Juan Carlos'!$A:$A,0))&"","") | K55: =IF($C55="","",IF($M55<>"Sí","C",IF($P55="Completo","A","B"))) | L55: =IF($C55="","",IF($G55="Congelado","Congelado — mensaje cada 15 días",IF(N($X55)>15,"CONGELAR HOY",IF($M55<>"Sí","COBRAR EL 50%",IF($P55<>"Completo","PERSEGUIR MATERIAL",IF(AND($G55="Desarrollo",$N55<>"Sí"),"COBRAR EL 30%",IF(AND($G55="QA + entrega",$O55<>"Sí"),"COBRAR EL 20%",IF($G55="Cola","Listo para asignar","Al día")))))))) | U55: =IF(N($R55)=0,"",$T55/$R55) | X55: =IF($W55="","",TODAY()-$W55) | Z55: =IFERROR(INDEX(Aarón!$P:$P,MATCH($C55,Aarón!$A:$A,0))&"",IFERROR(INDEX(Rubit!$P:$P,MATCH($C55,Rubit!$A:$A,0))&"",IFERROR(INDEX(Luis!$P:$P,MATCH($C55,Luis!$A:$A,0))&"",""))) | AA55: =IFERROR(INDEX(Aarón!$Q:$Q,MATCH($C55,Aarón!$A:$A,0))&"",IFERROR(INDEX(Rubit!$Q:$Q,MATCH($C55,Rubit!$A:$A,0))&"",IFERROR(INDEX(Luis!$Q:$Q,MATCH($C55,Luis!$A:$A,0))&"",""))) | AB55: =IFERROR(INDEX('Juan Carlos'!$Q:$Q,MATCH($C55,'Juan Carlos'!$A:$A,0))&"","")
J56: =IFERROR(INDEX('Juan Carlos'!$P:$P,MATCH($C56,'Juan Carlos'!$A:$A,0))&"","") | K56: =IF($C56="","",IF($M56<>"Sí","C",IF($P56="Completo","A","B"))) | L56: =IF($C56="","",IF($G56="Congelado","Congelado — mensaje cada 15 días",IF(N($X56)>15,"CONGELAR HOY",IF($M56<>"Sí","COBRAR EL 50%",IF($P56<>"Completo","PERSEGUIR MATERIAL",IF(AND($G56="Desarrollo",$N56<>"Sí"),"COBRAR EL 30%",IF(AND($G56="QA + entrega",$O56<>"Sí"),"COBRAR EL 20%",IF($G56="Cola","Listo para asignar","Al día")))))))) | U56: =IF(N($R56)=0,"",$T56/$R56) | X56: =IF($W56="","",TODAY()-$W56) | Z56: =IFERROR(INDEX(Aarón!$P:$P,MATCH($C56,Aarón!$A:$A,0))&"",IFERROR(INDEX(Rubit!$P:$P,MATCH($C56,Rubit!$A:$A,0))&"",IFERROR(INDEX(Luis!$P:$P,MATCH($C56,Luis!$A:$A,0))&"",""))) | AA56: =IFERROR(INDEX(Aarón!$Q:$Q,MATCH($C56,Aarón!$A:$A,0))&"",IFERROR(INDEX(Rubit!$Q:$Q,MATCH($C56,Rubit!$A:$A,0))&"",IFERROR(INDEX(Luis!$Q:$Q,MATCH($C56,Luis!$A:$A,0))&"",""))) | AB56: =IFERROR(INDEX('Juan Carlos'!$Q:$Q,MATCH($C56,'Juan Carlos'!$A:$A,0))&"","")
J57: =IFERROR(INDEX('Juan Carlos'!$P:$P,MATCH($C57,'Juan Carlos'!$A:$A,0))&"","") | K57: =IF($C57="","",IF($M57<>"Sí","C",IF($P57="Completo","A","B"))) | L57: =IF($C57="","",IF($G57="Congelado","Congelado — mensaje cada 15 días",IF(N($X57)>15,"CONGELAR HOY",IF($M57<>"Sí","COBRAR EL 50%",IF($P57<>"Completo","PERSEGUIR MATERIAL",IF(AND($G57="Desarrollo",$N57<>"Sí"),"COBRAR EL 30%",IF(AND($G57="QA + entrega",$O57<>"Sí"),"COBRAR EL 20%",IF($G57="Cola","Listo para asignar","Al día")))))))) | U57: =IF(N($R57)=0,"",$T57/$R57) | X57: =IF($W57="","",TODAY()-$W57) | Z57: =IFERROR(INDEX(Aarón!$P:$P,MATCH($C57,Aarón!$A:$A,0))&"",IFERROR(INDEX(Rubit!$P:$P,MATCH($C57,Rubit!$A:$A,0))&"",IFERROR(INDEX(Luis!$P:$P,MATCH($C57,Luis!$A:$A,0))&"",""))) | AA57: =IFERROR(INDEX(Aarón!$Q:$Q,MATCH($C57,Aarón!$A:$A,0))&"",IFERROR(INDEX(Rubit!$Q:$Q,MATCH($C57,Rubit!$A:$A,0))&"",IFERROR(INDEX(Luis!$Q:$Q,MATCH($C57,Luis!$A:$A,0))&"",""))) | AB57: =IFERROR(INDEX('Juan Carlos'!$Q:$Q,MATCH($C57,'Juan Carlos'!$A:$A,0))&"","")
J58: =IFERROR(INDEX('Juan Carlos'!$P:$P,MATCH($C58,'Juan Carlos'!$A:$A,0))&"","") | K58: =IF($C58="","",IF($M58<>"Sí","C",IF($P58="Completo","A","B"))) | L58: =IF($C58="","",IF($G58="Congelado","Congelado — mensaje cada 15 días",IF(N($X58)>15,"CONGELAR HOY",IF($M58<>"Sí","COBRAR EL 50%",IF($P58<>"Completo","PERSEGUIR MATERIAL",IF(AND($G58="Desarrollo",$N58<>"Sí"),"COBRAR EL 30%",IF(AND($G58="QA + entrega",$O58<>"Sí"),"COBRAR EL 20%",IF($G58="Cola","Listo para asignar","Al día")))))))) | U58: =IF(N($R58)=0,"",$T58/$R58) | X58: =IF($W58="","",TODAY()-$W58) | Z58: =IFERROR(INDEX(Aarón!$P:$P,MATCH($C58,Aarón!$A:$A,0))&"",IFERROR(INDEX(Rubit!$P:$P,MATCH($C58,Rubit!$A:$A,0))&"",IFERROR(INDEX(Luis!$P:$P,MATCH($C58,Luis!$A:$A,0))&"",""))) | AA58: =IFERROR(INDEX(Aarón!$Q:$Q,MATCH($C58,Aarón!$A:$A,0))&"",IFERROR(INDEX(Rubit!$Q:$Q,MATCH($C58,Rubit!$A:$A,0))&"",IFERROR(INDEX(Luis!$Q:$Q,MATCH($C58,Luis!$A:$A,0))&"",""))) | AB58: =IFERROR(INDEX('Juan Carlos'!$Q:$Q,MATCH($C58,'Juan Carlos'!$A:$A,0))&"","")
J59: =IFERROR(INDEX('Juan Carlos'!$P:$P,MATCH($C59,'Juan Carlos'!$A:$A,0))&"","") | K59: =IF($C59="","",IF($M59<>"Sí","C",IF($P59="Completo","A","B"))) | L59: =IF($C59="","",IF($G59="Congelado","Congelado — mensaje cada 15 días",IF(N($X59)>15,"CONGELAR HOY",IF($M59<>"Sí","COBRAR EL 50%",IF($P59<>"Completo","PERSEGUIR MATERIAL",IF(AND($G59="Desarrollo",$N59<>"Sí"),"COBRAR EL 30%",IF(AND($G59="QA + entrega",$O59<>"Sí"),"COBRAR EL 20%",IF($G59="Cola","Listo para asignar","Al día")))))))) | U59: =IF(N($R59)=0,"",$T59/$R59) | X59: =IF($W59="","",TODAY()-$W59) | Z59: =IFERROR(INDEX(Aarón!$P:$P,MATCH($C59,Aarón!$A:$A,0))&"",IFERROR(INDEX(Rubit!$P:$P,MATCH($C59,Rubit!$A:$A,0))&"",IFERROR(INDEX(Luis!$P:$P,MATCH($C59,Luis!$A:$A,0))&"",""))) | AA59: =IFERROR(INDEX(Aarón!$Q:$Q,MATCH($C59,Aarón!$A:$A,0))&"",IFERROR(INDEX(Rubit!$Q:$Q,MATCH($C59,Rubit!$A:$A,0))&"",IFERROR(INDEX(Luis!$Q:$Q,MATCH($C59,Luis!$A:$A,0))&"",""))) | AB59: =IFERROR(INDEX('Juan Carlos'!$Q:$Q,MATCH($C59,'Juan Carlos'!$A:$A,0))&"","")
J60: =IFERROR(INDEX('Juan Carlos'!$P:$P,MATCH($C60,'Juan Carlos'!$A:$A,0))&"","") | K60: =IF($C60="","",IF($M60<>"Sí","C",IF($P60="Completo","A","B"))) | L60: =IF($C60="","",IF($G60="Congelado","Congelado — mensaje cada 15 días",IF(N($X60)>15,"CONGELAR HOY",IF($M60<>"Sí","COBRAR EL 50%",IF($P60<>"Completo","PERSEGUIR MATERIAL",IF(AND($G60="Desarrollo",$N60<>"Sí"),"COBRAR EL 30%",IF(AND($G60="QA + entrega",$O60<>"Sí"),"COBRAR EL 20%",IF($G60="Cola","Listo para asignar","Al día")))))))) | U60: =IF(N($R60)=0,"",$T60/$R60) | X60: =IF($W60="","",TODAY()-$W60) | Z60: =IFERROR(INDEX(Aarón!$P:$P,MATCH($C60,Aarón!$A:$A,0))&"",IFERROR(INDEX(Rubit!$P:$P,MATCH($C60,Rubit!$A:$A,0))&"",IFERROR(INDEX(Luis!$P:$P,MATCH($C60,Luis!$A:$A,0))&"",""))) | AA60: =IFERROR(INDEX(Aarón!$Q:$Q,MATCH($C60,Aarón!$A:$A,0))&"",IFERROR(INDEX(Rubit!$Q:$Q,MATCH($C60,Rubit!$A:$A,0))&"",IFERROR(INDEX(Luis!$Q:$Q,MATCH($C60,Luis!$A:$A,0))&"",""))) | AB60: =IFERROR(INDEX('Juan Carlos'!$Q:$Q,MATCH($C60,'Juan Carlos'!$A:$A,0))&"","")

Sheet Tablero
B2: Tablero del área
B3: Todo lo de esta hoja se dibuja solo con lo que escribes en PROYECTOS. No se edita nada aquí.
B5: =COUNTIF(Proyectos!$K$4:$K$60,"A") -> 31 | D5: =COUNTIF(Proyectos!$K$4:$K$60,"B") -> 16 | F5: =COUNTIF(Proyectos!$K$4:$K$60,"C") -> 1 | H5: =COUNTIF(Proyectos!$X$4:$X$60,">15") -> 30 | J5: =COUNTIF(Proyectos!$G$4:$G$60,"Cerrado") -> 18
B6: Listos para producir | D6: Trabados por el cliente | F6: Sin pagar / sin responder | H6: Para congelar hoy | J6: Cerrados
B9: En qué etapa está cada proyecto
B10: Cola | C10: =COUNTIF(Proyectos!$G$4:$G$60,"Cola") -> 2
B11: Esperando material | C11: =COUNTIF(Proyectos!$G$4:$G$60,"Esperando material") -> 6
B12: Diseño | C12: =COUNTIF(Proyectos!$G$4:$G$60,"Diseño") -> 11
B13: Desarrollo | C13: =COUNTIF(Proyectos!$G$4:$G$60,"Desarrollo") -> 6
B14: Esperando catálogo | C14: =COUNTIF(Proyectos!$G$4:$G$60,"Esperando catálogo") -> 0
B15: QA + entrega | C15: =COUNTIF(Proyectos!$G$4:$G$60,"QA + entrega") -> 1
B16: Cerrado | C16: =COUNTIF(Proyectos!$G$4:$G$60,"Cerrado") -> 18
B17: Congelado | C17: =COUNTIF(Proyectos!$G$4:$G$60,"Congelado") -> 4
B20: Cuánto trabajo tiene cada uno ahora | E20: En qué plataforma va cada tienda | H20: Avance de diseño (Juan Carlos)
B21: Juan Carlos (diseño, grupo A) | C21: =COUNTIFS(Proyectos!$K$4:$K$60,"A",Proyectos!$G$4:$G$60,"<>Cerrado",Proyectos!$G$4:$G$60,"<>Congelado",Proyectos!$C$4:$C$60,"<>") -> 13 | E21: Shopify | F21: =COUNTIF(Proyectos!$F$4:$F$60,"Shopify") -> 1 | H21: Falta material | I21: =COUNTIF(Proyectos!$J$4:$J$60,"Falta material") -> 0
B22: Aarón (desarrollo) | C22: =COUNTIFS(Proyectos!$H$4:$H$60,"Aarón",Proyectos!$G$4:$G$60,"Desarrollo") -> 3 | E22: WooCommerce | F22: =COUNTIF(Proyectos!$F$4:$F$60,"WooCommerce") -> 1 | H22: Material completo — iniciar diseño | I22: =COUNTIF(Proyectos!$J$4:$J$60,"Material completo — iniciar diseño") -> 4
B23: Rubit (desarrollo) | C23: =COUNTIFS(Proyectos!$H$4:$H$60,"Rubit",Proyectos!$G$4:$G$60,"Desarrollo") -> 0 | E23: Personalizado | F23: =COUNTIF(Proyectos!$F$4:$F$60,"Personalizado") -> 0 | H23: Diseño en curso | I23: =COUNTIF(Proyectos!$J$4:$J$60,"Diseño en curso") -> 2
B24: Luis (desarrollo) | C24: =COUNTIFS(Proyectos!$H$4:$H$60,"Luis",Proyectos!$G$4:$G$60,"Desarrollo") -> 1 | E24: Por definir | F24: =COUNTIF(Proyectos!$F$4:$F$60,"Por definir") -> 46 | H24: Avance listo para presentar | I24: =COUNTIF(Proyectos!$J$4:$J$60,"Avance listo para presentar") -> 1
B25: SIN DEV ASIGNADO (activos) | C25: =COUNTIFS(Proyectos!$H$4:$H$60,"Sin asignar",Proyectos!$G$4:$G$60,"<>Cerrado",Proyectos!$G$4:$G$60,"<>Congelado",Proyectos!$C$4:$C$60,"<>") -> 5 | H25: En revisión del cliente | I25: =COUNTIF(Proyectos!$J$4:$J$60,"En revisión del cliente") -> 0
H26: Diseño finalizado | I26: =COUNTIF(Proyectos!$J$4:$J$60,"Diseño finalizado") -> 7
B31: Qué falta cobrar
B32: Falta el 50% inicial | C32: =COUNTIF(Proyectos!$M$4:$M$60,"No") -> 0
B33: Falta el 30% de diseño | C33: =COUNTIFS(Proyectos!$G$4:$G$60,"Desarrollo",Proyectos!$N$4:$N$60,"No") -> 1
B34: Falta el 20% final | C34: =COUNTIFS(Proyectos!$G$4:$G$60,"QA + entrega",Proyectos!$O$4:$O$60,"No") -> 1
B40: Para el reporte del viernes: captura esta hoja y pégala en el correo a Luis.

Sheet Juan Carlos
A1: Proyectos — Juan Carlos
A2: Juan Carlos solo recibe proyectos en GRUPO A (50% pagado + material de diseño completo). Ordenado por la cola de prioridad de diseño; los que no tienen número van al final. No incluye cerrados, congelados, ni los que siguen en grupo B o C.
A3: SOLO EDITAS LAS 3 ÚLTIMAS COLUMNAS, las amarillas del final (P, Q y R): «Avance de diseño» (lista desplegable), «Nota de diseño» y «Fecha». Lo que pongas ahí aparece automáticamente en la hoja PROYECTOS. La columna Cliente queda fija al desplazarte a la derecha. Todo lo demás es gris: se lee solo desde PROYECTOS.
A4: =IF(COUNTIFS(Proyectos!$K$4:$K$60,"A",Proyectos!$G$4:$G$60,"<>Cerrado",Proyectos!$G$4:$G$60,"<>Congelado",Proyectos!$C$4:$C$60,"<>")=COUNTA($A$6:$A$19),"Cuadra: "&COUNTIFS(Proyectos!$K$4:$K$60,"A",Proyectos!$G$4:$G$60,"<>Cerrado",Proyectos!$G$4:$G$60,"<>Congelado",Proyectos!$C$4:$C$60,"<>")&" proyectos en grupo A.","OJO: hay "&COUNTIFS(Proyectos!$K$4:$K$60,"A",Proyectos!$G$4:$G$60,"<>Cerrado",Proyectos!$G$4:$G$60,"<>Congelado",Proyectos!$C$4:$C$60,"<>")&" proyectos en grupo A en la hoja Proyectos y esta lista tiene "&COUNTA($A$6:$A$19)&". Pide que se regenere la hoja.") -> OJO: hay 13 proyectos en grupo A en la hoja Proyectos y esta lista tiene 14. Pide que se regenere la hoja.
A5: Cliente | B5: Prioridad diseño | C5: Código | D5: Correo del cliente | E5: Tipo | F5: Plataforma | G5: Estado | H5: Grupo | I5: Acción de hoy | J5: Material de diseño | K5: Plantilla productos | L5: Qué falta exactamente | M5: Últ. respuesta | N5: Días sin responder | O5: Notas | P5: Avance de diseño | Q5: Nota de diseño | R5: Fecha
A6: I&N Caprimoda | B6: =IFERROR(IF(INDEX(Proyectos!$A:$A,MATCH($A6,Proyectos!$C:$C,0))="","",INDEX(Proyectos!$A:$A,MATCH($A6,Proyectos!$C:$C,0))),"") -> 1 | C6: =IFERROR(INDEX(Proyectos!$B:$B,MATCH($A6,Proyectos!$C:$C,0))&"","") -> 062 | D6: =IFERROR(INDEX(Proyectos!$D:$D,MATCH($A6,Proyectos!$C:$C,0))&"","") | E6: =IFERROR(INDEX(Proyectos!$E:$E,MATCH($A6,Proyectos!$C:$C,0))&"","") -> E-commerce | F6: =IFERROR(INDEX(Proyectos!$F:$F,MATCH($A6,Proyectos!$C:$C,0))&"","") -> Por definir | G6: =IFERROR(INDEX(Proyectos!$G:$G,MATCH($A6,Proyectos!$C:$C,0))&"","") -> QA + entrega | H6: =IFERROR(INDEX(Proyectos!$K:$K,MATCH($A6,Proyectos!$C:$C,0))&"","") -> A | I6: =IFERROR(INDEX(Proyectos!$L:$L,MATCH($A6,Proyectos!$C:$C,0))&"","") -> CONGELAR HOY | J6: =IFERROR(INDEX(Proyectos!$P:$P,MATCH($A6,Proyectos!$C:$C,0))&"","") -> Completo | K6: =IFERROR(INDEX(Proyectos!$Q:$Q,MATCH($A6,Proyectos!$C:$C,0))&"","") -> No enviada | L6: =IFERROR(INDEX(Proyectos!$V:$V,MATCH($A6,Proyectos!$C:$C,0))&"","") -> Carga y validación de contenidos | M6: =IFERROR(IF(INDEX(Proyectos!$W:$W,MATCH($A6,Proyectos!$C:$C,0))="","",INDEX(Proyectos!$W:$W,MATCH($A6,Proyectos!$C:$C,0))),"") -> 46218 | N6: =IFERROR(INDEX(Proyectos!$X:$X,MATCH($A6,Proyectos!$C:$C,0)),"") -> 19 | O6: =IFERROR(INDEX(Proyectos!$Y:$Y,MATCH($A6,Proyectos!$C:$C,0))&"","") -> Cliente: Noelia Juanfer. OJO: Luis tiene capacidad 0 según Reglas — confirmar si esto es correcto. Cita viernes 24/07 | P6: Diseño finalizado
A7: Erika Garay | B7: =IFERROR(IF(INDEX(Proyectos!$A:$A,MATCH($A7,Proyectos!$C:$C,0))="","",INDEX(Proyectos!$A:$A,MATCH($A7,Proyectos!$C:$C,0))),"") -> 2 | C7: =IFERROR(INDEX(Proyectos!$B:$B,MATCH($A7,Proyectos!$C:$C,0))&"","") -> 066 | D7: =IFERROR(INDEX(Proyectos!$D:$D,MATCH($A7,Proyectos!$C:$C,0))&"","") | E7: =IFERROR(INDEX(Proyectos!$E:$E,MATCH($A7,Proyectos!$C:$C,0))&"","") -> E-commerce | F7: =IFERROR(INDEX(Proyectos!$F:$F,MATCH($A7,Proyectos!$C:$C,0))&"","") -> Por definir | G7: =IFERROR(INDEX(Proyectos!$G:$G,MATCH($A7,Proyectos!$C:$C,0))&"","") -> Diseño | H7: =IFERROR(INDEX(Proyectos!$K:$K,MATCH($A7,Proyectos!$C:$C,0))&"","") -> A | I7: =IFERROR(INDEX(Proyectos!$L:$L,MATCH($A7,Proyectos!$C:$C,0))&"","") -> CONGELAR HOY | J7: =IFERROR(INDEX(Proyectos!$P:$P,MATCH($A7,Proyectos!$C:$C,0))&"","") -> Completo | K7: =IFERROR(INDEX(Proyectos!$Q:$Q,MATCH($A7,Proyectos!$C:$C,0))&"","") -> No enviada | L7: =IFERROR(INDEX(Proyectos!$V:$V,MATCH($A7,Proyectos!$C:$C,0))&"","") -> Material de diseño en general | M7: =IFERROR(IF(INDEX(Proyectos!$W:$W,MATCH($A7,Proyectos!$C:$C,0))="","",INDEX(Proyectos!$W:$W,MATCH($A7,Proyectos!$C:$C,0))),"") -> 46218 | N7: =IFERROR(INDEX(Proyectos!$X:$X,MATCH($A7,Proyectos!$C:$C,0)),"") -> 19 | O7: =IFERROR(INDEX(Proyectos!$Y:$Y,MATCH($A7,Proyectos!$C:$C,0))&"","") -> Cliente: Erika Garay. Dev histórico: Aarón. | P7: Diseño en curso | Q7: en diseño
A8: HSM Foods & Agro | B8: =IFERROR(IF(INDEX(Proyectos!$A:$A,MATCH($A8,Proyectos!$C:$C,0))="","",INDEX(Proyectos!$A:$A,MATCH($A8,Proyectos!$C:$C,0))),"") -> 3 | C8: =IFERROR(INDEX(Proyectos!$B:$B,MATCH($A8,Proyectos!$C:$C,0))&"","") -> 074 | D8: =IFERROR(INDEX(Proyectos!$D:$D,MATCH($A8,Proyectos!$C:$C,0))&"","") | E8: =IFERROR(INDEX(Proyectos!$E:$E,MATCH($A8,Proyectos!$C:$C,0))&"","") -> E-commerce | F8: =IFERROR(INDEX(Proyectos!$F:$F,MATCH($A8,Proyectos!$C:$C,0))&"","") -> Por definir | G8: =IFERROR(INDEX(Proyectos!$G:$G,MATCH($A8,Proyectos!$C:$C,0))&"","") -> Diseño | H8: =IFERROR(INDEX(Proyectos!$K:$K,MATCH($A8,Proyectos!$C:$C,0))&"","") -> A | I8: =IFERROR(INDEX(Proyectos!$L:$L,MATCH($A8,Proyectos!$C:$C,0))&"","") -> CONGELAR HOY | J8: =IFERROR(INDEX(Proyectos!$P:$P,MATCH($A8,Proyectos!$C:$C,0))&"","") -> Completo | K8: =IFERROR(INDEX(Proyectos!$Q:$Q,MATCH($A8,Proyectos!$C:$C,0))&"","") -> Recibida con errores | L8: =IFERROR(INDEX(Proyectos!$V:$V,MATCH($A8,Proyectos!$C:$C,0))&"","") -> Fotos (comprometidas para la próxima semana) | M8: =IFERROR(IF(INDEX(Proyectos!$W:$W,MATCH($A8,Proyectos!$C:$C,0))="","",INDEX(Proyectos!$W:$W,MATCH($A8,Proyectos!$C:$C,0))),"") -> 46218 | N8: =IFERROR(INDEX(Proyectos!$X:$X,MATCH($A8,Proyectos!$C:$C,0)),"") -> 19 | O8: =IFERROR(INDEX(Proyectos!$Y:$Y,MATCH($A8,Proyectos!$C:$C,0))&"","") -> Cliente: Sebastian y Mauricio. Dev histórico: Aarón. PENDIENTE: subir las fotos al Drive. Pedir en el grupo que suban el brief al Drive para que Luis lo descargue. | P8: Material completo — iniciar diseño
A9: Luma Home | B9: =IFERROR(IF(INDEX(Proyectos!$A:$A,MATCH($A9,Proyectos!$C:$C,0))="","",INDEX(Proyectos!$A:$A,MATCH($A9,Proyectos!$C:$C,0))),"") -> 4 | C9: =IFERROR(INDEX(Proyectos!$B:$B,MATCH($A9,Proyectos!$C:$C,0))&"","") -> 075 | D9: =IFERROR(INDEX(Proyectos!$D:$D,MATCH($A9,Proyectos!$C:$C,0))&"","") | E9: =IFERROR(INDEX(Proyectos!$E:$E,MATCH($A9,Proyectos!$C:$C,0))&"","") -> E-commerce | F9: =IFERROR(INDEX(Proyectos!$F:$F,MATCH($A9,Proyectos!$C:$C,0))&"","") -> Por definir | G9: =IFERROR(INDEX(Proyectos!$G:$G,MATCH($A9,Proyectos!$C:$C,0))&"","") -> Diseño | H9: =IFERROR(INDEX(Proyectos!$K:$K,MATCH($A9,Proyectos!$C:$C,0))&"","") -> A | I9: =IFERROR(INDEX(Proyectos!$L:$L,MATCH($A9,Proyectos!$C:$C,0))&"","") -> CONGELAR HOY | J9: =IFERROR(INDEX(Proyectos!$P:$P,MATCH($A9,Proyectos!$C:$C,0))&"","") -> Completo | K9: =IFERROR(INDEX(Proyectos!$Q:$Q,MATCH($A9,Proyectos!$C:$C,0))&"","") -> No enviada | L9: =IFERROR(INDEX(Proyectos!$V:$V,MATCH($A9,Proyectos!$C:$C,0))&"","") -> Material de diseño (brief y drive ya completados administrativamente) | M9: =IFERROR(IF(INDEX(Proyectos!$W:$W,MATCH($A9,Proyectos!$C:$C,0))="","",INDEX(Proyectos!$W:$W,MATCH($A9,Proyectos!$C:$C,0))),"") -> 46218 | N9: =IFERROR(INDEX(Proyectos!$X:$X,MATCH($A9,Proyectos!$C:$C,0)),"") -> 19 | O9: =IFERROR(INDEX(Proyectos!$Y:$Y,MATCH($A9,Proyectos!$C:$C,0))&"","") -> Cliente: Fatima. Dev histórico: Rubit. PENDIENTE: que envíen todo su material al Drive. | P9: Material completo — iniciar diseño
A10: Teccons SAC | B10: =IFERROR(IF(INDEX(Proyectos!$A:$A,MATCH($A10,Proyectos!$C:$C,0))="","",INDEX(Proyectos!$A:$A,MATCH($A10,Proyectos!$C:$C,0))),"") -> 5 | C10: =IFERROR(INDEX(Proyectos!$B:$B,MATCH($A10,Proyectos!$C:$C,0))&"","") -> 071 | D10: =IFERROR(INDEX(Proyectos!$D:$D,MATCH($A10,Proyectos!$C:$C,0))&"","") | E10: =IFERROR(INDEX(Proyectos!$E:$E,MATCH($A10,Proyectos!$C:$C,0))&"","") -> Informativa | F10: =IFERROR(INDEX(Proyectos!$F:$F,MATCH($A10,Proyectos!$C:$C,0))&"","") -> Por definir | G10: =IFERROR(INDEX(Proyectos!$G:$G,MATCH($A10,Proyectos!$C:$C,0))&"","") -> Diseño | H10: =IFERROR(INDEX(Proyectos!$K:$K,MATCH($A10,Proyectos!$C:$C,0))&"","") -> A | I10: =IFERROR(INDEX(Proyectos!$L:$L,MATCH($A10,Proyectos!$C:$C,0))&"","") -> CONGELAR HOY | J10: =IFERROR(INDEX(Proyectos!$P:$P,MATCH($A10,Proyectos!$C:$C,0))&"","") -> Completo | K10: =IFERROR(INDEX(Proyectos!$Q:$Q,MATCH($A10,Proyectos!$C:$C,0))&"","") -> No aplica | L10: =IFERROR(INDEX(Proyectos!$V:$V,MATCH($A10,Proyectos!$C:$C,0))&"","") -> Material de diseño (brief y drive ya completados administrativamente) | M10: =IFERROR(IF(INDEX(Proyectos!$W:$W,MATCH($A10,Proyectos!$C:$C,0))="","",INDEX(Proyectos!$W:$W,MATCH($A10,Proyectos!$C:$C,0))),"") -> 46218 | N10: =IFERROR(INDEX(Proyectos!$X:$X,MATCH($A10,Proyectos!$C:$C,0)),"") -> 19 | O10: =IFERROR(INDEX(Proyectos!$Y:$Y,MATCH($A10,Proyectos!$C:$C,0))&"","") -> Cliente: Jhon Cabrera Sánchez. Dev histórico: Rubit. | P10: Avance listo para presentar | Q10: avance listo
A11: Buzz Studios | B11: =IFERROR(IF(INDEX(Proyectos!$A:$A,MATCH($A11,Proyectos!$C:$C,0))="","",INDEX(Proyectos!$A:$A,MATCH($A11,Proyectos!$C:$C,0))),"") -> 7 | C11: =IFERROR(INDEX(Proyectos!$B:$B,MATCH($A11,Proyectos!$C:$C,0))&"","") -> 070 | D11: =IFERROR(INDEX(Proyectos!$D:$D,MATCH($A11,Proyectos!$C:$C,0))&"","") | E11: =IFERROR(INDEX(Proyectos!$E:$E,MATCH($A11,Proyectos!$C:$C,0))&"","") -> E-commerce | F11: =IFERROR(INDEX(Proyectos!$F:$F,MATCH($A11,Proyectos!$C:$C,0))&"","") -> Por definir | G11: =IFERROR(INDEX(Proyectos!$G:$G,MATCH($A11,Proyectos!$C:$C,0))&"","") -> Diseño | H11: =IFERROR(INDEX(Proyectos!$K:$K,MATCH($A11,Proyectos!$C:$C,0))&"","") -> A | I11: =IFERROR(INDEX(Proyectos!$L:$L,MATCH($A11,Proyectos!$C:$C,0))&"","") -> CONGELAR HOY | J11: =IFERROR(INDEX(Proyectos!$P:$P,MATCH($A11,Proyectos!$C:$C,0))&"","") -> Completo | K11: =IFERROR(INDEX(Proyectos!$Q:$Q,MATCH($A11,Proyectos!$C:$C,0))&"","") -> No enviada | L11: =IFERROR(INDEX(Proyectos!$V:$V,MATCH($A11,Proyectos!$C:$C,0))&"","") -> Material de diseño (brief y drive ya completados administrativamente) | M11: =IFERROR(IF(INDEX(Proyectos!$W:$W,MATCH($A11,Proyectos!$C:$C,0))="","",INDEX(Proyectos!$W:$W,MATCH($A11,Proyectos!$C:$C,0))),"") -> 46218 | N11: =IFERROR(INDEX(Proyectos!$X:$X,MATCH($A11,Proyectos!$C:$C,0)),"") -> 19 | O11: =IFERROR(INDEX(Proyectos!$Y:$Y,MATCH($A11,Proyectos!$C:$C,0))&"","") -> Cliente: Elvis Stefano. Dev histórico: Aarón. | P11: Diseño en curso | Q11: Lunes
A12: Hasso Group | B12: =IFERROR(IF(INDEX(Proyectos!$A:$A,MATCH($A12,Proyectos!$C:$C,0))="","",INDEX(Proyectos!$A:$A,MATCH($A12,Proyectos!$C:$C,0))),"") -> 8 | C12: =IFERROR(INDEX(Proyectos!$B:$B,MATCH($A12,Proyectos!$C:$C,0))&"","") -> 073 | D12: =IFERROR(INDEX(Proyectos!$D:$D,MATCH($A12,Proyectos!$C:$C,0))&"","") | E12: =IFERROR(INDEX(Proyectos!$E:$E,MATCH($A12,Proyectos!$C:$C,0))&"","") -> E-commerce | F12: =IFERROR(INDEX(Proyectos!$F:$F,MATCH($A12,Proyectos!$C:$C,0))&"","") -> Por definir | G12: =IFERROR(INDEX(Proyectos!$G:$G,MATCH($A12,Proyectos!$C:$C,0))&"","") -> Diseño | H12: =IFERROR(INDEX(Proyectos!$K:$K,MATCH($A12,Proyectos!$C:$C,0))&"","") -> A | I12: =IFERROR(INDEX(Proyectos!$L:$L,MATCH($A12,Proyectos!$C:$C,0))&"","") -> CONGELAR HOY | J12: =IFERROR(INDEX(Proyectos!$P:$P,MATCH($A12,Proyectos!$C:$C,0))&"","") -> Completo | K12: =IFERROR(INDEX(Proyectos!$Q:$Q,MATCH($A12,Proyectos!$C:$C,0))&"","") -> No enviada | L12: =IFERROR(INDEX(Proyectos!$V:$V,MATCH($A12,Proyectos!$C:$C,0))&"","") -> Materiales y activos del cliente para iniciar estructura de la tienda | M12: =IFERROR(IF(INDEX(Proyectos!$W:$W,MATCH($A12,Proyectos!$C:$C,0))="","",INDEX(Proyectos!$W:$W,MATCH($A12,Proyectos!$C:$C,0))),"") -> 46218 | N12: =IFERROR(INDEX(Proyectos!$X:$X,MATCH($A12,Proyectos!$C:$C,0)),"") -> 19 | O12: =IFERROR(INDEX(Proyectos!$Y:$Y,MATCH($A12,Proyectos!$C:$C,0))&"","") -> Cliente: Sharmely Zanabria Carmona. Dev histórico: Rubit. Enviar materiales logotipos y fotos | P12: Material completo — iniciar diseño
A13: Soluz | B13: =IFERROR(IF(INDEX(Proyectos!$A:$A,MATCH($A13,Proyectos!$C:$C,0))="","",INDEX(Proyectos!$A:$A,MATCH($A13,Proyectos!$C:$C,0))),"") | C13: =IFERROR(INDEX(Proyectos!$B:$B,MATCH($A13,Proyectos!$C:$C,0))&"","") -> 036 | D13: =IFERROR(INDEX(Proyectos!$D:$D,MATCH($A13,Proyectos!$C:$C,0))&"","") | E13: =IFERROR(INDEX(Proyectos!$E:$E,MATCH($A13,Proyectos!$C:$C,0))&"","") -> E-commerce | F13: =IFERROR(INDEX(Proyectos!$F:$F,MATCH($A13,Proyectos!$C:$C,0))&"","") -> Por definir | G13: =IFERROR(INDEX(Proyectos!$G:$G,MATCH($A13,Proyectos!$C:$C,0))&"","") -> Desarrollo | H13: =IFERROR(INDEX(Proyectos!$K:$K,MATCH($A13,Proyectos!$C:$C,0))&"","") -> A | I13: =IFERROR(INDEX(Proyectos!$L:$L,MATCH($A13,Proyectos!$C:$C,0))&"","") -> CONGELAR HOY | J13: =IFERROR(INDEX(Proyectos!$P:$P,MATCH($A13,Proyectos!$C:$C,0))&"","") -> Completo | K13: =IFERROR(INDEX(Proyectos!$Q:$Q,MATCH($A13,Proyectos!$C:$C,0))&"","") -> No enviada | L13: =IFERROR(INDEX(Proyectos!$V:$V,MATCH($A13,Proyectos!$C:$C,0))&"","") -> Reunión reprogramada + validación del cliente sobre carga de productos | M13: =IFERROR(IF(INDEX(Proyectos!$W:$W,MATCH($A13,Proyectos!$C:$C,0))="","",INDEX(Proyectos!$W:$W,MATCH($A13,Proyectos!$C:$C,0))),"") -> 46213 | N13: =IFERROR(INDEX(Proyectos!$X:$X,MATCH($A13,Proyectos!$C:$C,0)),"") -> 24 | O13: =IFERROR(INDEX(Proyectos!$Y:$Y,MATCH($A13,Proyectos!$C:$C,0))&"","") -> Cliente: Giancarlo Rosario. En transición de Aarón a Luis (aún no formalizada). | P13: Diseño finalizado
A14: L'Andrea's Secret | B14: =IFERROR(IF(INDEX(Proyectos!$A:$A,MATCH($A14,Proyectos!$C:$C,0))="","",INDEX(Proyectos!$A:$A,MATCH($A14,Proyectos!$C:$C,0))),"") | C14: =IFERROR(INDEX(Proyectos!$B:$B,MATCH($A14,Proyectos!$C:$C,0))&"","") -> 038 | D14: =IFERROR(INDEX(Proyectos!$D:$D,MATCH($A14,Proyectos!$C:$C,0))&"","") | E14: =IFERROR(INDEX(Proyectos!$E:$E,MATCH($A14,Proyectos!$C:$C,0))&"","") -> E-commerce | F14: =IFERROR(INDEX(Proyectos!$F:$F,MATCH($A14,Proyectos!$C:$C,0))&"","") -> Por definir | G14: =IFERROR(INDEX(Proyectos!$G:$G,MATCH($A14,Proyectos!$C:$C,0))&"","") -> Esperando material | H14: =IFERROR(INDEX(Proyectos!$K:$K,MATCH($A14,Proyectos!$C:$C,0))&"","") -> A | I14: =IFERROR(INDEX(Proyectos!$L:$L,MATCH($A14,Proyectos!$C:$C,0))&"","") -> Al día | J14: =IFERROR(INDEX(Proyectos!$P:$P,MATCH($A14,Proyectos!$C:$C,0))&"","") -> Completo | K14: =IFERROR(INDEX(Proyectos!$Q:$Q,MATCH($A14,Proyectos!$C:$C,0))&"","") -> Recibida con errores | L14: =IFERROR(INDEX(Proyectos!$V:$V,MATCH($A14,Proyectos!$C:$C,0))&"","") -> Material de diseño — brief llenado | M14: =IFERROR(IF(INDEX(Proyectos!$W:$W,MATCH($A14,Proyectos!$C:$C,0))="","",INDEX(Proyectos!$W:$W,MATCH($A14,Proyectos!$C:$C,0))),"") | N14: =IFERROR(INDEX(Proyectos!$X:$X,MATCH($A14,Proyectos!$C:$C,0)),"") | O14: =IFERROR(INDEX(Proyectos!$Y:$Y,MATCH($A14,Proyectos!$C:$C,0))&"","") -> Cliente: Gladys Poma. Dev histórico: Luis. 30% ya pagado según pizarra. | P14: Material completo — iniciar diseño
A15: Maquinarias Aoxiang | B15: =IFERROR(IF(INDEX(Proyectos!$A:$A,MATCH($A15,Proyectos!$C:$C,0))="","",INDEX(Proyectos!$A:$A,MATCH($A15,Proyectos!$C:$C,0))),"") | C15: =IFERROR(INDEX(Proyectos!$B:$B,MATCH($A15,Proyectos!$C:$C,0))&"","") -> 040 | D15: =IFERROR(INDEX(Proyectos!$D:$D,MATCH($A15,Proyectos!$C:$C,0))&"","") | E15: =IFERROR(INDEX(Proyectos!$E:$E,MATCH($A15,Proyectos!$C:$C,0))&"","") -> E-commerce | F15: =IFERROR(INDEX(Proyectos!$F:$F,MATCH($A15,Proyectos!$C:$C,0))&"","") -> Por definir | G15: =IFERROR(INDEX(Proyectos!$G:$G,MATCH($A15,Proyectos!$C:$C,0))&"","") -> Cerrado | H15: =IFERROR(INDEX(Proyectos!$K:$K,MATCH($A15,Proyectos!$C:$C,0))&"","") -> A | I15: =IFERROR(INDEX(Proyectos!$L:$L,MATCH($A15,Proyectos!$C:$C,0))&"","") -> CONGELAR HOY | J15: =IFERROR(INDEX(Proyectos!$P:$P,MATCH($A15,Proyectos!$C:$C,0))&"","") -> Completo | K15: =IFERROR(INDEX(Proyectos!$Q:$Q,MATCH($A15,Proyectos!$C:$C,0))&"","") -> Recibida con errores | L15: =IFERROR(INDEX(Proyectos!$V:$V,MATCH($A15,Proyectos!$C:$C,0))&"","") -> Nada — diseño aprobado | M15: =IFERROR(IF(INDEX(Proyectos!$W:$W,MATCH($A15,Proyectos!$C:$C,0))="","",INDEX(Proyectos!$W:$W,MATCH($A15,Proyectos!$C:$C,0))),"") -> 46200 | N15: =IFERROR(INDEX(Proyectos!$X:$X,MATCH($A15,Proyectos!$C:$C,0)),"") -> 37 | O15: =IFERROR(INDEX(Proyectos!$Y:$Y,MATCH($A15,Proyectos!$C:$C,0))&"","") -> Cliente: Liliana y Javier. | P15: Diseño finalizado
A16: Youbi Importaciones | B16: =IFERROR(IF(INDEX(Proyectos!$A:$A,MATCH($A16,Proyectos!$C:$C,0))="","",INDEX(Proyectos!$A:$A,MATCH($A16,Proyectos!$C:$C,0))),"") | C16: =IFERROR(INDEX(Proyectos!$B:$B,MATCH($A16,Proyectos!$C:$C,0))&"","") -> 053 | D16: =IFERROR(INDEX(Proyectos!$D:$D,MATCH($A16,Proyectos!$C:$C,0))&"","") | E16: =IFERROR(INDEX(Proyectos!$E:$E,MATCH($A16,Proyectos!$C:$C,0))&"","") -> Informativa | F16: =IFERROR(INDEX(Proyectos!$F:$F,MATCH($A16,Proyectos!$C:$C,0))&"","") -> Por definir | G16: =IFERROR(INDEX(Proyectos!$G:$G,MATCH($A16,Proyectos!$C:$C,0))&"","") -> Desarrollo | H16: =IFERROR(INDEX(Proyectos!$K:$K,MATCH($A16,Proyectos!$C:$C,0))&"","") -> A | I16: =IFERROR(INDEX(Proyectos!$L:$L,MATCH($A16,Proyectos!$C:$C,0))&"","") -> CONGELAR HOY | J16: =IFERROR(INDEX(Proyectos!$P:$P,MATCH($A16,Proyectos!$C:$C,0))&"","") -> Completo | K16: =IFERROR(INDEX(Proyectos!$Q:$Q,MATCH($A16,Proyectos!$C:$C,0))&"","") -> No aplica | L16: =IFERROR(INDEX(Proyectos!$V:$V,MATCH($A16,Proyectos!$C:$C,0))&"","") -> Validación de diseño en paralelo al desarrollo | M16: =IFERROR(IF(INDEX(Proyectos!$W:$W,MATCH($A16,Proyectos!$C:$C,0))="","",INDEX(Proyectos!$W:$W,MATCH($A16,Proyectos!$C:$C,0))),"") -> 46212 | N16: =IFERROR(INDEX(Proyectos!$X:$X,MATCH($A16,Proyectos!$C:$C,0)),"") -> 25 | O16: =IFERROR(INDEX(Proyectos!$Y:$Y,MATCH($A16,Proyectos!$C:$C,0))&"","") -> Cliente: Jenifer y Jorge. 30% pagado. | P16: Diseño finalizado
A17: Los Halcones | B17: =IFERROR(IF(INDEX(Proyectos!$A:$A,MATCH($A17,Proyectos!$C:$C,0))="","",INDEX(Proyectos!$A:$A,MATCH($A17,Proyectos!$C:$C,0))),"") | C17: =IFERROR(INDEX(Proyectos!$B:$B,MATCH($A17,Proyectos!$C:$C,0))&"","") -> 059 | D17: =IFERROR(INDEX(Proyectos!$D:$D,MATCH($A17,Proyectos!$C:$C,0))&"","") | E17: =IFERROR(INDEX(Proyectos!$E:$E,MATCH($A17,Proyectos!$C:$C,0))&"","") -> E-commerce | F17: =IFERROR(INDEX(Proyectos!$F:$F,MATCH($A17,Proyectos!$C:$C,0))&"","") -> Por definir | G17: =IFERROR(INDEX(Proyectos!$G:$G,MATCH($A17,Proyectos!$C:$C,0))&"","") -> Desarrollo | H17: =IFERROR(INDEX(Proyectos!$K:$K,MATCH($A17,Proyectos!$C:$C,0))&"","") -> A | I17: =IFERROR(INDEX(Proyectos!$L:$L,MATCH($A17,Proyectos!$C:$C,0))&"","") -> CONGELAR HOY | J17: =IFERROR(INDEX(Proyectos!$P:$P,MATCH($A17,Proyectos!$C:$C,0))&"","") -> Completo | K17: =IFERROR(INDEX(Proyectos!$Q:$Q,MATCH($A17,Proyectos!$C:$C,0))&"","") -> No aplica | L17: =IFERROR(INDEX(Proyectos!$V:$V,MATCH($A17,Proyectos!$C:$C,0))&"","") -> Nada — en implementación, cliente informado y disponible | M17: =IFERROR(IF(INDEX(Proyectos!$W:$W,MATCH($A17,Proyectos!$C:$C,0))="","",INDEX(Proyectos!$W:$W,MATCH($A17,Proyectos!$C:$C,0))),"") -> 46218 | N17: =IFERROR(INDEX(Proyectos!$X:$X,MATCH($A17,Proyectos!$C:$C,0)),"") -> 19 | O17: =IFERROR(INDEX(Proyectos!$Y:$Y,MATCH($A17,Proyectos!$C:$C,0))&"","") -> Cliente: Juan. - Cita viernes 24-07 | P17: Diseño finalizado
A18: Eviext | B18: =IFERROR(IF(INDEX(Proyectos!$A:$A,MATCH($A18,Proyectos!$C:$C,0))="","",INDEX(Proyectos!$A:$A,MATCH($A18,Proyectos!$C:$C,0))),"") | C18: =IFERROR(INDEX(Proyectos!$B:$B,MATCH($A18,Proyectos!$C:$C,0))&"","") -> 064 | D18: =IFERROR(INDEX(Proyectos!$D:$D,MATCH($A18,Proyectos!$C:$C,0))&"","") | E18: =IFERROR(INDEX(Proyectos!$E:$E,MATCH($A18,Proyectos!$C:$C,0))&"","") -> Informativa | F18: =IFERROR(INDEX(Proyectos!$F:$F,MATCH($A18,Proyectos!$C:$C,0))&"","") -> Por definir | G18: =IFERROR(INDEX(Proyectos!$G:$G,MATCH($A18,Proyectos!$C:$C,0))&"","") -> Desarrollo | H18: =IFERROR(INDEX(Proyectos!$K:$K,MATCH($A18,Proyectos!$C:$C,0))&"","") -> A | I18: =IFERROR(INDEX(Proyectos!$L:$L,MATCH($A18,Proyectos!$C:$C,0))&"","") -> CONGELAR HOY | J18: =IFERROR(INDEX(Proyectos!$P:$P,MATCH($A18,Proyectos!$C:$C,0))&"","") -> Completo | K18: =IFERROR(INDEX(Proyectos!$Q:$Q,MATCH($A18,Proyectos!$C:$C,0))&"","") -> No aplica | L18: =IFERROR(INDEX(Proyectos!$V:$V,MATCH($A18,Proyectos!$C:$C,0))&"","") -> Integración de contenidos finales del cliente | M18: =IFERROR(IF(INDEX(Proyectos!$W:$W,MATCH($A18,Proyectos!$C:$C,0))="","",INDEX(Proyectos!$W:$W,MATCH($A18,Proyectos!$C:$C,0))),"") -> 46219 | N18: =IFERROR(INDEX(Proyectos!$X:$X,MATCH($A18,Proyectos!$C:$C,0)),"") -> 18 | O18: =IFERROR(INDEX(Proyectos!$Y:$Y,MATCH($A18,Proyectos!$C:$C,0))&"","") -> Cliente: Reina. 30% en camino/confirmado. Sin developer confirmado — asignar. | P18: Diseño finalizado
A19: Bellucci | B19: =IFERROR(IF(INDEX(Proyectos!$A:$A,MATCH($A19,Proyectos!$C:$C,0))="","",INDEX(Proyectos!$A:$A,MATCH($A19,Proyectos!$C:$C,0))),"") | C19: =IFERROR(INDEX(Proyectos!$B:$B,MATCH($A19,Proyectos!$C:$C,0))&"","") | D19: =IFERROR(INDEX(Proyectos!$D:$D,MATCH($A19,Proyectos!$C:$C,0))&"","") | E19: =IFERROR(INDEX(Proyectos!$E:$E,MATCH($A19,Proyectos!$C:$C,0))&"","") -> E-commerce | F19: =IFERROR(INDEX(Proyectos!$F:$F,MATCH($A19,Proyectos!$C:$C,0))&"","") -> Por definir | G19: =IFERROR(INDEX(Proyectos!$G:$G,MATCH($A19,Proyectos!$C:$C,0))&"","") -> Cerrado | H19: =IFERROR(INDEX(Proyectos!$K:$K,MATCH($A19,Proyectos!$C:$C,0))&"","") -> A | I19: =IFERROR(INDEX(Proyectos!$L:$L,MATCH($A19,Proyectos!$C:$C,0))&"","") -> Al día | J19: =IFERROR(INDEX(Proyectos!$P:$P,MATCH($A19,Proyectos!$C:$C,0))&"","") -> Completo | K19: =IFERROR(INDEX(Proyectos!$Q:$Q,MATCH($A19,Proyectos!$C:$C,0))&"","") -> Recibida y validada | L19: =IFERROR(INDEX(Proyectos!$V:$V,MATCH($A19,Proyectos!$C:$C,0))&"","") -> Todo — lead sin pago ni código | M19: =IFERROR(IF(INDEX(Proyectos!$W:$W,MATCH($A19,Proyectos!$C:$C,0))="","",INDEX(Proyectos!$W:$W,MATCH($A19,Proyectos!$C:$C,0))),"") | N19: =IFERROR(INDEX(Proyectos!$X:$X,MATCH($A19,Proyectos!$C:$C,0)),"") | O19: =IFERROR(INDEX(Proyectos!$Y:$Y,MATCH($A19,Proyectos!$C:$C,0))&"","") -> Cliente: Joselyn Mendoza Vasquez. | P19: Diseño finalizado
B20: =IFERROR(IF(INDEX(Proyectos!$A:$A,MATCH($A20,Proyectos!$C:$C,0))="","",INDEX(Proyectos!$A:$A,MATCH($A20,Proyectos!$C:$C,0))),"") | C20: =IFERROR(INDEX(Proyectos!$B:$B,MATCH($A20,Proyectos!$C:$C,0))&"","") | D20: =IFERROR(INDEX(Proyectos!$D:$D,MATCH($A20,Proyectos!$C:$C,0))&"","") | E20: =IFERROR(INDEX(Proyectos!$E:$E,MATCH($A20,Proyectos!$C:$C,0))&"","") | F20: =IFERROR(INDEX(Proyectos!$F:$F,MATCH($A20,Proyectos!$C:$C,0))&"","") | G20: =IFERROR(INDEX(Proyectos!$G:$G,MATCH($A20,Proyectos!$C:$C,0))&"","") | H20: =IFERROR(INDEX(Proyectos!$K:$K,MATCH($A20,Proyectos!$C:$C,0))&"","") | I20: =IFERROR(INDEX(Proyectos!$L:$L,MATCH($A20,Proyectos!$C:$C,0))&"","") | J20: =IFERROR(INDEX(Proyectos!$P:$P,MATCH($A20,Proyectos!$C:$C,0))&"","") | K20: =IFERROR(INDEX(Proyectos!$Q:$Q,MATCH($A20,Proyectos!$C:$C,0))&"","") | L20: =IFERROR(INDEX(Proyectos!$V:$V,MATCH($A20,Proyectos!$C:$C,0))&"","") | M20: =IFERROR(IF(INDEX(Proyectos!$W:$W,MATCH($A20,Proyectos!$C:$C,0))="","",INDEX(Proyectos!$W:$W,MATCH($A20,Proyectos!$C:$C,0))),"") | N20: =IFERROR(INDEX(Proyectos!$X:$X,MATCH($A20,Proyectos!$C:$C,0)),"") | O20: =IFERROR(INDEX(Proyectos!$Y:$Y,MATCH($A20,Proyectos!$C:$C,0))&"","")
B21: =IFERROR(IF(INDEX(Proyectos!$A:$A,MATCH($A21,Proyectos!$C:$C,0))="","",INDEX(Proyectos!$A:$A,MATCH($A21,Proyectos!$C:$C,0))),"") | C21: =IFERROR(INDEX(Proyectos!$B:$B,MATCH($A21,Proyectos!$C:$C,0))&"","") | D21: =IFERROR(INDEX(Proyectos!$D:$D,MATCH($A21,Proyectos!$C:$C,0))&"","") | E21: =IFERROR(INDEX(Proyectos!$E:$E,MATCH($A21,Proyectos!$C:$C,0))&"","") | F21: =IFERROR(INDEX(Proyectos!$F:$F,MATCH($A21,Proyectos!$C:$C,0))&"","") | G21: =IFERROR(INDEX(Proyectos!$G:$G,MATCH($A21,Proyectos!$C:$C,0))&"","") | H21: =IFERROR(INDEX(Proyectos!$K:$K,MATCH($A21,Proyectos!$C:$C,0))&"","") | I21: =IFERROR(INDEX(Proyectos!$L:$L,MATCH($A21,Proyectos!$C:$C,0))&"","") | J21: =IFERROR(INDEX(Proyectos!$P:$P,MATCH($A21,Proyectos!$C:$C,0))&"","") | K21: =IFERROR(INDEX(Proyectos!$Q:$Q,MATCH($A21,Proyectos!$C:$C,0))&"","") | L21: =IFERROR(INDEX(Proyectos!$V:$V,MATCH($A21,Proyectos!$C:$C,0))&"","") | M21: =IFERROR(IF(INDEX(Proyectos!$W:$W,MATCH($A21,Proyectos!$C:$C,0))="","",INDEX(Proyectos!$W:$W,MATCH($A21,Proyectos!$C:$C,0))),"") | N21: =IFERROR(INDEX(Proyectos!$X:$X,MATCH($A21,Proyectos!$C:$C,0)),"") | O21: =IFERROR(INDEX(Proyectos!$Y:$Y,MATCH($A21,Proyectos!$C:$C,0))&"","")
B22: =IFERROR(IF(INDEX(Proyectos!$A:$A,MATCH($A22,Proyectos!$C:$C,0))="","",INDEX(Proyectos!$A:$A,MATCH($A22,Proyectos!$C:$C,0))),"") | C22: =IFERROR(INDEX(Proyectos!$B:$B,MATCH($A22,Proyectos!$C:$C,0))&"","") | D22: =IFERROR(INDEX(Proyectos!$D:$D,MATCH($A22,Proyectos!$C:$C,0))&"","") | E22: =IFERROR(INDEX(Proyectos!$E:$E,MATCH($A22,Proyectos!$C:$C,0))&"","") | F22: =IFERROR(INDEX(Proyectos!$F:$F,MATCH($A22,Proyectos!$C:$C,0))&"","") | G22: =IFERROR(INDEX(Proyectos!$G:$G,MATCH($A22,Proyectos!$C:$C,0))&"","") | H22: =IFERROR(INDEX(Proyectos!$K:$K,MATCH($A22,Proyectos!$C:$C,0))&"","") | I22: =IFERROR(INDEX(Proyectos!$L:$L,MATCH($A22,Proyectos!$C:$C,0))&"","") | J22: =IFERROR(INDEX(Proyectos!$P:$P,MATCH($A22,Proyectos!$C:$C,0))&"","") | K22: =IFERROR(INDEX(Proyectos!$Q:$Q,MATCH($A22,Proyectos!$C:$C,0))&"","") | L22: =IFERROR(INDEX(Proyectos!$V:$V,MATCH($A22,Proyectos!$C:$C,0))&"","") | M22: =IFERROR(IF(INDEX(Proyectos!$W:$W,MATCH($A22,Proyectos!$C:$C,0))="","",INDEX(Proyectos!$W:$W,MATCH($A22,Proyectos!$C:$C,0))),"") | N22: =IFERROR(INDEX(Proyectos!$X:$X,MATCH($A22,Proyectos!$C:$C,0)),"") | O22: =IFERROR(INDEX(Proyectos!$Y:$Y,MATCH($A22,Proyectos!$C:$C,0))&"","")
B23: =IFERROR(IF(INDEX(Proyectos!$A:$A,MATCH($A23,Proyectos!$C:$C,0))="","",INDEX(Proyectos!$A:$A,MATCH($A23,Proyectos!$C:$C,0))),"") | C23: =IFERROR(INDEX(Proyectos!$B:$B,MATCH($A23,Proyectos!$C:$C,0))&"","") | D23: =IFERROR(INDEX(Proyectos!$D:$D,MATCH($A23,Proyectos!$C:$C,0))&"","") | E23: =IFERROR(INDEX(Proyectos!$E:$E,MATCH($A23,Proyectos!$C:$C,0))&"","") | F23: =IFERROR(INDEX(Proyectos!$F:$F,MATCH($A23,Proyectos!$C:$C,0))&"","") | G23: =IFERROR(INDEX(Proyectos!$G:$G,MATCH($A23,Proyectos!$C:$C,0))&"","") | H23: =IFERROR(INDEX(Proyectos!$K:$K,MATCH($A23,Proyectos!$C:$C,0))&"","") | I23: =IFERROR(INDEX(Proyectos!$L:$L,MATCH($A23,Proyectos!$C:$C,0))&"","") | J23: =IFERROR(INDEX(Proyectos!$P:$P,MATCH($A23,Proyectos!$C:$C,0))&"","") | K23: =IFERROR(INDEX(Proyectos!$Q:$Q,MATCH($A23,Proyectos!$C:$C,0))&"","") | L23: =IFERROR(INDEX(Proyectos!$V:$V,MATCH($A23,Proyectos!$C:$C,0))&"","") | M23: =IFERROR(IF(INDEX(Proyectos!$W:$W,MATCH($A23,Proyectos!$C:$C,0))="","",INDEX(Proyectos!$W:$W,MATCH($A23,Proyectos!$C:$C,0))),"") | N23: =IFERROR(INDEX(Proyectos!$X:$X,MATCH($A23,Proyectos!$C:$C,0)),"") | O23: =IFERROR(INDEX(Proyectos!$Y:$Y,MATCH($A23,Proyectos!$C:$C,0))&"","")
B24: =IFERROR(IF(INDEX(Proyectos!$A:$A,MATCH($A24,Proyectos!$C:$C,0))="","",INDEX(Proyectos!$A:$A,MATCH($A24,Proyectos!$C:$C,0))),"") | C24: =IFERROR(INDEX(Proyectos!$B:$B,MATCH($A24,Proyectos!$C:$C,0))&"","") | D24: =IFERROR(INDEX(Proyectos!$D:$D,MATCH($A24,Proyectos!$C:$C,0))&"","") | E24: =IFERROR(INDEX(Proyectos!$E:$E,MATCH($A24,Proyectos!$C:$C,0))&"","") | F24: =IFERROR(INDEX(Proyectos!$F:$F,MATCH($A24,Proyectos!$C:$C,0))&"","") | G24: =IFERROR(INDEX(Proyectos!$G:$G,MATCH($A24,Proyectos!$C:$C,0))&"","") | H24: =IFERROR(INDEX(Proyectos!$K:$K,MATCH($A24,Proyectos!$C:$C,0))&"","") | I24: =IFERROR(INDEX(Proyectos!$L:$L,MATCH($A24,Proyectos!$C:$C,0))&"","") | J24: =IFERROR(INDEX(Proyectos!$P:$P,MATCH($A24,Proyectos!$C:$C,0))&"","") | K24: =IFERROR(INDEX(Proyectos!$Q:$Q,MATCH($A24,Proyectos!$C:$C,0))&"","") | L24: =IFERROR(INDEX(Proyectos!$V:$V,MATCH($A24,Proyectos!$C:$C,0))&"","") | M24: =IFERROR(IF(INDEX(Proyectos!$W:$W,MATCH($A24,Proyectos!$C:$C,0))="","",INDEX(Proyectos!$W:$W,MATCH($A24,Proyectos!$C:$C,0))),"") | N24: =IFERROR(INDEX(Proyectos!$X:$X,MATCH($A24,Proyectos!$C:$C,0)),"") | O24: =IFERROR(INDEX(Proyectos!$Y:$Y,MATCH($A24,Proyectos!$C:$C,0))&"","")
B25: =IFERROR(IF(INDEX(Proyectos!$A:$A,MATCH($A25,Proyectos!$C:$C,0))="","",INDEX(Proyectos!$A:$A,MATCH($A25,Proyectos!$C:$C,0))),"") | C25: =IFERROR(INDEX(Proyectos!$B:$B,MATCH($A25,Proyectos!$C:$C,0))&"","") | D25: =IFERROR(INDEX(Proyectos!$D:$D,MATCH($A25,Proyectos!$C:$C,0))&"","") | E25: =IFERROR(INDEX(Proyectos!$E:$E,MATCH($A25,Proyectos!$C:$C,0))&"","") | F25: =IFERROR(INDEX(Proyectos!$F:$F,MATCH($A25,Proyectos!$C:$C,0))&"","") | G25: =IFERROR(INDEX(Proyectos!$G:$G,MATCH($A25,Proyectos!$C:$C,0))&"","") | H25: =IFERROR(INDEX(Proyectos!$K:$K,MATCH($A25,Proyectos!$C:$C,0))&"","") | I25: =IFERROR(INDEX(Proyectos!$L:$L,MATCH($A25,Proyectos!$C:$C,0))&"","") | J25: =IFERROR(INDEX(Proyectos!$P:$P,MATCH($A25,Proyectos!$C:$C,0))&"","") | K25: =IFERROR(INDEX(Proyectos!$Q:$Q,MATCH($A25,Proyectos!$C:$C,0))&"","") | L25: =IFERROR(INDEX(Proyectos!$V:$V,MATCH($A25,Proyectos!$C:$C,0))&"","") | M25: =IFERROR(IF(INDEX(Proyectos!$W:$W,MATCH($A25,Proyectos!$C:$C,0))="","",INDEX(Proyectos!$W:$W,MATCH($A25,Proyectos!$C:$C,0))),"") | N25: =IFERROR(INDEX(Proyectos!$X:$X,MATCH($A25,Proyectos!$C:$C,0)),"") | O25: =IFERROR(INDEX(Proyectos!$Y:$Y,MATCH($A25,Proyectos!$C:$C,0))&"","")

Sheet Aarón
A1: Proyectos — Aarón
A2: Proyectos con Dev = Aarón, ordenados por código. No incluye clientes cerrados. Si te asignan uno nuevo, escribe el nombre exacto del cliente en la columna A.
A3: SOLO EDITAS LAS 3 ÚLTIMAS COLUMNAS, las amarillas del final (P, Q y R): «Marcar» (lista desplegable), «Nota del dev» y «Fecha». Lo que pongas ahí aparece automáticamente en la hoja PROYECTOS. La columna Cliente queda fija al desplazarte a la derecha. Todo lo demás es gris: se lee solo desde PROYECTOS.
A5: Cliente | B5: Prioridad diseño | C5: Código | D5: Correo del cliente | E5: Tipo | F5: Plataforma | G5: Estado | H5: Grupo | I5: Acción de hoy | J5: Material de diseño | K5: Plantilla productos | L5: Qué falta exactamente | M5: Últ. respuesta | N5: Días sin responder | O5: Notas | P5: Marcar | Q5: Nota del dev | R5: Fecha
A6: Maginhard | B6: =IFERROR(IF(INDEX(Proyectos!$A:$A,MATCH($A6,Proyectos!$C:$C,0))="","",INDEX(Proyectos!$A:$A,MATCH($A6,Proyectos!$C:$C,0))),"") | C6: =IFERROR(INDEX(Proyectos!$B:$B,MATCH($A6,Proyectos!$C:$C,0))&"","") -> 026 | D6: =IFERROR(INDEX(Proyectos!$D:$D,MATCH($A6,Proyectos!$C:$C,0))&"","") | E6: =IFERROR(INDEX(Proyectos!$E:$E,MATCH($A6,Proyectos!$C:$C,0))&"","") -> E-commerce | F6: =IFERROR(INDEX(Proyectos!$F:$F,MATCH($A6,Proyectos!$C:$C,0))&"","") -> Por definir | G6: =IFERROR(INDEX(Proyectos!$G:$G,MATCH($A6,Proyectos!$C:$C,0))&"","") -> Esperando material | H6: =IFERROR(INDEX(Proyectos!$K:$K,MATCH($A6,Proyectos!$C:$C,0))&"","") -> B | I6: =IFERROR(INDEX(Proyectos!$L:$L,MATCH($A6,Proyectos!$C:$C,0))&"","") -> PERSEGUIR MATERIAL | J6: =IFERROR(INDEX(Proyectos!$P:$P,MATCH($A6,Proyectos!$C:$C,0))&"","") -> Nada | K6: =IFERROR(INDEX(Proyectos!$Q:$Q,MATCH($A6,Proyectos!$C:$C,0))&"","") -> No enviada | L6: =IFERROR(INDEX(Proyectos!$V:$V,MATCH($A6,Proyectos!$C:$C,0))&"","") -> Todo — BLOQUEADO: no hay acceso al grupo del cliente | M6: =IFERROR(IF(INDEX(Proyectos!$W:$W,MATCH($A6,Proyectos!$C:$C,0))="","",INDEX(Proyectos!$W:$W,MATCH($A6,Proyectos!$C:$C,0))),"") | N6: =IFERROR(INDEX(Proyectos!$X:$X,MATCH($A6,Proyectos!$C:$C,0)),"") | O6: =IFERROR(INDEX(Proyectos!$Y:$Y,MATCH($A6,Proyectos!$C:$C,0))&"","") -> Cliente: Kevin. Dev histórico: Aarón. Requiere desbloquear canal de comunicación antes de nada. 30
A7: Jufrarvp S.R.L. | B7: =IFERROR(IF(INDEX(Proyectos!$A:$A,MATCH($A7,Proyectos!$C:$C,0))="","",INDEX(Proyectos!$A:$A,MATCH($A7,Proyectos!$C:$C,0))),"") | C7: =IFERROR(INDEX(Proyectos!$B:$B,MATCH($A7,Proyectos!$C:$C,0))&"","") -> 035 | D7: =IFERROR(INDEX(Proyectos!$D:$D,MATCH($A7,Proyectos!$C:$C,0))&"","") | E7: =IFERROR(INDEX(Proyectos!$E:$E,MATCH($A7,Proyectos!$C:$C,0))&"","") -> E-commerce | F7: =IFERROR(INDEX(Proyectos!$F:$F,MATCH($A7,Proyectos!$C:$C,0))&"","") -> Por definir | G7: =IFERROR(INDEX(Proyectos!$G:$G,MATCH($A7,Proyectos!$C:$C,0))&"","") -> Congelado | H7: =IFERROR(INDEX(Proyectos!$K:$K,MATCH($A7,Proyectos!$C:$C,0))&"","") -> A | I7: =IFERROR(INDEX(Proyectos!$L:$L,MATCH($A7,Proyectos!$C:$C,0))&"","") -> Congelado — mensaje cada 15 días | J7: =IFERROR(INDEX(Proyectos!$P:$P,MATCH($A7,Proyectos!$C:$C,0))&"","") -> Completo | K7: =IFERROR(INDEX(Proyectos!$Q:$Q,MATCH($A7,Proyectos!$C:$C,0))&"","") -> Recibida y validada | L7: =IFERROR(INDEX(Proyectos!$V:$V,MATCH($A7,Proyectos!$C:$C,0))&"","") -> Validación/aprobación del cliente | M7: =IFERROR(IF(INDEX(Proyectos!$W:$W,MATCH($A7,Proyectos!$C:$C,0))="","",INDEX(Proyectos!$W:$W,MATCH($A7,Proyectos!$C:$C,0))),"") | N7: =IFERROR(INDEX(Proyectos!$X:$X,MATCH($A7,Proyectos!$C:$C,0)),"") | O7: =IFERROR(INDEX(Proyectos!$Y:$Y,MATCH($A7,Proyectos!$C:$C,0))&"","") -> Cliente: Julio Ponce. Sin fecha de última respuesta registrada — confirmar.
A8: Soluz | B8: =IFERROR(IF(INDEX(Proyectos!$A:$A,MATCH($A8,Proyectos!$C:$C,0))="","",INDEX(Proyectos!$A:$A,MATCH($A8,Proyectos!$C:$C,0))),"") | C8: =IFERROR(INDEX(Proyectos!$B:$B,MATCH($A8,Proyectos!$C:$C,0))&"","") -> 036 | D8: =IFERROR(INDEX(Proyectos!$D:$D,MATCH($A8,Proyectos!$C:$C,0))&"","") | E8: =IFERROR(INDEX(Proyectos!$E:$E,MATCH($A8,Proyectos!$C:$C,0))&"","") -> E-commerce | F8: =IFERROR(INDEX(Proyectos!$F:$F,MATCH($A8,Proyectos!$C:$C,0))&"","") -> Por definir | G8: =IFERROR(INDEX(Proyectos!$G:$G,MATCH($A8,Proyectos!$C:$C,0))&"","") -> Desarrollo | H8: =IFERROR(INDEX(Proyectos!$K:$K,MATCH($A8,Proyectos!$C:$C,0))&"","") -> A | I8: =IFERROR(INDEX(Proyectos!$L:$L,MATCH($A8,Proyectos!$C:$C,0))&"","") -> CONGELAR HOY | J8: =IFERROR(INDEX(Proyectos!$P:$P,MATCH($A8,Proyectos!$C:$C,0))&"","") -> Completo | K8: =IFERROR(INDEX(Proyectos!$Q:$Q,MATCH($A8,Proyectos!$C:$C,0))&"","") -> No enviada | L8: =IFERROR(INDEX(Proyectos!$V:$V,MATCH($A8,Proyectos!$C:$C,0))&"","") -> Reunión reprogramada + validación del cliente sobre carga de productos | M8: =IFERROR(IF(INDEX(Proyectos!$W:$W,MATCH($A8,Proyectos!$C:$C,0))="","",INDEX(Proyectos!$W:$W,MATCH($A8,Proyectos!$C:$C,0))),"") -> 46213 | N8: =IFERROR(INDEX(Proyectos!$X:$X,MATCH($A8,Proyectos!$C:$C,0)),"") -> 24 | O8: =IFERROR(INDEX(Proyectos!$Y:$Y,MATCH($A8,Proyectos!$C:$C,0))&"","") -> Cliente: Giancarlo Rosario. En transición de Aarón a Luis (aún no formalizada).
A9: Maquinarias Aoxiang | B9: =IFERROR(IF(INDEX(Proyectos!$A:$A,MATCH($A9,Proyectos!$C:$C,0))="","",INDEX(Proyectos!$A:$A,MATCH($A9,Proyectos!$C:$C,0))),"") | C9: =IFERROR(INDEX(Proyectos!$B:$B,MATCH($A9,Proyectos!$C:$C,0))&"","") -> 040 | D9: =IFERROR(INDEX(Proyectos!$D:$D,MATCH($A9,Proyectos!$C:$C,0))&"","") | E9: =IFERROR(INDEX(Proyectos!$E:$E,MATCH($A9,Proyectos!$C:$C,0))&"","") -> E-commerce | F9: =IFERROR(INDEX(Proyectos!$F:$F,MATCH($A9,Proyectos!$C:$C,0))&"","") -> Por definir | G9: =IFERROR(INDEX(Proyectos!$G:$G,MATCH($A9,Proyectos!$C:$C,0))&"","") -> Cerrado | H9: =IFERROR(INDEX(Proyectos!$K:$K,MATCH($A9,Proyectos!$C:$C,0))&"","") -> A | I9: =IFERROR(INDEX(Proyectos!$L:$L,MATCH($A9,Proyectos!$C:$C,0))&"","") -> CONGELAR HOY | J9: =IFERROR(INDEX(Proyectos!$P:$P,MATCH($A9,Proyectos!$C:$C,0))&"","") -> Completo | K9: =IFERROR(INDEX(Proyectos!$Q:$Q,MATCH($A9,Proyectos!$C:$C,0))&"","") -> Recibida con errores | L9: =IFERROR(INDEX(Proyectos!$V:$V,MATCH($A9,Proyectos!$C:$C,0))&"","") -> Nada — diseño aprobado | M9: =IFERROR(IF(INDEX(Proyectos!$W:$W,MATCH($A9,Proyectos!$C:$C,0))="","",INDEX(Proyectos!$W:$W,MATCH($A9,Proyectos!$C:$C,0))),"") -> 46200 | N9: =IFERROR(INDEX(Proyectos!$X:$X,MATCH($A9,Proyectos!$C:$C,0)),"") -> 37 | O9: =IFERROR(INDEX(Proyectos!$Y:$Y,MATCH($A9,Proyectos!$C:$C,0))&"","") -> Cliente: Liliana y Javier.
A10: Youbi Importaciones | B10: =IFERROR(IF(INDEX(Proyectos!$A:$A,MATCH($A10,Proyectos!$C:$C,0))="","",INDEX(Proyectos!$A:$A,MATCH($A10,Proyectos!$C:$C,0))),"") | C10: =IFERROR(INDEX(Proyectos!$B:$B,MATCH($A10,Proyectos!$C:$C,0))&"","") -> 053 | D10: =IFERROR(INDEX(Proyectos!$D:$D,MATCH($A10,Proyectos!$C:$C,0))&"","") | E10: =IFERROR(INDEX(Proyectos!$E:$E,MATCH($A10,Proyectos!$C:$C,0))&"","") -> Informativa | F10: =IFERROR(INDEX(Proyectos!$F:$F,MATCH($A10,Proyectos!$C:$C,0))&"","") -> Por definir | G10: =IFERROR(INDEX(Proyectos!$G:$G,MATCH($A10,Proyectos!$C:$C,0))&"","") -> Desarrollo | H10: =IFERROR(INDEX(Proyectos!$K:$K,MATCH($A10,Proyectos!$C:$C,0))&"","") -> A | I10: =IFERROR(INDEX(Proyectos!$L:$L,MATCH($A10,Proyectos!$C:$C,0))&"","") -> CONGELAR HOY | J10: =IFERROR(INDEX(Proyectos!$P:$P,MATCH($A10,Proyectos!$C:$C,0))&"","") -> Completo | K10: =IFERROR(INDEX(Proyectos!$Q:$Q,MATCH($A10,Proyectos!$C:$C,0))&"","") -> No aplica | L10: =IFERROR(INDEX(Proyectos!$V:$V,MATCH($A10,Proyectos!$C:$C,0))&"","") -> Validación de diseño en paralelo al desarrollo | M10: =IFERROR(IF(INDEX(Proyectos!$W:$W,MATCH($A10,Proyectos!$C:$C,0))="","",INDEX(Proyectos!$W:$W,MATCH($A10,Proyectos!$C:$C,0))),"") -> 46212 | N10: =IFERROR(INDEX(Proyectos!$X:$X,MATCH($A10,Proyectos!$C:$C,0)),"") -> 25 | O10: =IFERROR(INDEX(Proyectos!$Y:$Y,MATCH($A10,Proyectos!$C:$C,0))&"","") -> Cliente: Jenifer y Jorge. 30% pagado.
A11: Los Halcones | B11: =IFERROR(IF(INDEX(Proyectos!$A:$A,MATCH($A11,Proyectos!$C:$C,0))="","",INDEX(Proyectos!$A:$A,MATCH($A11,Proyectos!$C:$C,0))),"") | C11: =IFERROR(INDEX(Proyectos!$B:$B,MATCH($A11,Proyectos!$C:$C,0))&"","") -> 059 | D11: =IFERROR(INDEX(Proyectos!$D:$D,MATCH($A11,Proyectos!$C:$C,0))&"","") | E11: =IFERROR(INDEX(Proyectos!$E:$E,MATCH($A11,Proyectos!$C:$C,0))&"","") -> E-commerce | F11: =IFERROR(INDEX(Proyectos!$F:$F,MATCH($A11,Proyectos!$C:$C,0))&"","") -> Por definir | G11: =IFERROR(INDEX(Proyectos!$G:$G,MATCH($A11,Proyectos!$C:$C,0))&"","") -> Desarrollo | H11: =IFERROR(INDEX(Proyectos!$K:$K,MATCH($A11,Proyectos!$C:$C,0))&"","") -> A | I11: =IFERROR(INDEX(Proyectos!$L:$L,MATCH($A11,Proyectos!$C:$C,0))&"","") -> CONGELAR HOY | J11: =IFERROR(INDEX(Proyectos!$P:$P,MATCH($A11,Proyectos!$C:$C,0))&"","") -> Completo | K11: =IFERROR(INDEX(Proyectos!$Q:$Q,MATCH($A11,Proyectos!$C:$C,0))&"","") -> No aplica | L11: =IFERROR(INDEX(Proyectos!$V:$V,MATCH($A11,Proyectos!$C:$C,0))&"","") -> Nada — en implementación, cliente informado y disponible | M11: =IFERROR(IF(INDEX(Proyectos!$W:$W,MATCH($A11,Proyectos!$C:$C,0))="","",INDEX(Proyectos!$W:$W,MATCH($A11,Proyectos!$C:$C,0))),"") -> 46218 | N11: =IFERROR(INDEX(Proyectos!$X:$X,MATCH($A11,Proyectos!$C:$C,0)),"") -> 19 | O11: =IFERROR(INDEX(Proyectos!$Y:$Y,MATCH($A11,Proyectos!$C:$C,0))&"","") -> Cliente: Juan. - Cita viernes 24-07
A12: Erika Garay | B12: =IFERROR(IF(INDEX(Proyectos!$A:$A,MATCH($A12,Proyectos!$C:$C,0))="","",INDEX(Proyectos!$A:$A,MATCH($A12,Proyectos!$C:$C,0))),"") -> 2 | C12: =IFERROR(INDEX(Proyectos!$B:$B,MATCH($A12,Proyectos!$C:$C,0))&"","") -> 066 | D12: =IFERROR(INDEX(Proyectos!$D:$D,MATCH($A12,Proyectos!$C:$C,0))&"","") | E12: =IFERROR(INDEX(Proyectos!$E:$E,MATCH($A12,Proyectos!$C:$C,0))&"","") -> E-commerce | F12: =IFERROR(INDEX(Proyectos!$F:$F,MATCH($A12,Proyectos!$C:$C,0))&"","") -> Por definir | G12: =IFERROR(INDEX(Proyectos!$G:$G,MATCH($A12,Proyectos!$C:$C,0))&"","") -> Diseño | H12: =IFERROR(INDEX(Proyectos!$K:$K,MATCH($A12,Proyectos!$C:$C,0))&"","") -> A | I12: =IFERROR(INDEX(Proyectos!$L:$L,MATCH($A12,Proyectos!$C:$C,0))&"","") -> CONGELAR HOY | J12: =IFERROR(INDEX(Proyectos!$P:$P,MATCH($A12,Proyectos!$C:$C,0))&"","") -> Completo | K12: =IFERROR(INDEX(Proyectos!$Q:$Q,MATCH($A12,Proyectos!$C:$C,0))&"","") -> No enviada | L12: =IFERROR(INDEX(Proyectos!$V:$V,MATCH($A12,Proyectos!$C:$C,0))&"","") -> Material de diseño en general | M12: =IFERROR(IF(INDEX(Proyectos!$W:$W,MATCH($A12,Proyectos!$C:$C,0))="","",INDEX(Proyectos!$W:$W,MATCH($A12,Proyectos!$C:$C,0))),"") -> 46218 | N12: =IFERROR(INDEX(Proyectos!$X:$X,MATCH($A12,Proyectos!$C:$C,0)),"") -> 19 | O12: =IFERROR(INDEX(Proyectos!$Y:$Y,MATCH($A12,Proyectos!$C:$C,0))&"","") -> Cliente: Erika Garay. Dev histórico: Aarón.
A13: Camaleon | B13: =IFERROR(IF(INDEX(Proyectos!$A:$A,MATCH($A13,Proyectos!$C:$C,0))="","",INDEX(Proyectos!$A:$A,MATCH($A13,Proyectos!$C:$C,0))),"") -> 11 | C13: =IFERROR(INDEX(Proyectos!$B:$B,MATCH($A13,Proyectos!$C:$C,0))&"","") -> 068 | D13: =IFERROR(INDEX(Proyectos!$D:$D,MATCH($A13,Proyectos!$C:$C,0))&"","") | E13: =IFERROR(INDEX(Proyectos!$E:$E,MATCH($A13,Proyectos!$C:$C,0))&"","") -> E-commerce | F13: =IFERROR(INDEX(Proyectos!$F:$F,MATCH($A13,Proyectos!$C:$C,0))&"","") -> Por definir | G13: =IFERROR(INDEX(Proyectos!$G:$G,MATCH($A13,Proyectos!$C:$C,0))&"","") -> Esperando material | H13: =IFERROR(INDEX(Proyectos!$K:$K,MATCH($A13,Proyectos!$C:$C,0))&"","") -> B | I13: =IFERROR(INDEX(Proyectos!$L:$L,MATCH($A13,Proyectos!$C:$C,0))&"","") -> CONGELAR HOY | J13: =IFERROR(INDEX(Proyectos!$P:$P,MATCH($A13,Proyectos!$C:$C,0))&"","") -> Nada | K13: =IFERROR(INDEX(Proyectos!$Q:$Q,MATCH($A13,Proyectos!$C:$C,0))&"","") -> No enviada | L13: =IFERROR(INDEX(Proyectos!$V:$V,MATCH($A13,Proyectos!$C:$C,0))&"","") -> Todo — recién se llenó el brief | M13: =IFERROR(IF(INDEX(Proyectos!$W:$W,MATCH($A13,Proyectos!$C:$C,0))="","",INDEX(Proyectos!$W:$W,MATCH($A13,Proyectos!$C:$C,0))),"") -> 46219 | N13: =IFERROR(INDEX(Proyectos!$X:$X,MATCH($A13,Proyectos!$C:$C,0)),"") -> 18 | O13: =IFERROR(INDEX(Proyectos!$Y:$Y,MATCH($A13,Proyectos!$C:$C,0))&"","") -> Cliente: Lady Quispe. Dev histórico: Aarón. Marca previa de Juan Carlos (el proyecto salió de su hoja por no estar en grupo A): «PERSEGUIR».
A14: Buzz Studios | B14: =IFERROR(IF(INDEX(Proyectos!$A:$A,MATCH($A14,Proyectos!$C:$C,0))="","",INDEX(Proyectos!$A:$A,MATCH($A14,Proyectos!$C:$C,0))),"") -> 7 | C14: =IFERROR(INDEX(Proyectos!$B:$B,MATCH($A14,Proyectos!$C:$C,0))&"","") -> 070 | D14: =IFERROR(INDEX(Proyectos!$D:$D,MATCH($A14,Proyectos!$C:$C,0))&"","") | E14: =IFERROR(INDEX(Proyectos!$E:$E,MATCH($A14,Proyectos!$C:$C,0))&"","") -> E-commerce | F14: =IFERROR(INDEX(Proyectos!$F:$F,MATCH($A14,Proyectos!$C:$C,0))&"","") -> Por definir | G14: =IFERROR(INDEX(Proyectos!$G:$G,MATCH($A14,Proyectos!$C:$C,0))&"","") -> Diseño | H14: =IFERROR(INDEX(Proyectos!$K:$K,MATCH($A14,Proyectos!$C:$C,0))&"","") -> A | I14: =IFERROR(INDEX(Proyectos!$L:$L,MATCH($A14,Proyectos!$C:$C,0))&"","") -> CONGELAR HOY | J14: =IFERROR(INDEX(Proyectos!$P:$P,MATCH($A14,Proyectos!$C:$C,0))&"","") -> Completo | K14: =IFERROR(INDEX(Proyectos!$Q:$Q,MATCH($A14,Proyectos!$C:$C,0))&"","") -> No enviada | L14: =IFERROR(INDEX(Proyectos!$V:$V,MATCH($A14,Proyectos!$C:$C,0))&"","") -> Material de diseño (brief y drive ya completados administrativamente) | M14: =IFERROR(IF(INDEX(Proyectos!$W:$W,MATCH($A14,Proyectos!$C:$C,0))="","",INDEX(Proyectos!$W:$W,MATCH($A14,Proyectos!$C:$C,0))),"") -> 46218 | N14: =IFERROR(INDEX(Proyectos!$X:$X,MATCH($A14,Proyectos!$C:$C,0)),"") -> 19 | O14: =IFERROR(INDEX(Proyectos!$Y:$Y,MATCH($A14,Proyectos!$C:$C,0))&"","") -> Cliente: Elvis Stefano. Dev histórico: Aarón.
A15: HSM Foods & Agro | B15: =IFERROR(IF(INDEX(Proyectos!$A:$A,MATCH($A15,Proyectos!$C:$C,0))="","",INDEX(Proyectos!$A:$A,MATCH($A15,Proyectos!$C:$C,0))),"") -> 3 | C15: =IFERROR(INDEX(Proyectos!$B:$B,MATCH($A15,Proyectos!$C:$C,0))&"","") -> 074 | D15: =IFERROR(INDEX(Proyectos!$D:$D,MATCH($A15,Proyectos!$C:$C,0))&"","") | E15: =IFERROR(INDEX(Proyectos!$E:$E,MATCH($A15,Proyectos!$C:$C,0))&"","") -> E-commerce | F15: =IFERROR(INDEX(Proyectos!$F:$F,MATCH($A15,Proyectos!$C:$C,0))&"","") -> Por definir | G15: =IFERROR(INDEX(Proyectos!$G:$G,MATCH($A15,Proyectos!$C:$C,0))&"","") -> Diseño | H15: =IFERROR(INDEX(Proyectos!$K:$K,MATCH($A15,Proyectos!$C:$C,0))&"","") -> A | I15: =IFERROR(INDEX(Proyectos!$L:$L,MATCH($A15,Proyectos!$C:$C,0))&"","") -> CONGELAR HOY | J15: =IFERROR(INDEX(Proyectos!$P:$P,MATCH($A15,Proyectos!$C:$C,0))&"","") -> Completo | K15: =IFERROR(INDEX(Proyectos!$Q:$Q,MATCH($A15,Proyectos!$C:$C,0))&"","") -> Recibida con errores | L15: =IFERROR(INDEX(Proyectos!$V:$V,MATCH($A15,Proyectos!$C:$C,0))&"","") -> Fotos (comprometidas para la próxima semana) | M15: =IFERROR(IF(INDEX(Proyectos!$W:$W,MATCH($A15,Proyectos!$C:$C,0))="","",INDEX(Proyectos!$W:$W,MATCH($A15,Proyectos!$C:$C,0))),"") -> 46218 | N15: =IFERROR(INDEX(Proyectos!$X:$X,MATCH($A15,Proyectos!$C:$C,0)),"") -> 19 | O15: =IFERROR(INDEX(Proyectos!$Y:$Y,MATCH($A15,Proyectos!$C:$C,0))&"","") -> Cliente: Sebastian y Mauricio. Dev histórico: Aarón. PENDIENTE: subir las fotos al Drive. Pedir en el grupo que suban el brief al Drive para que Luis lo descargue.
A16: Raul Cabana | B16: =IFERROR(IF(INDEX(Proyectos!$A:$A,MATCH($A16,Proyectos!$C:$C,0))="","",INDEX(Proyectos!$A:$A,MATCH($A16,Proyectos!$C:$C,0))),"") -> 10 | C16: =IFERROR(INDEX(Proyectos!$B:$B,MATCH($A16,Proyectos!$C:$C,0))&"","") -> 076 | D16: =IFERROR(INDEX(Proyectos!$D:$D,MATCH($A16,Proyectos!$C:$C,0))&"","") | E16: =IFERROR(INDEX(Proyectos!$E:$E,MATCH($A16,Proyectos!$C:$C,0))&"","") -> E-commerce | F16: =IFERROR(INDEX(Proyectos!$F:$F,MATCH($A16,Proyectos!$C:$C,0))&"","") -> Por definir | G16: =IFERROR(INDEX(Proyectos!$G:$G,MATCH($A16,Proyectos!$C:$C,0))&"","") -> Cola | H16: =IFERROR(INDEX(Proyectos!$K:$K,MATCH($A16,Proyectos!$C:$C,0))&"","") -> B | I16: =IFERROR(INDEX(Proyectos!$L:$L,MATCH($A16,Proyectos!$C:$C,0))&"","") -> CONGELAR HOY | J16: =IFERROR(INDEX(Proyectos!$P:$P,MATCH($A16,Proyectos!$C:$C,0))&"","") -> Incompleto | K16: =IFERROR(INDEX(Proyectos!$Q:$Q,MATCH($A16,Proyectos!$C:$C,0))&"","") -> No enviada | L16: =IFERROR(INDEX(Proyectos!$V:$V,MATCH($A16,Proyectos!$C:$C,0))&"","") -> Material de diseño en general | M16: =IFERROR(IF(INDEX(Proyectos!$W:$W,MATCH($A16,Proyectos!$C:$C,0))="","",INDEX(Proyectos!$W:$W,MATCH($A16,Proyectos!$C:$C,0))),"") -> 46218 | N16: =IFERROR(INDEX(Proyectos!$X:$X,MATCH($A16,Proyectos!$C:$C,0)),"") -> 19 | O16: =IFERROR(INDEX(Proyectos!$Y:$Y,MATCH($A16,Proyectos!$C:$C,0))&"","") -> Cliente: Raul Cabana. Dev histórico: Aarón.
A17: Doctor G | B17: =IFERROR(IF(INDEX(Proyectos!$A:$A,MATCH($A17,Proyectos!$C:$C,0))="","",INDEX(Proyectos!$A:$A,MATCH($A17,Proyectos!$C:$C,0))),"") | C17: =IFERROR(INDEX(Proyectos!$B:$B,MATCH($A17,Proyectos!$C:$C,0))&"","") -> 079 | D17: =IFERROR(INDEX(Proyectos!$D:$D,MATCH($A17,Proyectos!$C:$C,0))&"","") | E17: =IFERROR(INDEX(Proyectos!$E:$E,MATCH($A17,Proyectos!$C:$C,0))&"","") -> Informativa | F17: =IFERROR(INDEX(Proyectos!$F:$F,MATCH($A17,Proyectos!$C:$C,0))&"","") -> Por definir | G17: =IFERROR(INDEX(Proyectos!$G:$G,MATCH($A17,Proyectos!$C:$C,0))&"","") -> Cola | H17: =IFERROR(INDEX(Proyectos!$K:$K,MATCH($A17,Proyectos!$C:$C,0))&"","") -> A | I17: =IFERROR(INDEX(Proyectos!$L:$L,MATCH($A17,Proyectos!$C:$C,0))&"","") -> Listo para asignar | J17: =IFERROR(INDEX(Proyectos!$P:$P,MATCH($A17,Proyectos!$C:$C,0))&"","") -> Completo | K17: =IFERROR(INDEX(Proyectos!$Q:$Q,MATCH($A17,Proyectos!$C:$C,0))&"","") -> No aplica | L17: =IFERROR(INDEX(Proyectos!$V:$V,MATCH($A17,Proyectos!$C:$C,0))&"","") -> Todo — sin información registrada aún | M17: =IFERROR(IF(INDEX(Proyectos!$W:$W,MATCH($A17,Proyectos!$C:$C,0))="","",INDEX(Proyectos!$W:$W,MATCH($A17,Proyectos!$C:$C,0))),"") | N17: =IFERROR(INDEX(Proyectos!$X:$X,MATCH($A17,Proyectos!$C:$C,0)),"") | O17: =IFERROR(INDEX(Proyectos!$Y:$Y,MATCH($A17,Proyectos!$C:$C,0))&"","") -> Dev histórico: Aarón. Cliente sin identificar en los registros — confirmar nombre. Viernes 24/07 cinco pm
... A19: Industrial Protection | B19: =IFERROR(IF(INDEX(Proyectos!$A:$A,MATCH($A19,Proyectos!$C:$C,0))="","",INDEX(Proyectos!$A:$A,MATCH($A19,Proyectos!$C:$C,0))),"") | C19: =IFERROR(INDEX(Proyectos!$B:$B,MATCH($A19,Proyectos!$C:$C,0))&"","") | D19: =IFERROR(INDEX(Proyectos!$D:$D,MATCH($A19,Proyectos!$C:$C,0))&"","") | E19: =IFERROR(INDEX(Proyectos!$E:$E,MATCH($A19,Proyectos!$C:$C,0))&"","") -> E-commerce | F19: =IFERROR(INDEX(Proyectos!$F:$F,MATCH($A19,Proyectos!$C:$C,0))&"","") -> Por definir | G19: =IFERROR(INDEX(Proyectos!$G:$G,MATCH($A19,Proyectos!$C:$C,0))&"","") -> Congelado | H19: =IFERROR(INDEX(Proyectos!$K:$K,MATCH($A19,Proyectos!$C:$C,0))&"","") -> B | I19: =IFERROR(INDEX(Proyectos!$L:$L,MATCH($A19,Proyectos!$C:$C,0))&"","") -> Congelado — mensaje cada 15 días | J19: =IFERROR(INDEX(Proyectos!$P:$P,MATCH($A19,Proyectos!$C:$C,0))&"","") -> Nada | K19: =IFERROR(INDEX(Proyectos!$Q:$Q,MATCH($A19,Proyectos!$C:$C,0))&"","") -> No aplica | L19: =IFERROR(INDEX(Proyectos!$V:$V,MATCH($A19,Proyectos!$C:$C,0))&"","") -> Todo — lead sin pago ni código | M19: =IFERROR(IF(INDEX(Proyectos!$W:$W,MATCH($A19,Proyectos!$C:$C,0))="","",INDEX(Proyectos!$W:$W,MATCH($A19,Proyectos!$C:$C,0))),"") | N19: =IFERROR(INDEX(Proyectos!$X:$X,MATCH($A19,Proyectos!$C:$C,0)),"") | O19: =IFERROR(INDEX(Proyectos!$Y:$Y,MATCH($A19,Proyectos!$C:$C,0))&"","") -> Cliente: Rugui. Primer contacto registrado 5/6/2026. Recuperado de la hoja de Aarón (no estaba en Proyectos).
B20: =IFERROR(IF(INDEX(Proyectos!$A:$A,MATCH($A20,Proyectos!$C:$C,0))="","",INDEX(Proyectos!$A:$A,MATCH($A20,Proyectos!$C:$C,0))),"") | C20: =IFERROR(INDEX(Proyectos!$B:$B,MATCH($A20,Proyectos!$C:$C,0))&"","") | D20: =IFERROR(INDEX(Proyectos!$D:$D,MATCH($A20,Proyectos!$C:$C,0))&"","") | E20: =IFERROR(INDEX(Proyectos!$E:$E,MATCH($A20,Proyectos!$C:$C,0))&"","") | F20: =IFERROR(INDEX(Proyectos!$F:$F,MATCH($A20,Proyectos!$C:$C,0))&"","") | G20: =IFERROR(INDEX(Proyectos!$G:$G,MATCH($A20,Proyectos!$C:$C,0))&"","") | H20: =IFERROR(INDEX(Proyectos!$K:$K,MATCH($A20,Proyectos!$C:$C,0))&"","") | I20: =IFERROR(INDEX(Proyectos!$L:$L,MATCH($A20,Proyectos!$C:$C,0))&"","") | J20: =IFERROR(INDEX(Proyectos!$P:$P,MATCH($A20,Proyectos!$C:$C,0))&"","") | K20: =IFERROR(INDEX(Proyectos!$Q:$Q,MATCH($A20,Proyectos!$C:$C,0))&"","") | L20: =IFERROR(INDEX(Proyectos!$V:$V,MATCH($A20,Proyectos!$C:$C,0))&"","") | M20: =IFERROR(IF(INDEX(Proyectos!$W:$W,MATCH($A20,Proyectos!$C:$C,0))="","",INDEX(Proyectos!$W:$W,MATCH($A20,Proyectos!$C:$C,0))),"") | N20: =IFERROR(INDEX(Proyectos!$X:$X,MATCH($A20,Proyectos!$C:$C,0)),"") | O20: =IFERROR(INDEX(Proyectos!$Y:$Y,MATCH($A20,Proyectos!$C:$C,0))&"","")
B21: =IFERROR(IF(INDEX(Proyectos!$A:$A,MATCH($A21,Proyectos!$C:$C,0))="","",INDEX(Proyectos!$A:$A,MATCH($A21,Proyectos!$C:$C,0))),"") | C21: =IFERROR(INDEX(Proyectos!$B:$B,MATCH($A21,Proyectos!$C:$C,0))&"","") | D21: =IFERROR(INDEX(Proyectos!$D:$D,MATCH($A21,Proyectos!$C:$C,0))&"","") | E21: =IFERROR(INDEX(Proyectos!$E:$E,MATCH($A21,Proyectos!$C:$C,0))&"","") | F21: =IFERROR(INDEX(Proyectos!$F:$F,MATCH($A21,Proyectos!$C:$C,0))&"","") | G21: =IFERROR(INDEX(Proyectos!$G:$G,MATCH($A21,Proyectos!$C:$C,0))&"","") | H21: =IFERROR(INDEX(Proyectos!$K:$K,MATCH($A21,Proyectos!$C:$C,0))&"","") | I21: =IFERROR(INDEX(Proyectos!$L:$L,MATCH($A21,Proyectos!$C:$C,0))&"","") | J21: =IFERROR(INDEX(Proyectos!$P:$P,MATCH($A21,Proyectos!$C:$C,0))&"","") | K21: =IFERROR(INDEX(Proyectos!$Q:$Q,MATCH($A21,Proyectos!$C:$C,0))&"","") | L21: =IFERROR(INDEX(Proyectos!$V:$V,MATCH($A21,Proyectos!$C:$C,0))&"","") | M21: =IFERROR(IF(INDEX(Proyectos!$W:$W,MATCH($A21,Proyectos!$C:$C,0))="","",INDEX(Proyectos!$W:$W,MATCH($A21,Proyectos!$C:$C,0))),"") | N21: =IFERROR(INDEX(Proyectos!$X:$X,MATCH($A21,Proyectos!$C:$C,0)),"") | O21: =IFERROR(INDEX(Proyectos!$Y:$Y,MATCH($A21,Proyectos!$C:$C,0))&"","")
B22: =IFERROR(IF(INDEX(Proyectos!$A:$A,MATCH($A22,Proyectos!$C:$C,0))="","",INDEX(Proyectos!$A:$A,MATCH($A22,Proyectos!$C:$C,0))),"") | C22: =IFERROR(INDEX(Proyectos!$B:$B,MATCH($A22,Proyectos!$C:$C,0))&"","") | D22: =IFERROR(INDEX(Proyectos!$D:$D,MATCH($A22,Proyectos!$C:$C,0))&"","") | E22: =IFERROR(INDEX(Proyectos!$E:$E,MATCH($A22,Proyectos!$C:$C,0))&"","") | F22: =IFERROR(INDEX(Proyectos!$F:$F,MATCH($A22,Proyectos!$C:$C,0))&"","") | G22: =IFERROR(INDEX(Proyectos!$G:$G,MATCH($A22,Proyectos!$C:$C,0))&"","") | H22: =IFERROR(INDEX(Proyectos!$K:$K,MATCH($A22,Proyectos!$C:$C,0))&"","") | I22: =IFERROR(INDEX(Proyectos!$L:$L,MATCH($A22,Proyectos!$C:$C,0))&"","") | J22: =IFERROR(INDEX(Proyectos!$P:$P,MATCH($A22,Proyectos!$C:$C,0))&"","") | K22: =IFERROR(INDEX(Proyectos!$Q:$Q,MATCH($A22,Proyectos!$C:$C,0))&"","") | L22: =IFERROR(INDEX(Proyectos!$V:$V,MATCH($A22,Proyectos!$C:$C,0))&"","") | M22: =IFERROR(IF(INDEX(Proyectos!$W:$W,MATCH($A22,Proyectos!$C:$C,0))="","",INDEX(Proyectos!$W:$W,MATCH($A22,Proyectos!$C:$C,0))),"") | N22: =IFERROR(INDEX(Proyectos!$X:$X,MATCH($A22,Proyectos!$C:$C,0)),"") | O22: =IFERROR(INDEX(Proyectos!$Y:$Y,MATCH($A22,Proyectos!$C:$C,0))&"","")
B23: =IFERROR(IF(INDEX(Proyectos!$A:$A,MATCH($A23,Proyectos!$C:$C,0))="","",INDEX(Proyectos!$A:$A,MATCH($A23,Proyectos!$C:$C,0))),"") | C23: =IFERROR(INDEX(Proyectos!$B:$B,MATCH($A23,Proyectos!$C:$C,0))&"","") | D23: =IFERROR(INDEX(Proyectos!$D:$D,MATCH($A23,Proyectos!$C:$C,0))&"","") | E23: =IFERROR(INDEX(Proyectos!$E:$E,MATCH($A23,Proyectos!$C:$C,0))&"","") | F23: =IFERROR(INDEX(Proyectos!$F:$F,MATCH($A23,Proyectos!$C:$C,0))&"","") | G23: =IFERROR(INDEX(Proyectos!$G:$G,MATCH($A23,Proyectos!$C:$C,0))&"","") | H23: =IFERROR(INDEX(Proyectos!$K:$K,MATCH($A23,Proyectos!$C:$C,0))&"","") | I23: =IFERROR(INDEX(Proyectos!$L:$L,MATCH($A23,Proyectos!$C:$C,0))&"","") | J23: =IFERROR(INDEX(Proyectos!$P:$P,MATCH($A23,Proyectos!$C:$C,0))&"","") | K23: =IFERROR(INDEX(Proyectos!$Q:$Q,MATCH($A23,Proyectos!$C:$C,0))&"","") | L23: =IFERROR(INDEX(Proyectos!$V:$V,MATCH($A23,Proyectos!$C:$C,0))&"","") | M23: =IFERROR(IF(INDEX(Proyectos!$W:$W,MATCH($A23,Proyectos!$C:$C,0))="","",INDEX(Proyectos!$W:$W,MATCH($A23,Proyectos!$C:$C,0))),"") | N23: =IFERROR(INDEX(Proyectos!$X:$X,MATCH($A23,Proyectos!$C:$C,0)),"") | O23: =IFERROR(INDEX(Proyectos!$Y:$Y,MATCH($A23,Proyectos!$C:$C,0))&"","")
B24: =IFERROR(IF(INDEX(Proyectos!$A:$A,MATCH($A24,Proyectos!$C:$C,0))="","",INDEX(Proyectos!$A:$A,MATCH($A24,Proyectos!$C:$C,0))),"") | C24: =IFERROR(INDEX(Proyectos!$B:$B,MATCH($A24,Proyectos!$C:$C,0))&"","") | D24: =IFERROR(INDEX(Proyectos!$D:$D,MATCH($A24,Proyectos!$C:$C,0))&"","") | E24: =IFERROR(INDEX(Proyectos!$E:$E,MATCH($A24,Proyectos!$C:$C,0))&"","") | F24: =IFERROR(INDEX(Proyectos!$F:$F,MATCH($A24,Proyectos!$C:$C,0))&"","") | G24: =IFERROR(INDEX(Proyectos!$G:$G,MATCH($A24,Proyectos!$C:$C,0))&"","") | H24: =IFERROR(INDEX(Proyectos!$K:$K,MATCH($A24,Proyectos!$C:$C,0))&"","") | I24: =IFERROR(INDEX(Proyectos!$L:$L,MATCH($A24,Proyectos!$C:$C,0))&"","") | J24: =IFERROR(INDEX(Proyectos!$P:$P,MATCH($A24,Proyectos!$C:$C,0))&"","") | K24: =IFERROR(INDEX(Proyectos!$Q:$Q,MATCH($A24,Proyectos!$C:$C,0))&"","") | L24: =IFERROR(INDEX(Proyectos!$V:$V,MATCH($A24,Proyectos!$C:$C,0))&"","") | M24: =IFERROR(IF(INDEX(Proyectos!$W:$W,MATCH($A24,Proyectos!$C:$C,0))="","",INDEX(Proyectos!$W:$W,MATCH($A24,Proyectos!$C:$C,0))),"") | N24: =IFERROR(INDEX(Proyectos!$X:$X,MATCH($A24,Proyectos!$C:$C,0)),"") | O24: =IFERROR(INDEX(Proyectos!$Y:$Y,MATCH($A24,Proyectos!$C:$C,0))&"","")
B25: =IFERROR(IF(INDEX(Proyectos!$A:$A,MATCH($A25,Proyectos!$C:$C,0))="","",INDEX(Proyectos!$A:$A,MATCH($A25,Proyectos!$C:$C,0))),"") | C25: =IFERROR(INDEX(Proyectos!$B:$B,MATCH($A25,Proyectos!$C:$C,0))&"","") | D25: =IFERROR(INDEX(Proyectos!$D:$D,MATCH($A25,Proyectos!$C:$C,0))&"","") | E25: =IFERROR(INDEX(Proyectos!$E:$E,MATCH($A25,Proyectos!$C:$C,0))&"","") | F25: =IFERROR(INDEX(Proyectos!$F:$F,MATCH($A25,Proyectos!$C:$C,0))&"","") | G25: =IFERROR(INDEX(Proyectos!$G:$G,MATCH($A25,Proyectos!$C:$C,0))&"","") | H25: =IFERROR(INDEX(Proyectos!$K:$K,MATCH($A25,Proyectos!$C:$C,0))&"","") | I25: =IFERROR(INDEX(Proyectos!$L:$L,MATCH($A25,Proyectos!$C:$C,0))&"","") | J25: =IFERROR(INDEX(Proyectos!$P:$P,MATCH($A25,Proyectos!$C:$C,0))&"","") | K25: =IFERROR(INDEX(Proyectos!$Q:$Q,MATCH($A25,Proyectos!$C:$C,0))&"","") | L25: =IFERROR(INDEX(Proyectos!$V:$V,MATCH($A25,Proyectos!$C:$C,0))&"","") | M25: =IFERROR(IF(INDEX(Proyectos!$W:$W,MATCH($A25,Proyectos!$C:$C,0))="","",INDEX(Proyectos!$W:$W,MATCH($A25,Proyectos!$C:$C,0))),"") | N25: =IFERROR(INDEX(Proyectos!$X:$X,MATCH($A25,Proyectos!$C:$C,0)),"") | O25: =IFERROR(INDEX(Proyectos!$Y:$Y,MATCH($A25,Proyectos!$C:$C,0))&"","")

Sheet Rubit
A1: Proyectos — Rubit
A2: Proyectos con Dev = Rubit, ordenados por código. No incluye clientes cerrados. Si te asignan uno nuevo, escribe el nombre exacto del cliente en la columna A.
A3: SOLO EDITAS LAS 3 ÚLTIMAS COLUMNAS, las amarillas del final (P, Q y R): «Marcar» (lista desplegable), «Nota del dev» y «Fecha». Lo que pongas ahí aparece automáticamente en la hoja PROYECTOS. La columna Cliente queda fija al desplazarte a la derecha. Todo lo demás es gris: se lee solo desde PROYECTOS.
A5: Cliente | B5: Prioridad diseño | C5: Código | D5: Correo del cliente | E5: Tipo | F5: Plataforma | G5: Estado | H5: Grupo | I5: Acción de hoy | J5: Material de diseño | K5: Plantilla productos | L5: Qué falta exactamente | M5: Últ. respuesta | N5: Días sin responder | O5: Notas | P5: Marcar | Q5: Nota del dev | R5: Fecha
A6: Place For Pet | B6: =IFERROR(IF(INDEX(Proyectos!$A:$A,MATCH($A6,Proyectos!$C:$C,0))="","",INDEX(Proyectos!$A:$A,MATCH($A6,Proyectos!$C:$C,0))),"") | C6: =IFERROR(INDEX(Proyectos!$B:$B,MATCH($A6,Proyectos!$C:$C,0))&"","") -> 041 | D6: =IFERROR(INDEX(Proyectos!$D:$D,MATCH($A6,Proyectos!$C:$C,0))&"","") | E6: =IFERROR(INDEX(Proyectos!$E:$E,MATCH($A6,Proyectos!$C:$C,0))&"","") -> E-commerce | F6: =IFERROR(INDEX(Proyectos!$F:$F,MATCH($A6,Proyectos!$C:$C,0))&"","") -> Por definir | G6: =IFERROR(INDEX(Proyectos!$G:$G,MATCH($A6,Proyectos!$C:$C,0))&"","") -> Congelado | H6: =IFERROR(INDEX(Proyectos!$K:$K,MATCH($A6,Proyectos!$C:$C,0))&"","") -> A | I6: =IFERROR(INDEX(Proyectos!$L:$L,MATCH($A6,Proyectos!$C:$C,0))&"","") -> Congelado — mensaje cada 15 días | J6: =IFERROR(INDEX(Proyectos!$P:$P,MATCH($A6,Proyectos!$C:$C,0))&"","") -> Completo | K6: =IFERROR(INDEX(Proyectos!$Q:$Q,MATCH($A6,Proyectos!$C:$C,0))&"","") -> Recibida con errores | L6: =IFERROR(INDEX(Proyectos!$V:$V,MATCH($A6,Proyectos!$C:$C,0))&"","") -> Reunión agendada | M6: =IFERROR(IF(INDEX(Proyectos!$W:$W,MATCH($A6,Proyectos!$C:$C,0))="","",INDEX(Proyectos!$W:$W,MATCH($A6,Proyectos!$C:$C,0))),"") -> 46216 | N6: =IFERROR(INDEX(Proyectos!$X:$X,MATCH($A6,Proyectos!$C:$C,0)),"") -> 21 | O6: =IFERROR(INDEX(Proyectos!$Y:$Y,MATCH($A6,Proyectos!$C:$C,0))&"","") -> Cliente: Natasha Marval y Vanessa Ayvar. Dev histórico: Rubit. - Perseguir material a partir del 5/08
A7: Ale Bakery | B7: =IFERROR(IF(INDEX(Proyectos!$A:$A,MATCH($A7,Proyectos!$C:$C,0))="","",INDEX(Proyectos!$A:$A,MATCH($A7,Proyectos!$C:$C,0))),"") | C7: =IFERROR(INDEX(Proyectos!$B:$B,MATCH($A7,Proyectos!$C:$C,0))&"","") -> 054 | D7: =IFERROR(INDEX(Proyectos!$D:$D,MATCH($A7,Proyectos!$C:$C,0))&"","") | E7: =IFERROR(INDEX(Proyectos!$E:$E,MATCH($A7,Proyectos!$C:$C,0))&"","") -> Informativa | F7: =IFERROR(INDEX(Proyectos!$F:$F,MATCH($A7,Proyectos!$C:$C,0))&"","") -> WooCommerce | G7: =IFERROR(INDEX(Proyectos!$G:$G,MATCH($A7,Proyectos!$C:$C,0))&"","") -> Cerrado | H7: =IFERROR(INDEX(Proyectos!$K:$K,MATCH($A7,Proyectos!$C:$C,0))&"","") -> A | I7: =IFERROR(INDEX(Proyectos!$L:$L,MATCH($A7,Proyectos!$C:$C,0))&"","") -> CONGELAR HOY | J7: =IFERROR(INDEX(Proyectos!$P:$P,MATCH($A7,Proyectos!$C:$C,0))&"","") -> Completo | K7: =IFERROR(INDEX(Proyectos!$Q:$Q,MATCH($A7,Proyectos!$C:$C,0))&"","") -> No aplica | L7: =IFERROR(INDEX(Proyectos!$V:$V,MATCH($A7,Proyectos!$C:$C,0))&"","") -> Fotografías finales del cliente para completar el diseño (30% ya pagado) | M7: =IFERROR(IF(INDEX(Proyectos!$W:$W,MATCH($A7,Proyectos!$C:$C,0))="","",INDEX(Proyectos!$W:$W,MATCH($A7,Proyectos!$C:$C,0))),"") -> 46219 | N7: =IFERROR(INDEX(Proyectos!$X:$X,MATCH($A7,Proyectos!$C:$C,0)),"") -> 18 | O7: =IFERROR(INDEX(Proyectos!$Y:$Y,MATCH($A7,Proyectos!$C:$C,0))&"","") -> Cliente: Alejandro y Alejandra. Dev histórico: Rubit. Cita viernes 24/07 . Finalizado , agendar reunion final 5 dias antes de su ultima cita
A8: Anahir Store | B8: =IFERROR(IF(INDEX(Proyectos!$A:$A,MATCH($A8,Proyectos!$C:$C,0))="","",INDEX(Proyectos!$A:$A,MATCH($A8,Proyectos!$C:$C,0))),"") | C8: =IFERROR(INDEX(Proyectos!$B:$B,MATCH($A8,Proyectos!$C:$C,0))&"","") -> 055 | D8: =IFERROR(INDEX(Proyectos!$D:$D,MATCH($A8,Proyectos!$C:$C,0))&"","") | E8: =IFERROR(INDEX(Proyectos!$E:$E,MATCH($A8,Proyectos!$C:$C,0))&"","") -> E-commerce | F8: =IFERROR(INDEX(Proyectos!$F:$F,MATCH($A8,Proyectos!$C:$C,0))&"","") -> Por definir | G8: =IFERROR(INDEX(Proyectos!$G:$G,MATCH($A8,Proyectos!$C:$C,0))&"","") -> Diseño | H8: =IFERROR(INDEX(Proyectos!$K:$K,MATCH($A8,Proyectos!$C:$C,0))&"","") -> B | I8: =IFERROR(INDEX(Proyectos!$L:$L,MATCH($A8,Proyectos!$C:$C,0))&"","") -> CONGELAR HOY | J8: =IFERROR(INDEX(Proyectos!$P:$P,MATCH($A8,Proyectos!$C:$C,0))&"","") -> Incompleto | K8: =IFERROR(INDEX(Proyectos!$Q:$Q,MATCH($A8,Proyectos!$C:$C,0))&"","") -> No aplica | L8: =IFERROR(INDEX(Proyectos!$V:$V,MATCH($A8,Proyectos!$C:$C,0))&"","") -> Feedback/aprobación del diseño (30% ya pagado) | M8: =IFERROR(IF(INDEX(Proyectos!$W:$W,MATCH($A8,Proyectos!$C:$C,0))="","",INDEX(Proyectos!$W:$W,MATCH($A8,Proyectos!$C:$C,0))),"") -> 46212 | N8: =IFERROR(INDEX(Proyectos!$X:$X,MATCH($A8,Proyectos!$C:$C,0)),"") -> 25 | O8: =IFERROR(INDEX(Proyectos!$Y:$Y,MATCH($A8,Proyectos!$C:$C,0))&"","") -> Cliente: Norma Gonzales. Dev histórico: Rubit.
A9: Karol Milena Añez | B9: =IFERROR(IF(INDEX(Proyectos!$A:$A,MATCH($A9,Proyectos!$C:$C,0))="","",INDEX(Proyectos!$A:$A,MATCH($A9,Proyectos!$C:$C,0))),"") | C9: =IFERROR(INDEX(Proyectos!$B:$B,MATCH($A9,Proyectos!$C:$C,0))&"","") -> 065b | D9: =IFERROR(INDEX(Proyectos!$D:$D,MATCH($A9,Proyectos!$C:$C,0))&"","") | E9: =IFERROR(INDEX(Proyectos!$E:$E,MATCH($A9,Proyectos!$C:$C,0))&"","") -> E-commerce | F9: =IFERROR(INDEX(Proyectos!$F:$F,MATCH($A9,Proyectos!$C:$C,0))&"","") -> Por definir | G9: =IFERROR(INDEX(Proyectos!$G:$G,MATCH($A9,Proyectos!$C:$C,0))&"","") -> Esperando material | H9: =IFERROR(INDEX(Proyectos!$K:$K,MATCH($A9,Proyectos!$C:$C,0))&"","") -> B | I9: =IFERROR(INDEX(Proyectos!$L:$L,MATCH($A9,Proyectos!$C:$C,0))&"","") -> CONGELAR HOY | J9: =IFERROR(INDEX(Proyectos!$P:$P,MATCH($A9,Proyectos!$C:$C,0))&"","") -> Incompleto | K9: =IFERROR(INDEX(Proyectos!$Q:$Q,MATCH($A9,Proyectos!$C:$C,0))&"","") -> No enviada | L9: =IFERROR(INDEX(Proyectos!$V:$V,MATCH($A9,Proyectos!$C:$C,0))&"","") -> Levantamiento de información y materiales, falta brief formal | M9: =IFERROR(IF(INDEX(Proyectos!$W:$W,MATCH($A9,Proyectos!$C:$C,0))="","",INDEX(Proyectos!$W:$W,MATCH($A9,Proyectos!$C:$C,0))),"") -> 46218 | N9: =IFERROR(INDEX(Proyectos!$X:$X,MATCH($A9,Proyectos!$C:$C,0)),"") -> 19 | O9: =IFERROR(INDEX(Proyectos!$Y:$Y,MATCH($A9,Proyectos!$C:$C,0))&"","") -> Cliente: Karol Añez. Dev histórico: Rubit.
A10: Ric Bian Originals | B10: =IFERROR(IF(INDEX(Proyectos!$A:$A,MATCH($A10,Proyectos!$C:$C,0))="","",INDEX(Proyectos!$A:$A,MATCH($A10,Proyectos!$C:$C,0))),"") | C10: =IFERROR(INDEX(Proyectos!$B:$B,MATCH($A10,Proyectos!$C:$C,0))&"","") -> 067 | D10: =IFERROR(INDEX(Proyectos!$D:$D,MATCH($A10,Proyectos!$C:$C,0))&"","") | E10: =IFERROR(INDEX(Proyectos!$E:$E,MATCH($A10,Proyectos!$C:$C,0))&"","") -> E-commerce | F10: =IFERROR(INDEX(Proyectos!$F:$F,MATCH($A10,Proyectos!$C:$C,0))&"","") -> Por definir | G10: =IFERROR(INDEX(Proyectos!$G:$G,MATCH($A10,Proyectos!$C:$C,0))&"","") -> Diseño | H10: =IFERROR(INDEX(Proyectos!$K:$K,MATCH($A10,Proyectos!$C:$C,0))&"","") -> B | I10: =IFERROR(INDEX(Proyectos!$L:$L,MATCH($A10,Proyectos!$C:$C,0))&"","") -> CONGELAR HOY | J10: =IFERROR(INDEX(Proyectos!$P:$P,MATCH($A10,Proyectos!$C:$C,0))&"","") -> Incompleto | K10: =IFERROR(INDEX(Proyectos!$Q:$Q,MATCH($A10,Proyectos!$C:$C,0))&"","") -> No enviada | L10: =IFERROR(INDEX(Proyectos!$V:$V,MATCH($A10,Proyectos!$C:$C,0))&"","") -> Material de diseño en general | M10: =IFERROR(IF(INDEX(Proyectos!$W:$W,MATCH($A10,Proyectos!$C:$C,0))="","",INDEX(Proyectos!$W:$W,MATCH($A10,Proyectos!$C:$C,0))),"") -> 46218 | N10: =IFERROR(INDEX(Proyectos!$X:$X,MATCH($A10,Proyectos!$C:$C,0)),"") -> 19 | O10: =IFERROR(INDEX(Proyectos!$Y:$Y,MATCH($A10,Proyectos!$C:$C,0))&"","") -> Cliente: Romel. Dev histórico: Rubit.- espera de manual de marca websy , si pudieron algunas de las propuestas de logotipo
A11: Global Peru Renting | B11: =IFERROR(IF(INDEX(Proyectos!$A:$A,MATCH($A11,Proyectos!$C:$C,0))="","",INDEX(Proyectos!$A:$A,MATCH($A11,Proyectos!$C:$C,0))),"") -> 6 | C11: =IFERROR(INDEX(Proyectos!$B:$B,MATCH($A11,Proyectos!$C:$C,0))&"","") -> 069 | D11: =IFERROR(INDEX(Proyectos!$D:$D,MATCH($A11,Proyectos!$C:$C,0))&"","") | E11: =IFERROR(INDEX(Proyectos!$E:$E,MATCH($A11,Proyectos!$C:$C,0))&"","") -> Informativa | F11: =IFERROR(INDEX(Proyectos!$F:$F,MATCH($A11,Proyectos!$C:$C,0))&"","") -> Por definir | G11: =IFERROR(INDEX(Proyectos!$G:$G,MATCH($A11,Proyectos!$C:$C,0))&"","") -> Diseño | H11: =IFERROR(INDEX(Proyectos!$K:$K,MATCH($A11,Proyectos!$C:$C,0))&"","") -> B | I11: =IFERROR(INDEX(Proyectos!$L:$L,MATCH($A11,Proyectos!$C:$C,0))&"","") -> CONGELAR HOY | J11: =IFERROR(INDEX(Proyectos!$P:$P,MATCH($A11,Proyectos!$C:$C,0))&"","") -> Incompleto | K11: =IFERROR(INDEX(Proyectos!$Q:$Q,MATCH($A11,Proyectos!$C:$C,0))&"","") -> No aplica | L11: =IFERROR(INDEX(Proyectos!$V:$V,MATCH($A11,Proyectos!$C:$C,0))&"","") -> Nada — en proceso de diseño | M11: =IFERROR(IF(INDEX(Proyectos!$W:$W,MATCH($A11,Proyectos!$C:$C,0))="","",INDEX(Proyectos!$W:$W,MATCH($A11,Proyectos!$C:$C,0))),"") -> 46218 | N11: =IFERROR(INDEX(Proyectos!$X:$X,MATCH($A11,Proyectos!$C:$C,0)),"") -> 19 | O11: =IFERROR(INDEX(Proyectos!$Y:$Y,MATCH($A11,Proyectos!$C:$C,0))&"","") -> Cliente: Erika Ventura. Dev histórico: Rubit. , que suban sus archivos al drive Marca previa de Juan Carlos (el proyecto salió de su hoja por no estar en grupo A): «avance listo».
A12: Teccons SAC | B12: =IFERROR(IF(INDEX(Proyectos!$A:$A,MATCH($A12,Proyectos!$C:$C,0))="","",INDEX(Proyectos!$A:$A,MATCH($A12,Proyectos!$C:$C,0))),"") -> 5 | C12: =IFERROR(INDEX(Proyectos!$B:$B,MATCH($A12,Proyectos!$C:$C,0))&"","") -> 071 | D12: =IFERROR(INDEX(Proyectos!$D:$D,MATCH($A12,Proyectos!$C:$C,0))&"","") | E12: =IFERROR(INDEX(Proyectos!$E:$E,MATCH($A12,Proyectos!$C:$C,0))&"","") -> Informativa | F12: =IFERROR(INDEX(Proyectos!$F:$F,MATCH($A12,Proyectos!$C:$C,0))&"","") -> Por definir | G12: =IFERROR(INDEX(Proyectos!$G:$G,MATCH($A12,Proyectos!$C:$C,0))&"","") -> Diseño | H12: =IFERROR(INDEX(Proyectos!$K:$K,MATCH($A12,Proyectos!$C:$C,0))&"","") -> A | I12: =IFERROR(INDEX(Proyectos!$L:$L,MATCH($A12,Proyectos!$C:$C,0))&"","") -> CONGELAR HOY | J12: =IFERROR(INDEX(Proyectos!$P:$P,MATCH($A12,Proyectos!$C:$C,0))&"","") -> Completo | K12: =IFERROR(INDEX(Proyectos!$Q:$Q,MATCH($A12,Proyectos!$C:$C,0))&"","") -> No aplica | L12: =IFERROR(INDEX(Proyectos!$V:$V,MATCH($A12,Proyectos!$C:$C,0))&"","") -> Material de diseño (brief y drive ya completados administrativamente) | M12: =IFERROR(IF(INDEX(Proyectos!$W:$W,MATCH($A12,Proyectos!$C:$C,0))="","",INDEX(Proyectos!$W:$W,MATCH($A12,Proyectos!$C:$C,0))),"") -> 46218 | N12: =IFERROR(INDEX(Proyectos!$X:$X,MATCH($A12,Proyectos!$C:$C,0)),"") -> 19 | O12: =IFERROR(INDEX(Proyectos!$Y:$Y,MATCH($A12,Proyectos!$C:$C,0))&"","") -> Cliente: Jhon Cabrera Sánchez. Dev histórico: Rubit.
A13: Hasso Group | B13: =IFERROR(IF(INDEX(Proyectos!$A:$A,MATCH($A13,Proyectos!$C:$C,0))="","",INDEX(Proyectos!$A:$A,MATCH($A13,Proyectos!$C:$C,0))),"") -> 8 | C13: =IFERROR(INDEX(Proyectos!$B:$B,MATCH($A13,Proyectos!$C:$C,0))&"","") -> 073 | D13: =IFERROR(INDEX(Proyectos!$D:$D,MATCH($A13,Proyectos!$C:$C,0))&"","") | E13: =IFERROR(INDEX(Proyectos!$E:$E,MATCH($A13,Proyectos!$C:$C,0))&"","") -> E-commerce | F13: =IFERROR(INDEX(Proyectos!$F:$F,MATCH($A13,Proyectos!$C:$C,0))&"","") -> Por definir | G13: =IFERROR(INDEX(Proyectos!$G:$G,MATCH($A13,Proyectos!$C:$C,0))&"","") -> Diseño | H13: =IFERROR(INDEX(Proyectos!$K:$K,MATCH($A13,Proyectos!$C:$C,0))&"","") -> A | I13: =IFERROR(INDEX(Proyectos!$L:$L,MATCH($A13,Proyectos!$C:$C,0))&"","") -> CONGELAR HOY | J13: =IFERROR(INDEX(Proyectos!$P:$P,MATCH($A13,Proyectos!$C:$C,0))&"","") -> Completo | K13: =IFERROR(INDEX(Proyectos!$Q:$Q,MATCH($A13,Proyectos!$C:$C,0))&"","") -> No enviada | L13: =IFERROR(INDEX(Proyectos!$V:$V,MATCH($A13,Proyectos!$C:$C,0))&"","") -> Materiales y activos del cliente para iniciar estructura de la tienda | M13: =IFERROR(IF(INDEX(Proyectos!$W:$W,MATCH($A13,Proyectos!$C:$C,0))="","",INDEX(Proyectos!$W:$W,MATCH($A13,Proyectos!$C:$C,0))),"") -> 46218 | N13: =IFERROR(INDEX(Proyectos!$X:$X,MATCH($A13,Proyectos!$C:$C,0)),"") -> 19 | O13: =IFERROR(INDEX(Proyectos!$Y:$Y,MATCH($A13,Proyectos!$C:$C,0))&"","") -> Cliente: Sharmely Zanabria Carmona. Dev histórico: Rubit. Enviar materiales logotipos y fotos
A14: Luma Home | B14: =IFERROR(IF(INDEX(Proyectos!$A:$A,MATCH($A14,Proyectos!$C:$C,0))="","",INDEX(Proyectos!$A:$A,MATCH($A14,Proyectos!$C:$C,0))),"") -> 4 | C14: =IFERROR(INDEX(Proyectos!$B:$B,MATCH($A14,Proyectos!$C:$C,0))&"","") -> 075 | D14: =IFERROR(INDEX(Proyectos!$D:$D,MATCH($A14,Proyectos!$C:$C,0))&"","") | E14: =IFERROR(INDEX(Proyectos!$E:$E,MATCH($A14,Proyectos!$C:$C,0))&"","") -> E-commerce | F14: =IFERROR(INDEX(Proyectos!$F:$F,MATCH($A14,Proyectos!$C:$C,0))&"","") -> Por definir | G14: =IFERROR(INDEX(Proyectos!$G:$G,MATCH($A14,Proyectos!$C:$C,0))&"","") -> Diseño | H14: =IFERROR(INDEX(Proyectos!$K:$K,MATCH($A14,Proyectos!$C:$C,0))&"","") -> A | I14: =IFERROR(INDEX(Proyectos!$L:$L,MATCH($A14,Proyectos!$C:$C,0))&"","") -> CONGELAR HOY | J14: =IFERROR(INDEX(Proyectos!$P:$P,MATCH($A14,Proyectos!$C:$C,0))&"","") -> Completo | K14: =IFERROR(INDEX(Proyectos!$Q:$Q,MATCH($A14,Proyectos!$C:$C,0))&"","") -> No enviada | L14: =IFERROR(INDEX(Proyectos!$V:$V,MATCH($A14,Proyectos!$C:$C,0))&"","") -> Material de diseño (brief y drive ya completados administrativamente) | M14: =IFERROR(IF(INDEX(Proyectos!$W:$W,MATCH($A14,Proyectos!$C:$C,0))="","",INDEX(Proyectos!$W:$W,MATCH($A14,Proyectos!$C:$C,0))),"") -> 46218 | N14: =IFERROR(INDEX(Proyectos!$X:$X,MATCH($A14,Proyectos!$C:$C,0)),"") -> 19 | O14: =IFERROR(INDEX(Proyectos!$Y:$Y,MATCH($A14,Proyectos!$C:$C,0))&"","") -> Cliente: Fatima. Dev histórico: Rubit. PENDIENTE: que envíen todo su material al Drive.
A15: Guardiania Total 360 | B15: =IFERROR(IF(INDEX(Proyectos!$A:$A,MATCH($A15,Proyectos!$C:$C,0))="","",INDEX(Proyectos!$A:$A,MATCH($A15,Proyectos!$C:$C,0))),"") | C15: =IFERROR(INDEX(Proyectos!$B:$B,MATCH($A15,Proyectos!$C:$C,0))&"","") -> 078 | D15: =IFERROR(INDEX(Proyectos!$D:$D,MATCH($A15,Proyectos!$C:$C,0))&"","") | E15: =IFERROR(INDEX(Proyectos!$E:$E,MATCH($A15,Proyectos!$C:$C,0))&"","") -> Informativa | F15: =IFERROR(INDEX(Proyectos!$F:$F,MATCH($A15,Proyectos!$C:$C,0))&"","") -> Por definir | G15: =IFERROR(INDEX(Proyectos!$G:$G,MATCH($A15,Proyectos!$C:$C,0))&"","") -> Esperando material | H15: =IFERROR(INDEX(Proyectos!$K:$K,MATCH($A15,Proyectos!$C:$C,0))&"","") -> B | I15: =IFERROR(INDEX(Proyectos!$L:$L,MATCH($A15,Proyectos!$C:$C,0))&"","") -> CONGELAR HOY | J15: =IFERROR(INDEX(Proyectos!$P:$P,MATCH($A15,Proyectos!$C:$C,0))&"","") -> Incompleto | K15: =IFERROR(INDEX(Proyectos!$Q:$Q,MATCH($A15,Proyectos!$C:$C,0))&"","") -> No aplica | L15: =IFERROR(INDEX(Proyectos!$V:$V,MATCH($A15,Proyectos!$C:$C,0))&"","") -> Material de diseño en general | M15: =IFERROR(IF(INDEX(Proyectos!$W:$W,MATCH($A15,Proyectos!$C:$C,0))="","",INDEX(Proyectos!$W:$W,MATCH($A15,Proyectos!$C:$C,0))),"") -> 46218 | N15: =IFERROR(INDEX(Proyectos!$X:$X,MATCH($A15,Proyectos!$C:$C,0)),"") -> 19 | O15: =IFERROR(INDEX(Proyectos!$Y:$Y,MATCH($A15,Proyectos!$C:$C,0))&"","") -> Cliente: Kenny. Dev histórico: Rubit.
B16: =IFERROR(IF(INDEX(Proyectos!$A:$A,MATCH($A16,Proyectos!$C:$C,0))="","",INDEX(Proyectos!$A:$A,MATCH($A16,Proyectos!$C:$C,0))),"") | C16: =IFERROR(INDEX(Proyectos!$B:$B,MATCH($A16,Proyectos!$C:$C,0))&"","") | D16: =IFERROR(INDEX(Proyectos!$D:$D,MATCH($A16,Proyectos!$C:$C,0))&"","") | E16: =IFERROR(INDEX(Proyectos!$E:$E,MATCH($A16,Proyectos!$C:$C,0))&"","") | F16: =IFERROR(INDEX(Proyectos!$F:$F,MATCH($A16,Proyectos!$C:$C,0))&"","") | G16: =IFERROR(INDEX(Proyectos!$G:$G,MATCH($A16,Proyectos!$C:$C,0))&"","") | H16: =IFERROR(INDEX(Proyectos!$K:$K,MATCH($A16,Proyectos!$C:$C,0))&"","") | I16: =IFERROR(INDEX(Proyectos!$L:$L,MATCH($A16,Proyectos!$C:$C,0))&"","") | J16: =IFERROR(INDEX(Proyectos!$P:$P,MATCH($A16,Proyectos!$C:$C,0))&"","") | K16: =IFERROR(INDEX(Proyectos!$Q:$Q,MATCH($A16,Proyectos!$C:$C,0))&"","") | L16: =IFERROR(INDEX(Proyectos!$V:$V,MATCH($A16,Proyectos!$C:$C,0))&"","") | M16: =IFERROR(IF(INDEX(Proyectos!$W:$W,MATCH($A16,Proyectos!$C:$C,0))="","",INDEX(Proyectos!$W:$W,MATCH($A16,Proyectos!$C:$C,0))),"") | N16: =IFERROR(INDEX(Proyectos!$X:$X,MATCH($A16,Proyectos!$C:$C,0)),"") | O16: =IFERROR(INDEX(Proyectos!$Y:$Y,MATCH($A16,Proyectos!$C:$C,0))&"","")
B17: =IFERROR(IF(INDEX(Proyectos!$A:$A,MATCH($A17,Proyectos!$C:$C,0))="","",INDEX(Proyectos!$A:$A,MATCH($A17,Proyectos!$C:$C,0))),"") | C17: =IFERROR(INDEX(Proyectos!$B:$B,MATCH($A17,Proyectos!$C:$C,0))&"","") | D17: =IFERROR(INDEX(Proyectos!$D:$D,MATCH($A17,Proyectos!$C:$C,0))&"","") | E17: =IFERROR(INDEX(Proyectos!$E:$E,MATCH($A17,Proyectos!$C:$C,0))&"","") | F17: =IFERROR(INDEX(Proyectos!$F:$F,MATCH($A17,Proyectos!$C:$C,0))&"","") | G17: =IFERROR(INDEX(Proyectos!$G:$G,MATCH($A17,Proyectos!$C:$C,0))&"","") | H17: =IFERROR(INDEX(Proyectos!$K:$K,MATCH($A17,Proyectos!$C:$C,0))&"","") | I17: =IFERROR(INDEX(Proyectos!$L:$L,MATCH($A17,Proyectos!$C:$C,0))&"","") | J17: =IFERROR(INDEX(Proyectos!$P:$P,MATCH($A17,Proyectos!$C:$C,0))&"","") | K17: =IFERROR(INDEX(Proyectos!$Q:$Q,MATCH($A17,Proyectos!$C:$C,0))&"","") | L17: =IFERROR(INDEX(Proyectos!$V:$V,MATCH($A17,Proyectos!$C:$C,0))&"","") | M17: =IFERROR(IF(INDEX(Proyectos!$W:$W,MATCH($A17,Proyectos!$C:$C,0))="","",INDEX(Proyectos!$W:$W,MATCH($A17,Proyectos!$C:$C,0))),"") | N17: =IFERROR(INDEX(Proyectos!$X:$X,MATCH($A17,Proyectos!$C:$C,0)),"") | O17: =IFERROR(INDEX(Proyectos!$Y:$Y,MATCH($A17,Proyectos!$C:$C,0))&"","")
B18: =IFERROR(IF(INDEX(Proyectos!$A:$A,MATCH($A18,Proyectos!$C:$C,0))="","",INDEX(Proyectos!$A:$A,MATCH($A18,Proyectos!$C:$C,0))),"") | C18: =IFERROR(INDEX(Proyectos!$B:$B,MATCH($A18,Proyectos!$C:$C,0))&"","") | D18: =IFERROR(INDEX(Proyectos!$D:$D,MATCH($A18,Proyectos!$C:$C,0))&"","") | E18: =IFERROR(INDEX(Proyectos!$E:$E,MATCH($A18,Proyectos!$C:$C,0))&"","") | F18: =IFERROR(INDEX(Proyectos!$F:$F,MATCH($A18,Proyectos!$C:$C,0))&"","") | G18: =IFERROR(INDEX(Proyectos!$G:$G,MATCH($A18,Proyectos!$C:$C,0))&"","") | H18: =IFERROR(INDEX(Proyectos!$K:$K,MATCH($A18,Proyectos!$C:$C,0))&"","") | I18: =IFERROR(INDEX(Proyectos!$L:$L,MATCH($A18,Proyectos!$C:$C,0))&"","") | J18: =IFERROR(INDEX(Proyectos!$P:$P,MATCH($A18,Proyectos!$C:$C,0))&"","") | K18: =IFERROR(INDEX(Proyectos!$Q:$Q,MATCH($A18,Proyectos!$C:$C,0))&"","") | L18: =IFERROR(INDEX(Proyectos!$V:$V,MATCH($A18,Proyectos!$C:$C,0))&"","") | M18: =IFERROR(IF(INDEX(Proyectos!$W:$W,MATCH($A18,Proyectos!$C:$C,0))="","",INDEX(Proyectos!$W:$W,MATCH($A18,Proyectos!$C:$C,0))),"") | N18: =IFERROR(INDEX(Proyectos!$X:$X,MATCH($A18,Proyectos!$C:$C,0)),"") | O18: =IFERROR(INDEX(Proyectos!$Y:$Y,MATCH($A18,Proyectos!$C:$C,0))&"","")
B19: =IFERROR(IF(INDEX(Proyectos!$A:$A,MATCH($A19,Proyectos!$C:$C,0))="","",INDEX(Proyectos!$A:$A,MATCH($A19,Proyectos!$C:$C,0))),"") | C19: =IFERROR(INDEX(Proyectos!$B:$B,MATCH($A19,Proyectos!$C:$C,0))&"","") | D19: =IFERROR(INDEX(Proyectos!$D:$D,MATCH($A19,Proyectos!$C:$C,0))&"","") | E19: =IFERROR(INDEX(Proyectos!$E:$E,MATCH($A19,Proyectos!$C:$C,0))&"","") | F19: =IFERROR(INDEX(Proyectos!$F:$F,MATCH($A19,Proyectos!$C:$C,0))&"","") | G19: =IFERROR(INDEX(Proyectos!$G:$G,MATCH($A19,Proyectos!$C:$C,0))&"","") | H19: =IFERROR(INDEX(Proyectos!$K:$K,MATCH($A19,Proyectos!$C:$C,0))&"","") | I19: =IFERROR(INDEX(Proyectos!$L:$L,MATCH($A19,Proyectos!$C:$C,0))&"","") | J19: =IFERROR(INDEX(Proyectos!$P:$P,MATCH($A19,Proyectos!$C:$C,0))&"","") | K19: =IFERROR(INDEX(Proyectos!$Q:$Q,MATCH($A19,Proyectos!$C:$C,0))&"","") | L19: =IFERROR(INDEX(Proyectos!$V:$V,MATCH($A19,Proyectos!$C:$C,0))&"","") | M19: =IFERROR(IF(INDEX(Proyectos!$W:$W,MATCH($A19,Proyectos!$C:$C,0))="","",INDEX(Proyectos!$W:$W,MATCH($A19,Proyectos!$C:$C,0))),"") | N19: =IFERROR(INDEX(Proyectos!$X:$X,MATCH($A19,Proyectos!$C:$C,0)),"") | O19: =IFERROR(INDEX(Proyectos!$Y:$Y,MATCH($A19,Proyectos!$C:$C,0))&"","")
B20: =IFERROR(IF(INDEX(Proyectos!$A:$A,MATCH($A20,Proyectos!$C:$C,0))="","",INDEX(Proyectos!$A:$A,MATCH($A20,Proyectos!$C:$C,0))),"") | C20: =IFERROR(INDEX(Proyectos!$B:$B,MATCH($A20,Proyectos!$C:$C,0))&"","") | D20: =IFERROR(INDEX(Proyectos!$D:$D,MATCH($A20,Proyectos!$C:$C,0))&"","") | E20: =IFERROR(INDEX(Proyectos!$E:$E,MATCH($A20,Proyectos!$C:$C,0))&"","") | F20: =IFERROR(INDEX(Proyectos!$F:$F,MATCH($A20,Proyectos!$C:$C,0))&"","") | G20: =IFERROR(INDEX(Proyectos!$G:$G,MATCH($A20,Proyectos!$C:$C,0))&"","") | H20: =IFERROR(INDEX(Proyectos!$K:$K,MATCH($A20,Proyectos!$C:$C,0))&"","") | I20: =IFERROR(INDEX(Proyectos!$L:$L,MATCH($A20,Proyectos!$C:$C,0))&"","") | J20: =IFERROR(INDEX(Proyectos!$P:$P,MATCH($A20,Proyectos!$C:$C,0))&"","") | K20: =IFERROR(INDEX(Proyectos!$Q:$Q,MATCH($A20,Proyectos!$C:$C,0))&"","") | L20: =IFERROR(INDEX(Proyectos!$V:$V,MATCH($A20,Proyectos!$C:$C,0))&"","") | M20: =IFERROR(IF(INDEX(Proyectos!$W:$W,MATCH($A20,Proyectos!$C:$C,0))="","",INDEX(Proyectos!$W:$W,MATCH($A20,Proyectos!$C:$C,0))),"") | N20: =IFERROR(INDEX(Proyectos!$X:$X,MATCH($A20,Proyectos!$C:$C,0)),"") | O20: =IFERROR(INDEX(Proyectos!$Y:$Y,MATCH($A20,Proyectos!$C:$C,0))&"","")
B21: =IFERROR(IF(INDEX(Proyectos!$A:$A,MATCH($A21,Proyectos!$C:$C,0))="","",INDEX(Proyectos!$A:$A,MATCH($A21,Proyectos!$C:$C,0))),"") | C21: =IFERROR(INDEX(Proyectos!$B:$B,MATCH($A21,Proyectos!$C:$C,0))&"","") | D21: =IFERROR(INDEX(Proyectos!$D:$D,MATCH($A21,Proyectos!$C:$C,0))&"","") | E21: =IFERROR(INDEX(Proyectos!$E:$E,MATCH($A21,Proyectos!$C:$C,0))&"","") | F21: =IFERROR(INDEX(Proyectos!$F:$F,MATCH($A21,Proyectos!$C:$C,0))&"","") | G21: =IFERROR(INDEX(Proyectos!$G:$G,MATCH($A21,Proyectos!$C:$C,0))&"","") | H21: =IFERROR(INDEX(Proyectos!$K:$K,MATCH($A21,Proyectos!$C:$C,0))&"","") | I21: =IFERROR(INDEX(Proyectos!$L:$L,MATCH($A21,Proyectos!$C:$C,0))&"","") | J21: =IFERROR(INDEX(Proyectos!$P:$P,MATCH($A21,Proyectos!$C:$C,0))&"","") | K21: =IFERROR(INDEX(Proyectos!$Q:$Q,MATCH($A21,Proyectos!$C:$C,0))&"","") | L21: =IFERROR(INDEX(Proyectos!$V:$V,MATCH($A21,Proyectos!$C:$C,0))&"","") | M21: =IFERROR(IF(INDEX(Proyectos!$W:$W,MATCH($A21,Proyectos!$C:$C,0))="","",INDEX(Proyectos!$W:$W,MATCH($A21,Proyectos!$C:$C,0))),"") | N21: =IFERROR(INDEX(Proyectos!$X:$X,MATCH($A21,Proyectos!$C:$C,0)),"") | O21: =IFERROR(INDEX(Proyectos!$Y:$Y,MATCH($A21,Proyectos!$C:$C,0))&"","")

Sheet Luis
A1: Proyectos — Luis
A2: Proyectos con Dev = Luis, ordenados por código. No incluye clientes cerrados. Si te asignan uno nuevo, escribe el nombre exacto del cliente en la columna A.
A3: SOLO EDITAS LAS 3 ÚLTIMAS COLUMNAS, las amarillas del final (P, Q y R): «Marcar» (lista desplegable), «Nota del dev» y «Fecha». Lo que pongas ahí aparece automáticamente en la hoja PROYECTOS. La columna Cliente queda fija al desplazarte a la derecha. Todo lo demás es gris: se lee solo desde PROYECTOS.
A5: Cliente | B5: Prioridad diseño | C5: Código | D5: Correo del cliente | E5: Tipo | F5: Plataforma | G5: Estado | H5: Grupo | I5: Acción de hoy | J5: Material de diseño | K5: Plantilla productos | L5: Qué falta exactamente | M5: Últ. respuesta | N5: Días sin responder | O5: Notas | P5: Marcar | Q5: Nota del dev | R5: Fecha
A6: L'Andrea's Secret | B6: =IFERROR(IF(INDEX(Proyectos!$A:$A,MATCH($A6,Proyectos!$C:$C,0))="","",INDEX(Proyectos!$A:$A,MATCH($A6,Proyectos!$C:$C,0))),"") | C6: =IFERROR(INDEX(Proyectos!$B:$B,MATCH($A6,Proyectos!$C:$C,0))&"","") -> 038 | D6: =IFERROR(INDEX(Proyectos!$D:$D,MATCH($A6,Proyectos!$C:$C,0))&"","") | E6: =IFERROR(INDEX(Proyectos!$E:$E,MATCH($A6,Proyectos!$C:$C,0))&"","") -> E-commerce | F6: =IFERROR(INDEX(Proyectos!$F:$F,MATCH($A6,Proyectos!$C:$C,0))&"","") -> Por definir | G6: =IFERROR(INDEX(Proyectos!$G:$G,MATCH($A6,Proyectos!$C:$C,0))&"","") -> Esperando material | H6: =IFERROR(INDEX(Proyectos!$K:$K,MATCH($A6,Proyectos!$C:$C,0))&"","") -> A | I6: =IFERROR(INDEX(Proyectos!$L:$L,MATCH($A6,Proyectos!$C:$C,0))&"","") -> Al día | J6: =IFERROR(INDEX(Proyectos!$P:$P,MATCH($A6,Proyectos!$C:$C,0))&"","") -> Completo | K6: =IFERROR(INDEX(Proyectos!$Q:$Q,MATCH($A6,Proyectos!$C:$C,0))&"","") -> Recibida con errores | L6: =IFERROR(INDEX(Proyectos!$V:$V,MATCH($A6,Proyectos!$C:$C,0))&"","") -> Material de diseño — brief llenado | M6: =IFERROR(IF(INDEX(Proyectos!$W:$W,MATCH($A6,Proyectos!$C:$C,0))="","",INDEX(Proyectos!$W:$W,MATCH($A6,Proyectos!$C:$C,0))),"") | N6: =IFERROR(INDEX(Proyectos!$X:$X,MATCH($A6,Proyectos!$C:$C,0)),"") | O6: =IFERROR(INDEX(Proyectos!$Y:$Y,MATCH($A6,Proyectos!$C:$C,0))&"","") -> Cliente: Gladys Poma. Dev histórico: Luis. 30% ya pagado según pizarra.
A7: Grúas Sagitario | B7: =IFERROR(IF(INDEX(Proyectos!$A:$A,MATCH($A7,Proyectos!$C:$C,0))="","",INDEX(Proyectos!$A:$A,MATCH($A7,Proyectos!$C:$C,0))),"") | C7: =IFERROR(INDEX(Proyectos!$B:$B,MATCH($A7,Proyectos!$C:$C,0))&"","") -> 057 | D7: =IFERROR(INDEX(Proyectos!$D:$D,MATCH($A7,Proyectos!$C:$C,0))&"","") | E7: =IFERROR(INDEX(Proyectos!$E:$E,MATCH($A7,Proyectos!$C:$C,0))&"","") -> Informativa | F7: =IFERROR(INDEX(Proyectos!$F:$F,MATCH($A7,Proyectos!$C:$C,0))&"","") -> Por definir | G7: =IFERROR(INDEX(Proyectos!$G:$G,MATCH($A7,Proyectos!$C:$C,0))&"","") -> Diseño | H7: =IFERROR(INDEX(Proyectos!$K:$K,MATCH($A7,Proyectos!$C:$C,0))&"","") -> B | I7: =IFERROR(INDEX(Proyectos!$L:$L,MATCH($A7,Proyectos!$C:$C,0))&"","") -> CONGELAR HOY | J7: =IFERROR(INDEX(Proyectos!$P:$P,MATCH($A7,Proyectos!$C:$C,0))&"","") -> Incompleto | K7: =IFERROR(INDEX(Proyectos!$Q:$Q,MATCH($A7,Proyectos!$C:$C,0))&"","") -> No aplica | L7: =IFERROR(INDEX(Proyectos!$V:$V,MATCH($A7,Proyectos!$C:$C,0))&"","") -> Aprobación del diseño por parte del cliente | M7: =IFERROR(IF(INDEX(Proyectos!$W:$W,MATCH($A7,Proyectos!$C:$C,0))="","",INDEX(Proyectos!$W:$W,MATCH($A7,Proyectos!$C:$C,0))),"") -> 46218 | N7: =IFERROR(INDEX(Proyectos!$X:$X,MATCH($A7,Proyectos!$C:$C,0)),"") -> 19 | O7: =IFERROR(INDEX(Proyectos!$Y:$Y,MATCH($A7,Proyectos!$C:$C,0))&"","") -> Cliente: J Pino.
A8: Editora Desarrollo Humano | B8: =IFERROR(IF(INDEX(Proyectos!$A:$A,MATCH($A8,Proyectos!$C:$C,0))="","",INDEX(Proyectos!$A:$A,MATCH($A8,Proyectos!$C:$C,0))),"") | C8: =IFERROR(INDEX(Proyectos!$B:$B,MATCH($A8,Proyectos!$C:$C,0))&"","") -> 077 | D8: =IFERROR(INDEX(Proyectos!$D:$D,MATCH($A8,Proyectos!$C:$C,0))&"","") | E8: =IFERROR(INDEX(Proyectos!$E:$E,MATCH($A8,Proyectos!$C:$C,0))&"","") -> Informativa | F8: =IFERROR(INDEX(Proyectos!$F:$F,MATCH($A8,Proyectos!$C:$C,0))&"","") -> Por definir | G8: =IFERROR(INDEX(Proyectos!$G:$G,MATCH($A8,Proyectos!$C:$C,0))&"","") -> Desarrollo | H8: =IFERROR(INDEX(Proyectos!$K:$K,MATCH($A8,Proyectos!$C:$C,0))&"","") -> C | I8: =IFERROR(INDEX(Proyectos!$L:$L,MATCH($A8,Proyectos!$C:$C,0))&"","") -> CONGELAR HOY | J8: =IFERROR(INDEX(Proyectos!$P:$P,MATCH($A8,Proyectos!$C:$C,0))&"","") -> Incompleto | K8: =IFERROR(INDEX(Proyectos!$Q:$Q,MATCH($A8,Proyectos!$C:$C,0))&"","") -> No aplica | L8: =IFERROR(INDEX(Proyectos!$V:$V,MATCH($A8,Proyectos!$C:$C,0))&"","") -> Material de diseño / contenidos (proyecto de branding + intranet + LMS) | M8: =IFERROR(IF(INDEX(Proyectos!$W:$W,MATCH($A8,Proyectos!$C:$C,0))="","",INDEX(Proyectos!$W:$W,MATCH($A8,Proyectos!$C:$C,0))),"") -> 46218 | N8: =IFERROR(INDEX(Proyectos!$X:$X,MATCH($A8,Proyectos!$C:$C,0)),"") -> 19 | O8: =IFERROR(INDEX(Proyectos!$Y:$Y,MATCH($A8,Proyectos!$C:$C,0))&"","") -> Cliente: Maria Gracia. Luis mencionado como responsable — capacidad 0 según Reglas, confirmar quién lo lleva en la práctica.
B9: =IFERROR(IF(INDEX(Proyectos!$A:$A,MATCH($A9,Proyectos!$C:$C,0))="","",INDEX(Proyectos!$A:$A,MATCH($A9,Proyectos!$C:$C,0))),"") | C9: =IFERROR(INDEX(Proyectos!$B:$B,MATCH($A9,Proyectos!$C:$C,0))&"","") | D9: =IFERROR(INDEX(Proyectos!$D:$D,MATCH($A9,Proyectos!$C:$C,0))&"","") | E9: =IFERROR(INDEX(Proyectos!$E:$E,MATCH($A9,Proyectos!$C:$C,0))&"","") | F9: =IFERROR(INDEX(Proyectos!$F:$F,MATCH($A9,Proyectos!$C:$C,0))&"","") | G9: =IFERROR(INDEX(Proyectos!$G:$G,MATCH($A9,Proyectos!$C:$C,0))&"","") | H9: =IFERROR(INDEX(Proyectos!$K:$K,MATCH($A9,Proyectos!$C:$C,0))&"","") | I9: =IFERROR(INDEX(Proyectos!$L:$L,MATCH($A9,Proyectos!$C:$C,0))&"","") | J9: =IFERROR(INDEX(Proyectos!$P:$P,MATCH($A9,Proyectos!$C:$C,0))&"","") | K9: =IFERROR(INDEX(Proyectos!$Q:$Q,MATCH($A9,Proyectos!$C:$C,0))&"","") | L9: =IFERROR(INDEX(Proyectos!$V:$V,MATCH($A9,Proyectos!$C:$C,0))&"","") | M9: =IFERROR(IF(INDEX(Proyectos!$W:$W,MATCH($A9,Proyectos!$C:$C,0))="","",INDEX(Proyectos!$W:$W,MATCH($A9,Proyectos!$C:$C,0))),"") | N9: =IFERROR(INDEX(Proyectos!$X:$X,MATCH($A9,Proyectos!$C:$C,0)),"") | O9: =IFERROR(INDEX(Proyectos!$Y:$Y,MATCH($A9,Proyectos!$C:$C,0))&"","")
B10: =IFERROR(IF(INDEX(Proyectos!$A:$A,MATCH($A10,Proyectos!$C:$C,0))="","",INDEX(Proyectos!$A:$A,MATCH($A10,Proyectos!$C:$C,0))),"") | C10: =IFERROR(INDEX(Proyectos!$B:$B,MATCH($A10,Proyectos!$C:$C,0))&"","") | D10: =IFERROR(INDEX(Proyectos!$D:$D,MATCH($A10,Proyectos!$C:$C,0))&"","") | E10: =IFERROR(INDEX(Proyectos!$E:$E,MATCH($A10,Proyectos!$C:$C,0))&"","") | F10: =IFERROR(INDEX(Proyectos!$F:$F,MATCH($A10,Proyectos!$C:$C,0))&"","") | G10: =IFERROR(INDEX(Proyectos!$G:$G,MATCH($A10,Proyectos!$C:$C,0))&"","") | H10: =IFERROR(INDEX(Proyectos!$K:$K,MATCH($A10,Proyectos!$C:$C,0))&"","") | I10: =IFERROR(INDEX(Proyectos!$L:$L,MATCH($A10,Proyectos!$C:$C,0))&"","") | J10: =IFERROR(INDEX(Proyectos!$P:$P,MATCH($A10,Proyectos!$C:$C,0))&"","") | K10: =IFERROR(INDEX(Proyectos!$Q:$Q,MATCH($A10,Proyectos!$C:$C,0))&"","") | L10: =IFERROR(INDEX(Proyectos!$V:$V,MATCH($A10,Proyectos!$C:$C,0))&"","") | M10: =IFERROR(IF(INDEX(Proyectos!$W:$W,MATCH($A10,Proyectos!$C:$C,0))="","",INDEX(Proyectos!$W:$W,MATCH($A10,Proyectos!$C:$C,0))),"") | N10: =IFERROR(INDEX(Proyectos!$X:$X,MATCH($A10,Proyectos!$C:$C,0)),"") | O10: =IFERROR(INDEX(Proyectos!$Y:$Y,MATCH($A10,Proyectos!$C:$C,0))&"","")
B11: =IFERROR(IF(INDEX(Proyectos!$A:$A,MATCH($A11,Proyectos!$C:$C,0))="","",INDEX(Proyectos!$A:$A,MATCH($A11,Proyectos!$C:$C,0))),"") | C11: =IFERROR(INDEX(Proyectos!$B:$B,MATCH($A11,Proyectos!$C:$C,0))&"","") | D11: =IFERROR(INDEX(Proyectos!$D:$D,MATCH($A11,Proyectos!$C:$C,0))&"","") | E11: =IFERROR(INDEX(Proyectos!$E:$E,MATCH($A11,Proyectos!$C:$C,0))&"","") | F11: =IFERROR(INDEX(Proyectos!$F:$F,MATCH($A11,Proyectos!$C:$C,0))&"","") | G11: =IFERROR(INDEX(Proyectos!$G:$G,MATCH($A11,Proyectos!$C:$C,0))&"","") | H11: =IFERROR(INDEX(Proyectos!$K:$K,MATCH($A11,Proyectos!$C:$C,0))&"","") | I11: =IFERROR(INDEX(Proyectos!$L:$L,MATCH($A11,Proyectos!$C:$C,0))&"","") | J11: =IFERROR(INDEX(Proyectos!$P:$P,MATCH($A11,Proyectos!$C:$C,0))&"","") | K11: =IFERROR(INDEX(Proyectos!$Q:$Q,MATCH($A11,Proyectos!$C:$C,0))&"","") | L11: =IFERROR(INDEX(Proyectos!$V:$V,MATCH($A11,Proyectos!$C:$C,0))&"","") | M11: =IFERROR(IF(INDEX(Proyectos!$W:$W,MATCH($A11,Proyectos!$C:$C,0))="","",INDEX(Proyectos!$W:$W,MATCH($A11,Proyectos!$C:$C,0))),"") | N11: =IFERROR(INDEX(Proyectos!$X:$X,MATCH($A11,Proyectos!$C:$C,0)),"") | O11: =IFERROR(INDEX(Proyectos!$Y:$Y,MATCH($A11,Proyectos!$C:$C,0))&"","")
B12: =IFERROR(IF(INDEX(Proyectos!$A:$A,MATCH($A12,Proyectos!$C:$C,0))="","",INDEX(Proyectos!$A:$A,MATCH($A12,Proyectos!$C:$C,0))),"") | C12: =IFERROR(INDEX(Proyectos!$B:$B,MATCH($A12,Proyectos!$C:$C,0))&"","") | D12: =IFERROR(INDEX(Proyectos!$D:$D,MATCH($A12,Proyectos!$C:$C,0))&"","") | E12: =IFERROR(INDEX(Proyectos!$E:$E,MATCH($A12,Proyectos!$C:$C,0))&"","") | F12: =IFERROR(INDEX(Proyectos!$F:$F,MATCH($A12,Proyectos!$C:$C,0))&"","") | G12: =IFERROR(INDEX(Proyectos!$G:$G,MATCH($A12,Proyectos!$C:$C,0))&"","") | H12: =IFERROR(INDEX(Proyectos!$K:$K,MATCH($A12,Proyectos!$C:$C,0))&"","") | I12: =IFERROR(INDEX(Proyectos!$L:$L,MATCH($A12,Proyectos!$C:$C,0))&"","") | J12: =IFERROR(INDEX(Proyectos!$P:$P,MATCH($A12,Proyectos!$C:$C,0))&"","") | K12: =IFERROR(INDEX(Proyectos!$Q:$Q,MATCH($A12,Proyectos!$C:$C,0))&"","") | L12: =IFERROR(INDEX(Proyectos!$V:$V,MATCH($A12,Proyectos!$C:$C,0))&"","") | M12: =IFERROR(IF(INDEX(Proyectos!$W:$W,MATCH($A12,Proyectos!$C:$C,0))="","",INDEX(Proyectos!$W:$W,MATCH($A12,Proyectos!$C:$C,0))),"") | N12: =IFERROR(INDEX(Proyectos!$X:$X,MATCH($A12,Proyectos!$C:$C,0)),"") | O12: =IFERROR(INDEX(Proyectos!$Y:$Y,MATCH($A12,Proyectos!$C:$C,0))&"","")
B13: =IFERROR(IF(INDEX(Proyectos!$A:$A,MATCH($A13,Proyectos!$C:$C,0))="","",INDEX(Proyectos!$A:$A,MATCH($A13,Proyectos!$C:$C,0))),"") | C13: =IFERROR(INDEX(Proyectos!$B:$B,MATCH($A13,Proyectos!$C:$C,0))&"","") | D13: =IFERROR(INDEX(Proyectos!$D:$D,MATCH($A13,Proyectos!$C:$C,0))&"","") | E13: =IFERROR(INDEX(Proyectos!$E:$E,MATCH($A13,Proyectos!$C:$C,0))&"","") | F13: =IFERROR(INDEX(Proyectos!$F:$F,MATCH($A13,Proyectos!$C:$C,0))&"","") | G13: =IFERROR(INDEX(Proyectos!$G:$G,MATCH($A13,Proyectos!$C:$C,0))&"","") | H13: =IFERROR(INDEX(Proyectos!$K:$K,MATCH($A13,Proyectos!$C:$C,0))&"","") | I13: =IFERROR(INDEX(Proyectos!$L:$L,MATCH($A13,Proyectos!$C:$C,0))&"","") | J13: =IFERROR(INDEX(Proyectos!$P:$P,MATCH($A13,Proyectos!$C:$C,0))&"","") | K13: =IFERROR(INDEX(Proyectos!$Q:$Q,MATCH($A13,Proyectos!$C:$C,0))&"","") | L13: =IFERROR(INDEX(Proyectos!$V:$V,MATCH($A13,Proyectos!$C:$C,0))&"","") | M13: =IFERROR(IF(INDEX(Proyectos!$W:$W,MATCH($A13,Proyectos!$C:$C,0))="","",INDEX(Proyectos!$W:$W,MATCH($A13,Proyectos!$C:$C,0))),"") | N13: =IFERROR(INDEX(Proyectos!$X:$X,MATCH($A13,Proyectos!$C:$C,0)),"") | O13: =IFERROR(INDEX(Proyectos!$Y:$Y,MATCH($A13,Proyectos!$C:$C,0))&"","")
B14: =IFERROR(IF(INDEX(Proyectos!$A:$A,MATCH($A14,Proyectos!$C:$C,0))="","",INDEX(Proyectos!$A:$A,MATCH($A14,Proyectos!$C:$C,0))),"") | C14: =IFERROR(INDEX(Proyectos!$B:$B,MATCH($A14,Proyectos!$C:$C,0))&"","") | D14: =IFERROR(INDEX(Proyectos!$D:$D,MATCH($A14,Proyectos!$C:$C,0))&"","") | E14: =IFERROR(INDEX(Proyectos!$E:$E,MATCH($A14,Proyectos!$C:$C,0))&"","") | F14: =IFERROR(INDEX(Proyectos!$F:$F,MATCH($A14,Proyectos!$C:$C,0))&"","") | G14: =IFERROR(INDEX(Proyectos!$G:$G,MATCH($A14,Proyectos!$C:$C,0))&"","") | H14: =IFERROR(INDEX(Proyectos!$K:$K,MATCH($A14,Proyectos!$C:$C,0))&"","") | I14: =IFERROR(INDEX(Proyectos!$L:$L,MATCH($A14,Proyectos!$C:$C,0))&"","") | J14: =IFERROR(INDEX(Proyectos!$P:$P,MATCH($A14,Proyectos!$C:$C,0))&"","") | K14: =IFERROR(INDEX(Proyectos!$Q:$Q,MATCH($A14,Proyectos!$C:$C,0))&"","") | L14: =IFERROR(INDEX(Proyectos!$V:$V,MATCH($A14,Proyectos!$C:$C,0))&"","") | M14: =IFERROR(IF(INDEX(Proyectos!$W:$W,MATCH($A14,Proyectos!$C:$C,0))="","",INDEX(Proyectos!$W:$W,MATCH($A14,Proyectos!$C:$C,0))),"") | N14: =IFERROR(INDEX(Proyectos!$X:$X,MATCH($A14,Proyectos!$C:$C,0)),"") | O14: =IFERROR(INDEX(Proyectos!$Y:$Y,MATCH($A14,Proyectos!$C:$C,0))&"","")

Sheet Checklists
B2: Checklists de material
B3: Un proyecto no pasa la compuerta hasta que TODO está marcado. Sin excepciones.
B5: Compuerta 1 — Material de diseño
B6: Bloquea la entrada a DISEÑO. Este es duro: sin esto Juan Carlos no puede empezar y no se negocia.
C7: Qué se pide | D7: Cómo sabes que está bien
B8: ☐ | C8: Logo en vectores (.ai, .svg o .eps) | D8: Un JPG del logo NO sirve. Si no lo tiene, avísale a Luis: es trabajo extra.
B9: ☐ | C9: Paleta de colores o manual de marca | D9: Si no tiene, que diga al menos 2 colores. No dejar que Juan Carlos invente sin confirmar.
B10: ☐ | C10: Fotos para banners y secciones | D10: Mínimo 5, horizontales, más de 1500 px de ancho. Nada bajado de Google.
B11: ☐ | C11: Textos de la web | D11: Quién es la empresa, qué vende, contacto. En un documento, no en mensajes sueltos.
B12: ☐ | C12: 2 o 3 webs de referencia que le gusten | D12: Con link. «Algo moderno» no es una referencia.
B13: ☐ | C13: Solo informativas: fotos de cada servicio | D13: Una foto por servicio, mínimo. Reemplaza a las fotos de producto.
B15: Compuerta 2 — Acta de aprobación de diseño
B16: Bloquea la entrada a DESARROLLO. Sin esto el cliente pide cambios después y nos come el proyecto.
C17: Qué se pide | D17: Cómo sabes que está bien
B18: ☐ | C18: Acta de aprobación firmada | D18: Correo o PDF donde el cliente dice que aprueba el diseño. Guárdalo en su carpeta.
B19: ☐ | C19: Pago del 30% confirmado | D19: Confirmado en el banco, no «ya te transferí».
B20: ☐ | C20: Le explicaste que ya no hay cambios | D20: Escrito, en el mismo correo del acta. Que quede constancia.
B22: Compuerta 3 — Material de productos
B23: Bloquea la CARGA, no el desarrollo. El dev puede construir toda la web sin un solo producto real.
C24: Qué se pide | D24: Cómo sabes que está bien
B25: ☐ | C25: Lote piloto: 20 a 30 productos primero | D25: Nunca pidas el catálogo completo de entrada. Con 20 filas se detecta si la plantilla está mal.
B26: ☐ | C26: Plantilla llena sin cambiar las cabeceras | D26: Si movió o renombró columnas, se devuelve. No lo arregles tú.
B27: ☐ | C27: SKU único en cada fila | D27: Ordena la columna y busca repetidos. Un SKU repetido rompe la importación entera.
B28: ☐ | C28: Precio y stock en todas las filas | D28: Celdas vacías = productos que no se publican.
B29: ☐ | C29: Fotos nombradas con el SKU (SKU.jpg) | D29: Si las fotos se llaman IMG_2043.jpg, se devuelven. Esto le ahorra días al dev.
B30: ☐ | C30: Cada fila de la plantilla tiene su foto | D30: Cuenta filas y cuenta archivos. Si no coinciden, se devuelve.
B31: ☐ | C31: Fotos de más de 1000 px, fondo parejo | D31: Fotos de WhatsApp comprimidas se ven mal en la tienda.

Sheet Reglas
B2: Reglas del tablero
B3: Estas reglas las haces cumplir tú. Ningún archivo lo va a hacer por ti.
B5: Se jala, no se empuja | C5: Nadie reparte trabajo hacia adelante. Cuando un dev cierra un proyecto, él avisa que tiene espacio y recién ahí le entregas la siguiente tarjeta del Grupo A.
B6: Columna llena, columna cerrada | C6: Diseño aguanta 2. Cada dev aguanta 2 en desarrollo. Cuando está lleno no se mete un tercero: se ayuda a sacar los que ya están adentro. Diez proyectos al 30% no facturan; dos al 100% sí.
B7: Las compuertas no se negocian | C7: Sin material de diseño completo no hay diseño. Sin acta firmada y 30% pagado no hay desarrollo. Sin plantilla validada no hay carga. Tú eres quien dice que no.
B8: Esperar al cliente no ocupa espacio | C8: Un catálogo de 2000 productos no puede tener a un dev bloqueado un mes. Cuando la web está lista y solo falta catálogo, la tarjeta pasa a «Esperando catálogo» y ese dev queda libre para tomar otro proyecto.
B9: Avanza el que entrega | C9: El orden de la cola no lo decide la antigüedad ni quién reclama más fuerte. Lo decide quién entregó su material. Esto además educa a los clientes solo.
B10: Regla de los 15 días | C10: Cliente que lleva 15 días sin entregar lo que se le pidió pasa a Congelado, pierde su lugar en la fila y vuelve al final cuando entregue. Se le avisa por escrito el día 10.
B11: Regla de los 30 días de catálogo | C11: Si a los 30 días el cliente no completó su catálogo, se publica la web con lo que haya cargado y se le entrega. Lo que falte lo sube él: para eso tiene su capacitación.
B12: Qué se le escala a Luis | C12: Solo tres cosas: cliente que amenaza con cancelar, cliente que pide devolución de dinero, o una decisión técnica que ningún dev sabe resolver. Todo lo demás lo resuelves con Aarón y Rubit. Luis está fuera de la operación diaria por tres meses.
B14: Rutina de Julio
B15: Cada mañana — 15 min | C15: Abre PROYECTOS, ordena por «Acción de hoy» y trabaja de arriba hacia abajo. Manda los mensajes de seguimiento y actualiza «Últ. respuesta» de todos los que respondieron.
B16: Cada vez que llega material | C16: Revísalo TÚ contra el checklist antes de pasarlo. Si falta algo, se devuelve completo con la lista de lo que falta — no en pedacitos.
B17: Cuando un dev queda libre | C17: Mira la hoja TABLERO, confirma que no pasa el límite de 2, y entrégale el primer Grupo A de la cola.
B18: Viernes — 20 min | C18: Captura la hoja TABLERO y mándasela a Luis con una línea por cada proyecto trabado.
